Workbook

Sheet README
A1: GoodBelly - Decision Sciences II - Excel Analysis Workbook
A3: Purpose | B3: Reproducible Excel analysis supporting GoodBelly_Final_Report. Every regression is run with LINEST on the Analysis Data sheet; p-values, CIs, diagnostics, VIFs and influence measures are Excel formulas.
A4: Source data | B4: "Real Data" sheet of Case_Study_Dataset.xlsx copied unchanged to Raw Data (1386 rows). The Explanation sheet (variable dictionary) is not used for numbers. No answer/solution sheets exist in the supplied workbook; none were used.
A5: Colour code | B5: Blue font = input/typed value; black = formula/calculation; yellow fill, bold = key output.
A6: Sheet order | B6: Raw Data -> Analysis Data (renamed variables, EndRep, model blocks) -> Data Audit -> Descriptive Stats -> Correlations -> Baseline Models -> Full MLR -> Variable Selection -> Interaction Analysis -> Final Model -> Demo Analysis -> Endcap Analysis -> Residual Diagnostics -> VIF -> Outliers -> Influence -> Model Comparison -> Excel vs JASP -> Final Results.
A7: Derived variables | B7: Variable -> Formula -> Reason: EndRep -> Endcap × Sales Rep (=Endcap*Rep, Analysis Data col L) -> tests whether the Endcap effect depends on regional-rep presence. All other variables are the original columns renamed (Units Sold=Sales, Average Retail Price=Price, Sales Rep=Rep, Demo1-3=D13, Demo4-5=D45, Natural Retailers=Natural, Fitness Centers=Fitness).
A8: Dummy coding | B8: Rep, Endcap, Demo, D13, D45 are 0/1 as supplied; reference category = 0 for each. Intercept = predicted sales with all dummies 0 and Price = 0.
A9: Items computed outside Excel | B9: Stepwise logs (Variable Selection), other interaction candidates, sensitivity re-fits (region/week/store dummies, outlier exclusion), cluster-robust SEs and the Python reference column are static values from analysis.py (statsmodels), labelled "static". Everything else is formula-driven.
A10: JASP | B10: NOT RUN. See Excel vs JASP sheet. A JASP-ready dataset and model specification are supplied separately.
A11: Data discrepancy | B11: Case text: 10 weeks. Dataset: 11 weekly dates (4 May-13 Jul 2010) x 126 stores = 1,386 rows. The dataset was used as supplied. Region "NA" is a real code, not missing.
A12: Recalculation | B12: Open in Excel; formulas recalculate automatically. LINEST/MMULT/MINVERSE cells are array formulas - do not edit partially.

Sheet Raw Data
A1: Date | B1: Region | C1: Store | D1: Units Sold | E1: Average Retail Price | F1: Sales Rep | G1: Endcap | H1: Demo | I1: Demo1-3 | J1: Demo4-5 | K1: Natural | L1: Fitness
A2: 40302 | B2: FL | C2: Biscayne (aka Aventura) | D2: 150.70209 | E2: 4.39 | F2: 0 | G2: 0 | H2: 0 | I2: 0 | J2: 0 | K2: 1 | L2: 0
A3: 40309 | B3: FL | C3: Biscayne (aka Aventura) | D3: 197.4038 | E3: 3.9976923 | F3: 0 | G3: 0 | H3: 0 | I3: 0 | J3: 0 | K3: 1 | L3: 0
A4: 40316 | B4: FL | C4: Biscayne (aka Aventura) | D4: 235.10617 | E4: 3.8092308 | F4: 0 | G4: 0 | H4: 0 | I4: 0 | J4: 0 | K4: 1 | L4: 0
A5: 40323 | B5: FL | C5: Biscayne (aka Aventura) | D5: 226.69243 | E5: 3.835 | F5: 0 | G5: 0 | H5: 0 | I5: 0 | J5: 0 | K5: 1 | L5: 0
A6: 40330 | B6: FL | C6: Biscayne (aka Aventura) | D6: 257.68815 | E6: 3.9025 | F6: 0 | G6: 0 | H6: 0 | I6: 0 | J6: 0 | K6: 1 | L6: 0
A7: 40337 | B7: FL | C7: Biscayne (aka Aventura) | D7: 132.95719 | E7: 4.4976923 | F7: 0 | G7: 0 | H7: 0 | I7: 0 | J7: 0 | K7: 1 | L7: 0
A8: 40344 | B8: FL | C8: Biscayne (aka Aventura) | D8: 221.88997 | E8: 4.1166667 | F8: 0 | G8: 0 | H8: 0 | I8: 0 | J8: 0 | K8: 1 | L8: 0
A9: 40351 | B9: FL | C9: Biscayne (aka Aventura) | D9: 245.88136 | E9: 4.1166667 | F9: 0 | G9: 0 | H9: 0 | I9: 0 | J9: 0 | K9: 1 | L9: 0
A10: 40358 | B10: FL | C10: Biscayne (aka Aventura) | D10: 156.10253 | E10: 4.1166667 | F10: 0 | G10: 0 | H10: 0 | I10: 0 | J10: 0 | K10: 4 | L10: 0
A11: 40365 | B11: FL | C11: Biscayne (aka Aventura) | D11: 200.10397 | E11: 3.7473333 | F11: 0 | G11: 0 | H11: 0 | I11: 0 | J11: 0 | K11: 1 | L11: 0
A12: 40372 | B12: FL | C12: Biscayne (aka Aventura) | D12: 128.396 | E12: 4.0125 | F12: 0 | G12: 0 | H12: 0 | I12: 0 | J12: 0 | K12: 1 | L12: 0
A13: 40302 | B13: FL | C13: Boca Raton | D13: 142.77821 | E13: 4.39 | F13: 0 | G13: 0 | H13: 0 | I13: 0 | J13: 0 | K13: 0 | L13: 4
... A1387: 40372 | B1387: SW | C1387: Veterans | D1387: 166.89303 | E1387: 4.19 | F1387: 0 | G1387: 0 | H1387: 0 | I1387: 0 | J1387: 0 | K1387: 0 | L1387: 1

Sheet Analysis Data
A1: Store | B1: Date | C1: Sales | D1: Price | E1: Rep | F1: Endcap | G1: Demo | H1: D13 | I1: D45 | J1: Natural | K1: Fitness | L1: EndRep | N1: const | O1: Price | P1: Rep | Q1: Endcap | R1: Demo | S1: D13 | T1: D45 | U1: EndRep | W1: Price | X1: Rep | Y1: Endcap | Z1: EndRep | AA1: Demo | AC1: Price | AD1: Rep | AE1: Demo | AF1: D13 | AG1: D45 | AH1: EndRep | AJ1: Block guide (all columns are formulas linked to Raw Data):
A2: ='Raw Data'!C2 -> Biscayne (aka Aventura) | B2: ='Raw Data'!A2 -> 40302 | C2: ='Raw Data'!D2 -> 150.70209 | D2: ='Raw Data'!E2 -> 4.39 | E2: ='Raw Data'!F2 -> 0 | F2: ='Raw Data'!G2 -> 0 | G2: ='Raw Data'!H2 -> 0 | H2: ='Raw Data'!I2 -> 0 | I2: ='Raw Data'!J2 -> 0 | J2: ='Raw Data'!K2 -> 1 | K2: ='Raw Data'!L2 -> 0 | L2: =F2*E2 -> 0 | N2: 1 | O2: =D2 -> 4.39 | P2: =E2 -> 0 | Q2: =F2 -> 0 | R2: =G2 -> 0 | S2: =H2 -> 0 | T2: =I2 -> 0 | U2: =L2 -> 0 | W2: =D2 -> 4.39 | X2: =E2 -> 0 | Y2: =F2 -> 0 | Z2: =L2 -> 0 | AA2: =G2 -> 0 | AC2: =D2 -> 4.39 | AD2: =E2 -> 0 | AE2: =G2 -> 0 | AF2: =H2 -> 0 | AG2: =I2 -> 0 | AH2: =L2 -> 0 | AJ2: A:K = analysis variables (renamed). L = Endcap x Sales Rep (=Endcap*Sales Rep).
A3: ='Raw Data'!C3 -> Biscayne (aka Aventura) | B3: ='Raw Data'!A3 -> 40309 | C3: ='Raw Data'!D3 -> 197.4038 | D3: ='Raw Data'!E3 -> 3.9976923 | E3: ='Raw Data'!F3 -> 0 | F3: ='Raw Data'!G3 -> 0 | G3: ='Raw Data'!H3 -> 0 | H3: ='Raw Data'!I3 -> 0 | I3: ='Raw Data'!J3 -> 0 | J3: ='Raw Data'!K3 -> 1 | K3: ='Raw Data'!L3 -> 0 | L3: =F3*E3 -> 0 | N3: 1 | O3: =D3 -> 3.9976923 | P3: =E3 -> 0 | Q3: =F3 -> 0 | R3: =G3 -> 0 | S3: =H3 -> 0 | T3: =I3 -> 0 | U3: =L3 -> 0 | W3: =D3 -> 3.9976923 | X3: =E3 -> 0 | Y3: =F3 -> 0 | Z3: =L3 -> 0 | AA3: =G3 -> 0 | AC3: =D3 -> 3.9976923 | AD3: =E3 -> 0 | AE3: =G3 -> 0 | AF3: =H3 -> 0 | AG3: =I3 -> 0 | AH3: =L3 -> 0 | AJ3: D:K = predictors of Model 1 (Full MLR); D:L adds the interaction (Model 3).
A4: ='Raw Data'!C4 -> Biscayne (aka Aventura) | B4: ='Raw Data'!A4 -> 40316 | C4: ='Raw Data'!D4 -> 235.10617 | D4: ='Raw Data'!E4 -> 3.8092308 | E4: ='Raw Data'!F4 -> 0 | F4: ='Raw Data'!G4 -> 0 | G4: ='Raw Data'!H4 -> 0 | H4: ='Raw Data'!I4 -> 0 | I4: ='Raw Data'!J4 -> 0 | J4: ='Raw Data'!K4 -> 1 | K4: ='Raw Data'!L4 -> 0 | L4: =F4*E4 -> 0 | N4: 1 | O4: =D4 -> 3.8092308 | P4: =E4 -> 0 | Q4: =F4 -> 0 | R4: =G4 -> 0 | S4: =H4 -> 0 | T4: =I4 -> 0 | U4: =L4 -> 0 | W4: =D4 -> 3.8092308 | X4: =E4 -> 0 | Y4: =F4 -> 0 | Z4: =L4 -> 0 | AA4: =G4 -> 0 | AC4: =D4 -> 3.8092308 | AD4: =E4 -> 0 | AE4: =G4 -> 0 | AF4: =H4 -> 0 | AG4: =I4 -> 0 | AH4: =L4 -> 0 | AJ4: N:U = [constant + final-model predictors] used by Final Model, diagnostics, leverage.
A5: ='Raw Data'!C5 -> Biscayne (aka Aventura) | B5: ='Raw Data'!A5 -> 40323 | C5: ='Raw Data'!D5 -> 226.69243 | D5: ='Raw Data'!E5 -> 3.835 | E5: ='Raw Data'!F5 -> 0 | F5: ='Raw Data'!G5 -> 0 | G5: ='Raw Data'!H5 -> 0 | H5: ='Raw Data'!I5 -> 0 | I5: ='Raw Data'!J5 -> 0 | J5: ='Raw Data'!K5 -> 1 | K5: ='Raw Data'!L5 -> 0 | L5: =F5*E5 -> 0 | N5: 1 | O5: =D5 -> 3.835 | P5: =E5 -> 0 | Q5: =F5 -> 0 | R5: =G5 -> 0 | S5: =H5 -> 0 | T5: =I5 -> 0 | U5: =L5 -> 0 | W5: =D5 -> 3.835 | X5: =E5 -> 0 | Y5: =F5 -> 0 | Z5: =L5 -> 0 | AA5: =G5 -> 0 | AC5: =D5 -> 3.835 | AD5: =E5 -> 0 | AE5: =G5 -> 0 | AF5: =H5 -> 0 | AG5: =I5 -> 0 | AH5: =L5 -> 0 | AJ5: W:AA = Price, Rep, Endcap, Endcap x Rep, Demo (restricted model for partial-F tests).
A6: ='Raw Data'!C6 -> Biscayne (aka Aventura) | B6: ='Raw Data'!A6 -> 40330 | C6: ='Raw Data'!D6 -> 257.68815 | D6: ='Raw Data'!E6 -> 3.9025 | E6: ='Raw Data'!F6 -> 0 | F6: ='Raw Data'!G6 -> 0 | G6: ='Raw Data'!H6 -> 0 | H6: ='Raw Data'!I6 -> 0 | I6: ='Raw Data'!J6 -> 0 | J6: ='Raw Data'!K6 -> 1 | K6: ='Raw Data'!L6 -> 0 | L6: =F6*E6 -> 0 | N6: 1 | O6: =D6 -> 3.9025 | P6: =E6 -> 0 | Q6: =F6 -> 0 | R6: =G6 -> 0 | S6: =H6 -> 0 | T6: =I6 -> 0 | U6: =L6 -> 0 | W6: =D6 -> 3.9025 | X6: =E6 -> 0 | Y6: =F6 -> 0 | Z6: =L6 -> 0 | AA6: =G6 -> 0 | AC6: =D6 -> 3.9025 | AD6: =E6 -> 0 | AE6: =G6 -> 0 | AF6: =H6 -> 0 | AG6: =I6 -> 0 | AH6: =L6 -> 0 | AJ6: AC:AH = final model WITHOUT the Endcap main effect (restricted model).
A7: ='Raw Data'!C7 -> Biscayne (aka Aventura) | B7: ='Raw Data'!A7 -> 40337 | C7: ='Raw Data'!D7 -> 132.95719 | D7: ='Raw Data'!E7 -> 4.4976923 | E7: ='Raw Data'!F7 -> 0 | F7: ='Raw Data'!G7 -> 0 | G7: ='Raw Data'!H7 -> 0 | H7: ='Raw Data'!I7 -> 0 | I7: ='Raw Data'!J7 -> 0 | J7: ='Raw Data'!K7 -> 1 | K7: ='Raw Data'!L7 -> 0 | L7: =F7*E7 -> 0 | N7: 1 | O7: =D7 -> 4.4976923 | P7: =E7 -> 0 | Q7: =F7 -> 0 | R7: =G7 -> 0 | S7: =H7 -> 0 | T7: =I7 -> 0 | U7: =L7 -> 0 | W7: =D7 -> 4.4976923 | X7: =E7 -> 0 | Y7: =F7 -> 0 | Z7: =L7 -> 0 | AA7: =G7 -> 0 | AC7: =D7 -> 4.4976923 | AD7: =E7 -> 0 | AE7: =G7 -> 0 | AF7: =H7 -> 0 | AG7: =I7 -> 0 | AH7: =L7 -> 0
A8: ='Raw Data'!C8 -> Biscayne (aka Aventura) | B8: ='Raw Data'!A8 -> 40344 | C8: ='Raw Data'!D8 -> 221.88997 | D8: ='Raw Data'!E8 -> 4.1166667 | E8: ='Raw Data'!F8 -> 0 | F8: ='Raw Data'!G8 -> 0 | G8: ='Raw Data'!H8 -> 0 | H8: ='Raw Data'!I8 -> 0 | I8: ='Raw Data'!J8 -> 0 | J8: ='Raw Data'!K8 -> 1 | K8: ='Raw Data'!L8 -> 0 | L8: =F8*E8 -> 0 | N8: 1 | O8: =D8 -> 4.1166667 | P8: =E8 -> 0 | Q8: =F8 -> 0 | R8: =G8 -> 0 | S8: =H8 -> 0 | T8: =I8 -> 0 | U8: =L8 -> 0 | W8: =D8 -> 4.1166667 | X8: =E8 -> 0 | Y8: =F8 -> 0 | Z8: =L8 -> 0 | AA8: =G8 -> 0 | AC8: =D8 -> 4.1166667 | AD8: =E8 -> 0 | AE8: =G8 -> 0 | AF8: =H8 -> 0 | AG8: =I8 -> 0 | AH8: =L8 -> 0
A9: ='Raw Data'!C9 -> Biscayne (aka Aventura) | B9: ='Raw Data'!A9 -> 40351 | C9: ='Raw Data'!D9 -> 245.88136 | D9: ='Raw Data'!E9 -> 4.1166667 | E9: ='Raw Data'!F9 -> 0 | F9: ='Raw Data'!G9 -> 0 | G9: ='Raw Data'!H9 -> 0 | H9: ='Raw Data'!I9 -> 0 | I9: ='Raw Data'!J9 -> 0 | J9: ='Raw Data'!K9 -> 1 | K9: ='Raw Data'!L9 -> 0 | L9: =F9*E9 -> 0 | N9: 1 | O9: =D9 -> 4.1166667 | P9: =E9 -> 0 | Q9: =F9 -> 0 | R9: =G9 -> 0 | S9: =H9 -> 0 | T9: =I9 -> 0 | U9: =L9 -> 0 | W9: =D9 -> 4.1166667 | X9: =E9 -> 0 | Y9: =F9 -> 0 | Z9: =L9 -> 0 | AA9: =G9 -> 0 | AC9: =D9 -> 4.1166667 | AD9: =E9 -> 0 | AE9: =G9 -> 0 | AF9: =H9 -> 0 | AG9: =I9 -> 0 | AH9: =L9 -> 0
A10: ='Raw Data'!C10 -> Biscayne (aka Aventura) | B10: ='Raw Data'!A10 -> 40358 | C10: ='Raw Data'!D10 -> 156.10253 | D10: ='Raw Data'!E10 -> 4.1166667 | E10: ='Raw Data'!F10 -> 0 | F10: ='Raw Data'!G10 -> 0 | G10: ='Raw Data'!H10 -> 0 | H10: ='Raw Data'!I10 -> 0 | I10: ='Raw Data'!J10 -> 0 | J10: ='Raw Data'!K10 -> 4 | K10: ='Raw Data'!L10 -> 0 | L10: =F10*E10 -> 0 | N10: 1 | O10: =D10 -> 4.1166667 | P10: =E10 -> 0 | Q10: =F10 -> 0 | R10: =G10 -> 0 | S10: =H10 -> 0 | T10: =I10 -> 0 | U10: =L10 -> 0 | W10: =D10 -> 4.1166667 | X10: =E10 -> 0 | Y10: =F10 -> 0 | Z10: =L10 -> 0 | AA10: =G10 -> 0 | AC10: =D10 -> 4.1166667 | AD10: =E10 -> 0 | AE10: =G10 -> 0 | AF10: =H10 -> 0 | AG10: =I10 -> 0 | AH10: =L10 -> 0
A11: ='Raw Data'!C11 -> Biscayne (aka Aventura) | B11: ='Raw Data'!A11 -> 40365 | C11: ='Raw Data'!D11 -> 200.10397 | D11: ='Raw Data'!E11 -> 3.7473333 | E11: ='Raw Data'!F11 -> 0 | F11: ='Raw Data'!G11 -> 0 | G11: ='Raw Data'!H11 -> 0 | H11: ='Raw Data'!I11 -> 0 | I11: ='Raw Data'!J11 -> 0 | J11: ='Raw Data'!K11 -> 1 | K11: ='Raw Data'!L11 -> 0 | L11: =F11*E11 -> 0 | N11: 1 | O11: =D11 -> 3.7473333 | P11: =E11 -> 0 | Q11: =F11 -> 0 | R11: =G11 -> 0 | S11: =H11 -> 0 | T11: =I11 -> 0 | U11: =L11 -> 0 | W11: =D11 -> 3.7473333 | X11: =E11 -> 0 | Y11: =F11 -> 0 | Z11: =L11 -> 0 | AA11: =G11 -> 0 | AC11: =D11 -> 3.7473333 | AD11: =E11 -> 0 | AE11: =G11 -> 0 | AF11: =H11 -> 0 | AG11: =I11 -> 0 | AH11: =L11 -> 0
A12: ='Raw Data'!C12 -> Biscayne (aka Aventura) | B12: ='Raw Data'!A12 -> 40372 | C12: ='Raw Data'!D12 -> 128.396 | D12: ='Raw Data'!E12 -> 4.0125 | E12: ='Raw Data'!F12 -> 0 | F12: ='Raw Data'!G12 -> 0 | G12: ='Raw Data'!H12 -> 0 | H12: ='Raw Data'!I12 -> 0 | I12: ='Raw Data'!J12 -> 0 | J12: ='Raw Data'!K12 -> 1 | K12: ='Raw Data'!L12 -> 0 | L12: =F12*E12 -> 0 | N12: 1 | O12: =D12 -> 4.0125 | P12: =E12 -> 0 | Q12: =F12 -> 0 | R12: =G12 -> 0 | S12: =H12 -> 0 | T12: =I12 -> 0 | U12: =L12 -> 0 | W12: =D12 -> 4.0125 | X12: =E12 -> 0 | Y12: =F12 -> 0 | Z12: =L12 -> 0 | AA12: =G12 -> 0 | AC12: =D12 -> 4.0125 | AD12: =E12 -> 0 | AE12: =G12 -> 0 | AF12: =H12 -> 0 | AG12: =I12 -> 0 | AH12: =L12 -> 0
A13: ='Raw Data'!C13 -> Boca Raton | B13: ='Raw Data'!A13 -> 40302 | C13: ='Raw Data'!D13 -> 142.77821 | D13: ='Raw Data'!E13 -> 4.39 | E13: ='Raw Data'!F13 -> 0 | F13: ='Raw Data'!G13 -> 0 | G13: ='Raw Data'!H13 -> 0 | H13: ='Raw Data'!I13 -> 0 | I13: ='Raw Data'!J13 -> 0 | J13: ='Raw Data'!K13 -> 0 | K13: ='Raw Data'!L13 -> 4 | L13: =F13*E13 -> 0 | N13: 1 | O13: =D13 -> 4.39 | P13: =E13 -> 0 | Q13: =F13 -> 0 | R13: =G13 -> 0 | S13: =H13 -> 0 | T13: =I13 -> 0 | U13: =L13 -> 0 | W13: =D13 -> 4.39 | X13: =E13 -> 0 | Y13: =F13 -> 0 | Z13: =L13 -> 0 | AA13: =G13 -> 0 | AC13: =D13 -> 4.39 | AD13: =E13 -> 0 | AE13: =G13 -> 0 | AF13: =H13 -> 0 | AG13: =I13 -> 0 | AH13: =L13 -> 0
A14: ='Raw Data'!C14 -> Boca Raton | B14: ='Raw Data'!A14 -> 40309 | C14: ='Raw Data'!D14 -> 237.54455 | D14: ='Raw Data'!E14 -> 4.2354545 | E14: ='Raw Data'!F14 -> 0 | F14: ='Raw Data'!G14 -> 0 | G14: ='Raw Data'!H14 -> 0 | H14: ='Raw Data'!I14 -> 0 | I14: ='Raw Data'!J14 -> 0 | J14: ='Raw Data'!K14 -> 0 | K14: ='Raw Data'!L14 -> 4 | L14: =F14*E14 -> 0 | N14: 1 | O14: =D14 -> 4.2354545 | P14: =E14 -> 0 | Q14: =F14 -> 0 | R14: =G14 -> 0 | S14: =H14 -> 0 | T14: =I14 -> 0 | U14: =L14 -> 0 | W14: =D14 -> 4.2354545 | X14: =E14 -> 0 | Y14: =F14 -> 0 | Z14: =L14 -> 0 | AA14: =G14 -> 0 | AC14: =D14 -> 4.2354545 | AD14: =E14 -> 0 | AE14: =G14 -> 0 | AF14: =H14 -> 0 | AG14: =I14 -> 0 | AH14: =L14 -> 0
A15: ='Raw Data'!C15 -> Boca Raton | B15: ='Raw Data'!A15 -> 40316 | C15: ='Raw Data'!D15 -> 141.5333 | D15: ='Raw Data'!E15 -> 3.8092308 | E15: ='Raw Data'!F15 -> 0 | F15: ='Raw Data'!G15 -> 0 | G15: ='Raw Data'!H15 -> 0 | H15: ='Raw Data'!I15 -> 0 | I15: ='Raw Data'!J15 -> 0 | J15: ='Raw Data'!K15 -> 0 | K15: ='Raw Data'!L15 -> 4 | L15: =F15*E15 -> 0 | N15: 1 | O15: =D15 -> 3.8092308 | P15: =E15 -> 0 | Q15: =F15 -> 0 | R15: =G15 -> 0 | S15: =H15 -> 0 | T15: =I15 -> 0 | U15: =L15 -> 0 | W15: =D15 -> 3.8092308 | X15: =E15 -> 0 | Y15: =F15 -> 0 | Z15: =L15 -> 0 | AA15: =G15 -> 0 | AC15: =D15 -> 3.8092308 | AD15: =E15 -> 0 | AE15: =G15 -> 0 | AF15: =H15 -> 0 | AG15: =I15 -> 0 | AH15: =L15 -> 0
A16: ='Raw Data'!C16 -> Boca Raton | B16: ='Raw Data'!A16 -> 40323 | C16: ='Raw Data'!D16 -> 158.07395 | D16: ='Raw Data'!E16 -> 3.8092308 | E16: ='Raw Data'!F16 -> 0 | F16: ='Raw Data'!G16 -> 0 | G16: ='Raw Data'!H16 -> 0 | H16: ='Raw Data'!I16 -> 0 | I16: ='Raw Data'!J16 -> 0 | J16: ='Raw Data'!K16 -> 0 | K16: ='Raw Data'!L16 -> 4 | L16: =F16*E16 -> 0 | N16: 1 | O16: =D16 -> 3.8092308 | P16: =E16 -> 0 | Q16: =F16 -> 0 | R16: =G16 -> 0 | S16: =H16 -> 0 | T16: =I16 -> 0 | U16: =L16 -> 0 | W16: =D16 -> 3.8092308 | X16: =E16 -> 0 | Y16: =F16 -> 0 | Z16: =L16 -> 0 | AA16: =G16 -> 0 | AC16: =D16 -> 3.8092308 | AD16: =E16 -> 0 | AE16: =G16 -> 0 | AF16: =H16 -> 0 | AG16: =I16 -> 0 | AH16: =L16 -> 0
A17: ='Raw Data'!C17 -> Boca Raton | B17: ='Raw Data'!A17 -> 40330 | C17: ='Raw Data'!D17 -> 255.11774 | D17: ='Raw Data'!E17 -> 4.055625 | E17: ='Raw Data'!F17 -> 0 | F17: ='Raw Data'!G17 -> 0 | G17: ='Raw Data'!H17 -> 0 | H17: ='Raw Data'!I17 -> 0 | I17: ='Raw Data'!J17 -> 0 | J17: ='Raw Data'!K17 -> 0 | K17: ='Raw Data'!L17 -> 4 | L17: =F17*E17 -> 0 | N17: 1 | O17: =D17 -> 4.055625 | P17: =E17 -> 0 | Q17: =F17 -> 0 | R17: =G17 -> 0 | S17: =H17 -> 0 | T17: =I17 -> 0 | U17: =L17 -> 0 | W17: =D17 -> 4.055625 | X17: =E17 -> 0 | Y17: =F17 -> 0 | Z17: =L17 -> 0 | AA17: =G17 -> 0 | AC17: =D17 -> 4.055625 | AD17: =E17 -> 0 | AE17: =G17 -> 0 | AF17: =H17 -> 0 | AG17: =I17 -> 0 | AH17: =L17 -> 0
A18: ='Raw Data'!C18 -> Boca Raton | B18: ='Raw Data'!A18 -> 40337 | C18: ='Raw Data'!D18 -> 129.79363 | D18: ='Raw Data'!E18 -> 4.3833333 | E18: ='Raw Data'!F18 -> 0 | F18: ='Raw Data'!G18 -> 0 | G18: ='Raw Data'!H18 -> 0 | H18: ='Raw Data'!I18 -> 0 | I18: ='Raw Data'!J18 -> 0 | J18: ='Raw Data'!K18 -> 0 | K18: ='Raw Data'!L18 -> 4 | L18: =F18*E18 -> 0 | N18: 1 | O18: =D18 -> 4.3833333 | P18: =E18 -> 0 | Q18: =F18 -> 0 | R18: =G18 -> 0 | S18: =H18 -> 0 | T18: =I18 -> 0 | U18: =L18 -> 0 | W18: =D18 -> 4.3833333 | X18: =E18 -> 0 | Y18: =F18 -> 0 | Z18: =L18 -> 0 | AA18: =G18 -> 0 | AC18: =D18 -> 4.3833333 | AD18: =E18 -> 0 | AE18: =G18 -> 0 | AF18: =H18 -> 0 | AG18: =I18 -> 0 | AH18: =L18 -> 0
... A1387: ='Raw Data'!C1387 -> Veterans | B1387: ='Raw Data'!A1387 -> 40372 | C1387: ='Raw Data'!D1387 -> 166.89303 | D1387: ='Raw Data'!E1387 -> 4.19 | E1387: ='Raw Data'!F1387 -> 0 | F1387: ='Raw Data'!G1387 -> 0 | G1387: ='Raw Data'!H1387 -> 0 | H1387: ='Raw Data'!I1387 -> 0 | I1387: ='Raw Data'!J1387 -> 0 | J1387: ='Raw Data'!K1387 -> 0 | K1387: ='Raw Data'!L1387 -> 1 | L1387: =F1387*E1387 -> 0 | N1387: 1 | O1387: =D1387 -> 4.19 | P1387: =E1387 -> 0 | Q1387: =F1387 -> 0 | R1387: =G1387 -> 0 | S1387: =H1387 -> 0 | T1387: =I1387 -> 0 | U1387: =L1387 -> 0 | W1387: =D1387 -> 4.19 | X1387: =E1387 -> 0 | Y1387: =F1387 -> 0 | Z1387: =L1387 -> 0 | AA1387: =G1387 -> 0 | AC1387: =D1387 -> 4.19 | AD1387: =E1387 -> 0 | AE1387: =G1387 -> 0 | AF1387: =H1387 -> 0 | AG1387: =I1387 -> 0 | AH1387: =L1387 -> 0

Sheet Data Audit
A1: DATA AUDIT
A3: Structure checks | B3: Value | C3: Comment
A4: Rows (observations) | B4: =COUNTA('Raw Data'!$C$2:$C$1387) -> 1386 | C4: Matches case: 1,386 store-week observations
A5: Columns | B5: =COUNTA('Raw Data'!$A$1:$L$1) -> 12 | C5: 12 columns in Real Data sheet
A6: Distinct stores | B6: =SUMPRODUCT(1/COUNTIF('Raw Data'!$C$2:$C$1387,'Raw Data'!$C$2:$C$1387)) -> 126 | C6: Matches case: 126 stores
A7: Distinct dates (weeks) | B7: =SUMPRODUCT(1/COUNTIF('Raw Data'!$A$2:$A$1387,'Raw Data'!$A$2:$A$1387)) -> 11 | C7: DISCREPANCY: dataset has 11 weekly dates (4 May - 13 Jul 2010); case Exhibit 1 says 10 weeks. 126 x 11 = 1,386 confirms 11 weeks. Dataset used as supplied.
A8: Observations per store (min) | B8: {=MIN(COUNTIF('Raw Data'!$C$2:$C$1387,'Raw Data'!$C$2:$C$1387))} -> 11 | C8: Balanced panel: every store has 11 weekly records (array calc)
A9: First date | B9: =MIN('Raw Data'!$A$2:$A$1387) -> 40302
A10: Last date | B10: =MAX('Raw Data'!$A$2:$A$1387) -> 40372
A11: Blank cells in numeric/dummy columns D:L | B11: =COUNTBLANK('Raw Data'!$D$2:$L$1387) -> 0 | C11: None
A12: Blank cells in Region | B12: =COUNTBLANK('Raw Data'!$B$2:$B$1387) -> 0 | C12: None. Region code "NA" (143 rows, 13 stores) is a genuine region code, not a missing value; software that reads "NA" as missing would silently drop these rows
A13: Rows with Region = "NA" | B13: =COUNTIF('Raw Data'!$B$2:$B$1387,"NA") -> 143 | C13: Kept in analysis (Region is not a model predictor)
A14: Exact duplicate rows | B14: 0 | C14: Checked in Python (all 12 fields identical): none
A15: Sales <= 0 | B15: =COUNTIF('Raw Data'!$D$2:$D$1387,"<=0") -> 0 | C15: None; minimum 47.6 units
A16: Stores whose Sales Rep flag changes during the window | B16: 10 | C16: Sales Rep is not constant within 10 stores (Python check). Treated as an observation-level indicator, as defined in the case.
A17: Stores whose Natural Retailers count changes | B17: 3 | C17: 3 stores (Python check)
A19: Variable summary
A20: Variable | B20: Count | C20: Distinct values | D20: Mean | E20: Median | F20: Std dev | G20: Min | H20: Max | I20: Type / coding
A21: Sales (Units Sold) | B21: =COUNT('Analysis Data'!$C$2:$C$1387) -> 1386 | C21: ="continuous" -> continuous | D21: =AVERAGE('Analysis Data'!$C$2:$C$1387) -> 253.82072 | E21: =MEDIAN('Analysis Data'!$C$2:$C$1387) -> 236.73527 | F21: =_xlfn.STDEV.S('Analysis Data'!$C$2:$C$1387) -> 110.99873 | G21: =MIN('Analysis Data'!$C$2:$C$1387) -> 47.559852 | H21: =MAX('Analysis Data'!$C$2:$C$1387) -> 1041.2003 | I21: Continuous - dependent variable
A22: Price (Avg Retail Price) | B22: =COUNT('Analysis Data'!$D$2:$D$1387) -> 1386 | C22: ="continuous" -> continuous | D22: =AVERAGE('Analysis Data'!$D$2:$D$1387) -> 4.1070929 | E22: =MEDIAN('Analysis Data'!$D$2:$D$1387) -> 4.0966667 | F22: =_xlfn.STDEV.S('Analysis Data'!$D$2:$D$1387) -> 0.46382837 | G22: =MIN('Analysis Data'!$D$2:$D$1387) -> 2.8892857 | H22: =MAX('Analysis Data'!$D$2:$D$1387) -> 6.2515385 | I22: Continuous, $
A23: Rep (Sales Rep) | B23: =COUNT('Analysis Data'!$E$2:$E$1387) -> 1386 | C23: =SUMPRODUCT(1/COUNTIF('Analysis Data'!$E$2:$E$1387,'Analysis Data'!$E$2:$E$1387)) -> 2 | D23: =AVERAGE('Analysis Data'!$E$2:$E$1387) -> 0.54978355 | E23: =MEDIAN('Analysis Data'!$E$2:$E$1387) -> 1 | F23: =_xlfn.STDEV.S('Analysis Data'!$E$2:$E$1387) -> 0.497695 | G23: =MIN('Analysis Data'!$E$2:$E$1387) -> 0 | H23: =MAX('Analysis Data'!$E$2:$E$1387) -> 1 | I23: Dummy 1 = regional rep, 0 = national only
A24: Endcap | B24: =COUNT('Analysis Data'!$F$2:$F$1387) -> 1386 | C24: =SUMPRODUCT(1/COUNTIF('Analysis Data'!$F$2:$F$1387,'Analysis Data'!$F$2:$F$1387)) -> 2 | D24: =AVERAGE('Analysis Data'!$F$2:$F$1387) -> 0.038239538 | E24: =MEDIAN('Analysis Data'!$F$2:$F$1387) -> 0 | F24: =_xlfn.STDEV.S('Analysis Data'!$F$2:$F$1387) -> 0.19184324 | G24: =MIN('Analysis Data'!$F$2:$F$1387) -> 0 | H24: =MAX('Analysis Data'!$F$2:$F$1387) -> 1 | I24: Dummy 1 = endcap promotion
A25: Demo | B25: =COUNT('Analysis Data'!$G$2:$G$1387) -> 1386 | C25: =SUMPRODUCT(1/COUNTIF('Analysis Data'!$G$2:$G$1387,'Analysis Data'!$G$2:$G$1387)) -> 2 | D25: =AVERAGE('Analysis Data'!$G$2:$G$1387) -> 0.058441558 | E25: =MEDIAN('Analysis Data'!$G$2:$G$1387) -> 0 | F25: =_xlfn.STDEV.S('Analysis Data'!$G$2:$G$1387) -> 0.23466119 | G25: =MIN('Analysis Data'!$G$2:$G$1387) -> 0 | H25: =MAX('Analysis Data'!$G$2:$G$1387) -> 1 | I25: Dummy: demo this week
A26: D13 (Demo1-3) | B26: =COUNT('Analysis Data'!$H$2:$H$1387) -> 1386 | C26: =SUMPRODUCT(1/COUNTIF('Analysis Data'!$H$2:$H$1387,'Analysis Data'!$H$2:$H$1387)) -> 2 | D26: =AVERAGE('Analysis Data'!$H$2:$H$1387) -> 0.15656566 | E26: =MEDIAN('Analysis Data'!$H$2:$H$1387) -> 0 | F26: =_xlfn.STDEV.S('Analysis Data'!$H$2:$H$1387) -> 0.36352193 | G26: =MIN('Analysis Data'!$H$2:$H$1387) -> 0 | H26: =MAX('Analysis Data'!$H$2:$H$1387) -> 1 | I26: Dummy: demo 1-3 weeks ago
A27: D45 (Demo4-5) | B27: =COUNT('Analysis Data'!$I$2:$I$1387) -> 1386 | C27: =SUMPRODUCT(1/COUNTIF('Analysis Data'!$I$2:$I$1387,'Analysis Data'!$I$2:$I$1387)) -> 2 | D27: =AVERAGE('Analysis Data'!$I$2:$I$1387) -> 0.075757576 | E27: =MEDIAN('Analysis Data'!$I$2:$I$1387) -> 0 | F27: =_xlfn.STDEV.S('Analysis Data'!$I$2:$I$1387) -> 0.26470535 | G27: =MIN('Analysis Data'!$I$2:$I$1387) -> 0 | H27: =MAX('Analysis Data'!$I$2:$I$1387) -> 1 | I27: Dummy: demo 4-5+ weeks ago
A28: Natural | B28: =COUNT('Analysis Data'!$J$2:$J$1387) -> 1386 | C28: =SUMPRODUCT(1/COUNTIF('Analysis Data'!$J$2:$J$1387,'Analysis Data'!$J$2:$J$1387)) -> 5 | D28: =AVERAGE('Analysis Data'!$J$2:$J$1387) -> 1.4487734 | E28: =MEDIAN('Analysis Data'!$J$2:$J$1387) -> 1 | F28: =_xlfn.STDEV.S('Analysis Data'!$J$2:$J$1387) -> 0.97509156 | G28: =MIN('Analysis Data'!$J$2:$J$1387) -> 0 | H28: =MAX('Analysis Data'!$J$2:$J$1387) -> 4 | I28: Count within 5 miles
A29: Fitness | B29: =COUNT('Analysis Data'!$K$2:$K$1387) -> 1386 | C29: =SUMPRODUCT(1/COUNTIF('Analysis Data'!$K$2:$K$1387,'Analysis Data'!$K$2:$K$1387)) -> 6 | D29: =AVERAGE('Analysis Data'!$K$2:$K$1387) -> 2.4761905 | E29: =MEDIAN('Analysis Data'!$K$2:$K$1387) -> 2 | F29: =_xlfn.STDEV.S('Analysis Data'!$K$2:$K$1387) -> 1.5927893 | G29: =MIN('Analysis Data'!$K$2:$K$1387) -> 0 | H29: =MAX('Analysis Data'!$K$2:$K$1387) -> 5 | I29: Count within 5 miles
A31: Dummy-variable counts (rows equal to 1)
A32: Rep | B32: =SUM('Analysis Data'!$E$2:$E$1387) -> 762
A33: Endcap | B33: =SUM('Analysis Data'!$F$2:$F$1387) -> 53
A34: Demo | B34: =SUM('Analysis Data'!$G$2:$G$1387) -> 81
A35: Demo1-3 | B35: =SUM('Analysis Data'!$H$2:$H$1387) -> 217
A36: Demo4-5 | B36: =SUM('Analysis Data'!$I$2:$I$1387) -> 105
A37: Endcap x Rep | B37: =SUM('Analysis Data'!$L$2:$L$1387) -> 36
A39: Outlier note: no data-entry errors found; max Sales 1,041 units (store with endcap + rep) is plausible given the Endcap x Rep effect; see Outliers sheet.

Sheet Descriptive Stats
A1: DESCRIPTIVE STATISTICS & UNADJUSTED PROMOTION COMPARISONS
A2: Unadjusted comparisons are descriptive; they do not control for other variables and are not causal estimates.
A4: Variable | B4: Mean | C4: Median | D4: Std dev | E4: Min | F4: Max | G4: N
A5: Sales (Units Sold) | B5: =AVERAGE('Analysis Data'!$C$2:$C$1387) -> 253.82072 | C5: =MEDIAN('Analysis Data'!$C$2:$C$1387) -> 236.73527 | D5: =_xlfn.STDEV.S('Analysis Data'!$C$2:$C$1387) -> 110.99873 | E5: =MIN('Analysis Data'!$C$2:$C$1387) -> 47.559852 | F5: =MAX('Analysis Data'!$C$2:$C$1387) -> 1041.2003 | G5: =COUNT('Analysis Data'!$C$2:$C$1387) -> 1386
A6: Price (Avg Retail Price) | B6: =AVERAGE('Analysis Data'!$D$2:$D$1387) -> 4.1070929 | C6: =MEDIAN('Analysis Data'!$D$2:$D$1387) -> 4.0966667 | D6: =_xlfn.STDEV.S('Analysis Data'!$D$2:$D$1387) -> 0.46382837 | E6: =MIN('Analysis Data'!$D$2:$D$1387) -> 2.8892857 | F6: =MAX('Analysis Data'!$D$2:$D$1387) -> 6.2515385 | G6: =COUNT('Analysis Data'!$D$2:$D$1387) -> 1386
A7: Rep (Sales Rep) | B7: =AVERAGE('Analysis Data'!$E$2:$E$1387) -> 0.54978355 | C7: =MEDIAN('Analysis Data'!$E$2:$E$1387) -> 1 | D7: =_xlfn.STDEV.S('Analysis Data'!$E$2:$E$1387) -> 0.497695 | E7: =MIN('Analysis Data'!$E$2:$E$1387) -> 0 | F7: =MAX('Analysis Data'!$E$2:$E$1387) -> 1 | G7: =COUNT('Analysis Data'!$E$2:$E$1387) -> 1386
A8: Endcap | B8: =AVERAGE('Analysis Data'!$F$2:$F$1387) -> 0.038239538 | C8: =MEDIAN('Analysis Data'!$F$2:$F$1387) -> 0 | D8: =_xlfn.STDEV.S('Analysis Data'!$F$2:$F$1387) -> 0.19184324 | E8: =MIN('Analysis Data'!$F$2:$F$1387) -> 0 | F8: =MAX('Analysis Data'!$F$2:$F$1387) -> 1 | G8: =COUNT('Analysis Data'!$F$2:$F$1387) -> 1386
A9: Demo | B9: =AVERAGE('Analysis Data'!$G$2:$G$1387) -> 0.058441558 | C9: =MEDIAN('Analysis Data'!$G$2:$G$1387) -> 0 | D9: =_xlfn.STDEV.S('Analysis Data'!$G$2:$G$1387) -> 0.23466119 | E9: =MIN('Analysis Data'!$G$2:$G$1387) -> 0 | F9: =MAX('Analysis Data'!$G$2:$G$1387) -> 1 | G9: =COUNT('Analysis Data'!$G$2:$G$1387) -> 1386
A10: D13 (Demo1-3) | B10: =AVERAGE('Analysis Data'!$H$2:$H$1387) -> 0.15656566 | C10: =MEDIAN('Analysis Data'!$H$2:$H$1387) -> 0 | D10: =_xlfn.STDEV.S('Analysis Data'!$H$2:$H$1387) -> 0.36352193 | E10: =MIN('Analysis Data'!$H$2:$H$1387) -> 0 | F10: =MAX('Analysis Data'!$H$2:$H$1387) -> 1 | G10: =COUNT('Analysis Data'!$H$2:$H$1387) -> 1386
A11: D45 (Demo4-5) | B11: =AVERAGE('Analysis Data'!$I$2:$I$1387) -> 0.075757576 | C11: =MEDIAN('Analysis Data'!$I$2:$I$1387) -> 0 | D11: =_xlfn.STDEV.S('Analysis Data'!$I$2:$I$1387) -> 0.26470535 | E11: =MIN('Analysis Data'!$I$2:$I$1387) -> 0 | F11: =MAX('Analysis Data'!$I$2:$I$1387) -> 1 | G11: =COUNT('Analysis Data'!$I$2:$I$1387) -> 1386
A12: Natural | B12: =AVERAGE('Analysis Data'!$J$2:$J$1387) -> 1.4487734 | C12: =MEDIAN('Analysis Data'!$J$2:$J$1387) -> 1 | D12: =_xlfn.STDEV.S('Analysis Data'!$J$2:$J$1387) -> 0.97509156 | E12: =MIN('Analysis Data'!$J$2:$J$1387) -> 0 | F12: =MAX('Analysis Data'!$J$2:$J$1387) -> 4 | G12: =COUNT('Analysis Data'!$J$2:$J$1387) -> 1386
A13: Fitness | B13: =AVERAGE('Analysis Data'!$K$2:$K$1387) -> 2.4761905 | C13: =MEDIAN('Analysis Data'!$K$2:$K$1387) -> 2 | D13: =_xlfn.STDEV.S('Analysis Data'!$K$2:$K$1387) -> 1.5927893 | E13: =MIN('Analysis Data'!$K$2:$K$1387) -> 0 | F13: =MAX('Analysis Data'!$K$2:$K$1387) -> 5 | G13: =COUNT('Analysis Data'!$K$2:$K$1387) -> 1386
A15: Unadjusted mean Sales: promotion = 1 vs 0 (Welch two-sample t-test)
A16: Promotion | B16: Mean (=1) | C16: Mean (=0) | D16: Difference | E16: N (=1) | F16: N (=0) | G16: SD (=1) | H16: SD (=0) | I16: Welch t | J16: Welch df | K16: p-value
A17: Demo (current week) | B17: =AVERAGEIF('Analysis Data'!$G$2:$G$1387,1,'Analysis Data'!$C$2:$C$1387) -> 400.50795 | C17: =AVERAGEIF('Analysis Data'!$G$2:$G$1387,0,'Analysis Data'!$C$2:$C$1387) -> 244.71599 | D17: =B17-C17 -> 155.79196 | E17: =COUNTIF('Analysis Data'!$G$2:$G$1387,1) -> 81 | F17: =COUNTIF('Analysis Data'!$G$2:$G$1387,0) -> 1305 | G17: {=_xlfn.STDEV.S(IF('Analysis Data'!$G$2:$G$1387=1,'Analysis Data'!$C$2:$C$1387))} -> 162.70749 | H17: {=_xlfn.STDEV.S(IF('Analysis Data'!$G$2:$G$1387=0,'Analysis Data'!$C$2:$C$1387))} -> 100.21154 | I17: =D17/SQRT(G17^2/E17+H17^2/F17) -> 8.5177829 | J17: =(G17^2/E17+H17^2/F17)^2/((G17^2/E17)^2/(E17-1)+(H17^2/F17)^2/(F17-1)) -> 83.808665 | K17: =_xlfn.T.DIST.2T(ABS(I17),J17) -> 6.0238074e-13
A18: Demo1-3 | B18: =AVERAGEIF('Analysis Data'!$H$2:$H$1387,1,'Analysis Data'!$C$2:$C$1387) -> 352.86975 | C18: =AVERAGEIF('Analysis Data'!$H$2:$H$1387,0,'Analysis Data'!$C$2:$C$1387) -> 235.43437 | D18: =B18-C18 -> 117.43539 | E18: =COUNTIF('Analysis Data'!$H$2:$H$1387,1) -> 217 | F18: =COUNTIF('Analysis Data'!$H$2:$H$1387,0) -> 1169 | G18: {=_xlfn.STDEV.S(IF('Analysis Data'!$H$2:$H$1387=1,'Analysis Data'!$C$2:$C$1387))} -> 136.94347 | H18: {=_xlfn.STDEV.S(IF('Analysis Data'!$H$2:$H$1387=0,'Analysis Data'!$C$2:$C$1387))} -> 94.765942 | I18: =D18/SQRT(G18^2/E18+H18^2/F18) -> 12.10584 | J18: =(G18^2/E18+H18^2/F18)^2/((G18^2/E18)^2/(E18-1)+(H18^2/F18)^2/(F18-1)) -> 255.73485 | K18: =_xlfn.T.DIST.2T(ABS(I18),J18) -> 5.9034953e-27
A19: Demo4-5 | B19: =AVERAGEIF('Analysis Data'!$I$2:$I$1387,1,'Analysis Data'!$C$2:$C$1387) -> 330.68614 | C19: =AVERAGEIF('Analysis Data'!$I$2:$I$1387,0,'Analysis Data'!$C$2:$C$1387) -> 247.52027 | D19: =B19-C19 -> 83.165864 | E19: =COUNTIF('Analysis Data'!$I$2:$I$1387,1) -> 105 | F19: =COUNTIF('Analysis Data'!$I$2:$I$1387,0) -> 1281 | G19: {=_xlfn.STDEV.S(IF('Analysis Data'!$I$2:$I$1387=1,'Analysis Data'!$C$2:$C$1387))} -> 106.11667 | H19: {=_xlfn.STDEV.S(IF('Analysis Data'!$I$2:$I$1387=0,'Analysis Data'!$C$2:$C$1387))} -> 109.05079 | I19: =D19/SQRT(G19^2/E19+H19^2/F19) -> 7.7042215 | J19: =(G19^2/E19+H19^2/F19)^2/((G19^2/E19)^2/(E19-1)+(H19^2/F19)^2/(F19-1)) -> 122.70961 | K19: =_xlfn.T.DIST.2T(ABS(I19),J19) -> 3.9005256e-12
A20: Endcap | B20: =AVERAGEIF('Analysis Data'!$F$2:$F$1387,1,'Analysis Data'!$C$2:$C$1387) -> 583.92496 | C20: =AVERAGEIF('Analysis Data'!$F$2:$F$1387,0,'Analysis Data'!$C$2:$C$1387) -> 240.69579 | D20: =B20-C20 -> 343.22917 | E20: =COUNTIF('Analysis Data'!$F$2:$F$1387,1) -> 53 | F20: =COUNTIF('Analysis Data'!$F$2:$F$1387,0) -> 1333 | G20: {=_xlfn.STDEV.S(IF('Analysis Data'!$F$2:$F$1387=1,'Analysis Data'!$C$2:$C$1387))} -> 265.9761 | H20: {=_xlfn.STDEV.S(IF('Analysis Data'!$F$2:$F$1387=0,'Analysis Data'!$C$2:$C$1387))} -> 74.43768 | I20: =D20/SQRT(G20^2/E20+H20^2/F20) -> 9.3800321 | J20: =(G20^2/E20+H20^2/F20)^2/((G20^2/E20)^2/(E20-1)+(H20^2/F20)^2/(F20-1)) -> 52.324361 | K20: =_xlfn.T.DIST.2T(ABS(I20),J20) -> 9.0369156e-13
A21: Sales Rep | B21: =AVERAGEIF('Analysis Data'!$E$2:$E$1387,1,'Analysis Data'!$C$2:$C$1387) -> 298.94889 | C21: =AVERAGEIF('Analysis Data'!$E$2:$E$1387,0,'Analysis Data'!$C$2:$C$1387) -> 198.71227 | D21: =B21-C21 -> 100.23662 | E21: =COUNTIF('Analysis Data'!$E$2:$E$1387,1) -> 762 | F21: =COUNTIF('Analysis Data'!$E$2:$E$1387,0) -> 624 | G21: {=_xlfn.STDEV.S(IF('Analysis Data'!$E$2:$E$1387=1,'Analysis Data'!$C$2:$C$1387))} -> 123.03375 | H21: {=_xlfn.STDEV.S(IF('Analysis Data'!$E$2:$E$1387=0,'Analysis Data'!$C$2:$C$1387))} -> 58.028094 | I21: =D21/SQRT(G21^2/E21+H21^2/F21) -> 19.9433 | J21: =(G21^2/E21+H21^2/F21)^2/((G21^2/E21)^2/(E21-1)+(H21^2/F21)^2/(F21-1)) -> 1128.8461 | K21: =_xlfn.T.DIST.2T(ABS(I21),J21) -> 4.8599039e-76
A23: Mean Sales by Sales Rep x Endcap cell
A24: Cell | B24: Mean Sales | C24: N
A25: No rep, no endcap | B25: =AVERAGEIFS('Analysis Data'!$C$2:$C$1387,'Analysis Data'!$E$2:$E$1387,0,'Analysis Data'!$F$2:$F$1387,0) -> 198.18336 | C25: =COUNTIFS('Analysis Data'!$E$2:$E$1387,0,'Analysis Data'!$F$2:$F$1387,0) -> 607
A26: No rep, endcap | B26: =AVERAGEIFS('Analysis Data'!$C$2:$C$1387,'Analysis Data'!$E$2:$E$1387,0,'Analysis Data'!$F$2:$F$1387,1) -> 217.59744 | C26: =COUNTIFS('Analysis Data'!$E$2:$E$1387,0,'Analysis Data'!$F$2:$F$1387,1) -> 17
A27: Rep, no endcap | B27: =AVERAGEIFS('Analysis Data'!$C$2:$C$1387,'Analysis Data'!$E$2:$E$1387,1,'Analysis Data'!$F$2:$F$1387,0) -> 276.23993 | C27: =COUNTIFS('Analysis Data'!$E$2:$E$1387,1,'Analysis Data'!$F$2:$F$1387,0) -> 726
A28: Rep, endcap | B28: =AVERAGEIFS('Analysis Data'!$C$2:$C$1387,'Analysis Data'!$E$2:$E$1387,1,'Analysis Data'!$F$2:$F$1387,1) -> 756.91295 | C28: =COUNTIFS('Analysis Data'!$E$2:$E$1387,1,'Analysis Data'!$F$2:$F$1387,1) -> 36

Sheet Correlations
A1: PAIRWISE CORRELATION MATRIX (Pearson, CORREL formulas)
B3: Sales | C3: Price | D3: Rep | E3: Endcap | F3: Demo | G3: Demo1-3 | H3: Demo4-5 | I3: Natural | J3: Fitness | K3: Endcap x Rep
A4: Sales | B4: =CORREL('Analysis Data'!$C$2:$C$1387,'Analysis Data'!$C$2:$C$1387) -> 1 | C4: =CORREL('Analysis Data'!$C$2:$C$1387,'Analysis Data'!$D$2:$D$1387) -> -0.018828588 | D4: =CORREL('Analysis Data'!$C$2:$C$1387,'Analysis Data'!$E$2:$E$1387) -> 0.44943995 | E4: =CORREL('Analysis Data'!$C$2:$C$1387,'Analysis Data'!$F$2:$F$1387) -> 0.59321576 | F4: =CORREL('Analysis Data'!$C$2:$C$1387,'Analysis Data'!$G$2:$G$1387) -> 0.32935805 | G4: =CORREL('Analysis Data'!$C$2:$C$1387,'Analysis Data'!$H$2:$H$1387) -> 0.38460204 | H4: =CORREL('Analysis Data'!$C$2:$C$1387,'Analysis Data'!$I$2:$I$1387) -> 0.19833063 | I4: =CORREL('Analysis Data'!$C$2:$C$1387,'Analysis Data'!$J$2:$J$1387) -> 0.062784251 | J4: =CORREL('Analysis Data'!$C$2:$C$1387,'Analysis Data'!$K$2:$K$1387) -> -0.031771848 | K4: =CORREL('Analysis Data'!$C$2:$C$1387,'Analysis Data'!$L$2:$L$1387) -> 0.74040731
A5: Price | B5: =CORREL('Analysis Data'!$D$2:$D$1387,'Analysis Data'!$C$2:$C$1387) -> -0.018828588 | C5: =CORREL('Analysis Data'!$D$2:$D$1387,'Analysis Data'!$D$2:$D$1387) -> 1 | D5: =CORREL('Analysis Data'!$D$2:$D$1387,'Analysis Data'!$E$2:$E$1387) -> 0.32890041 | E5: =CORREL('Analysis Data'!$D$2:$D$1387,'Analysis Data'!$F$2:$F$1387) -> -0.067293565 | F5: =CORREL('Analysis Data'!$D$2:$D$1387,'Analysis Data'!$G$2:$G$1387) -> 0.051664462 | G5: =CORREL('Analysis Data'!$D$2:$D$1387,'Analysis Data'!$H$2:$H$1387) -> -0.01509762 | H5: =CORREL('Analysis Data'!$D$2:$D$1387,'Analysis Data'!$I$2:$I$1387) -> 0.087935982 | I5: =CORREL('Analysis Data'!$D$2:$D$1387,'Analysis Data'!$J$2:$J$1387) -> -0.0048123855 | J5: =CORREL('Analysis Data'!$D$2:$D$1387,'Analysis Data'!$K$2:$K$1387) -> 0.071174912 | K5: =CORREL('Analysis Data'!$D$2:$D$1387,'Analysis Data'!$L$2:$L$1387) -> -0.058266802
A6: Rep | B6: =CORREL('Analysis Data'!$E$2:$E$1387,'Analysis Data'!$C$2:$C$1387) -> 0.44943995 | C6: =CORREL('Analysis Data'!$E$2:$E$1387,'Analysis Data'!$D$2:$D$1387) -> 0.32890041 | D6: =CORREL('Analysis Data'!$E$2:$E$1387,'Analysis Data'!$E$2:$E$1387) -> 1 | E6: =CORREL('Analysis Data'!$E$2:$E$1387,'Analysis Data'!$F$2:$F$1387) -> 0.0518869 | F6: =CORREL('Analysis Data'!$E$2:$E$1387,'Analysis Data'!$G$2:$G$1387) -> 0.1512641 | G6: =CORREL('Analysis Data'!$E$2:$E$1387,'Analysis Data'!$H$2:$H$1387) -> 0.24222744 | H6: =CORREL('Analysis Data'!$E$2:$E$1387,'Analysis Data'!$I$2:$I$1387) -> 0.13850847 | I6: =CORREL('Analysis Data'!$E$2:$E$1387,'Analysis Data'!$J$2:$J$1387) -> 0.089318908 | J6: =CORREL('Analysis Data'!$E$2:$E$1387,'Analysis Data'!$K$2:$K$1387) -> 0.057511255 | K6: =CORREL('Analysis Data'!$E$2:$E$1387,'Analysis Data'!$L$2:$L$1387) -> 0.14777439
A7: Endcap | B7: =CORREL('Analysis Data'!$F$2:$F$1387,'Analysis Data'!$C$2:$C$1387) -> 0.59321576 | C7: =CORREL('Analysis Data'!$F$2:$F$1387,'Analysis Data'!$D$2:$D$1387) -> -0.067293565 | D7: =CORREL('Analysis Data'!$F$2:$F$1387,'Analysis Data'!$E$2:$E$1387) -> 0.0518869 | E7: =CORREL('Analysis Data'!$F$2:$F$1387,'Analysis Data'!$F$2:$F$1387) -> 1 | F7: =CORREL('Analysis Data'!$F$2:$F$1387,'Analysis Data'!$G$2:$G$1387) -> 0.078630074 | G7: =CORREL('Analysis Data'!$F$2:$F$1387,'Analysis Data'!$H$2:$H$1387) -> 0.090093443 | H7: =CORREL('Analysis Data'!$F$2:$F$1387,'Analysis Data'!$I$2:$I$1387) -> -0.00021542548 | I7: =CORREL('Analysis Data'!$F$2:$F$1387,'Analysis Data'!$J$2:$J$1387) -> 0.081884463 | J7: =CORREL('Analysis Data'!$F$2:$F$1387,'Analysis Data'!$K$2:$K$1387) -> -0.059635101 | K7: =CORREL('Analysis Data'!$F$2:$F$1387,'Analysis Data'!$L$2:$L$1387) -> 0.81895777
A8: Demo | B8: =CORREL('Analysis Data'!$G$2:$G$1387,'Analysis Data'!$C$2:$C$1387) -> 0.32935805 | C8: =CORREL('Analysis Data'!$G$2:$G$1387,'Analysis Data'!$D$2:$D$1387) -> 0.051664462 | D8: =CORREL('Analysis Data'!$G$2:$G$1387,'Analysis Data'!$E$2:$E$1387) -> 0.1512641 | E8: =CORREL('Analysis Data'!$G$2:$G$1387,'Analysis Data'!$F$2:$F$1387) -> 0.078630074 | F8: =CORREL('Analysis Data'!$G$2:$G$1387,'Analysis Data'!$G$2:$G$1387) -> 1 | G8: =CORREL('Analysis Data'!$G$2:$G$1387,'Analysis Data'!$H$2:$H$1387) -> 0.036549317 | H8: =CORREL('Analysis Data'!$G$2:$G$1387,'Analysis Data'!$I$2:$I$1387) -> -0.013208807 | I8: =CORREL('Analysis Data'!$G$2:$G$1387,'Analysis Data'!$J$2:$J$1387) -> -0.0011064623 | J8: =CORREL('Analysis Data'!$G$2:$G$1387,'Analysis Data'!$K$2:$K$1387) -> 0.0066231384 | K8: =CORREL('Analysis Data'!$G$2:$G$1387,'Analysis Data'!$L$2:$L$1387) -> 0.094677756
A9: Demo1-3 | B9: =CORREL('Analysis Data'!$H$2:$H$1387,'Analysis Data'!$C$2:$C$1387) -> 0.38460204 | C9: =CORREL('Analysis Data'!$H$2:$H$1387,'Analysis Data'!$D$2:$D$1387) -> -0.01509762 | D9: =CORREL('Analysis Data'!$H$2:$H$1387,'Analysis Data'!$E$2:$E$1387) -> 0.24222744 | E9: =CORREL('Analysis Data'!$H$2:$H$1387,'Analysis Data'!$F$2:$F$1387) -> 0.090093443 | F9: =CORREL('Analysis Data'!$H$2:$H$1387,'Analysis Data'!$G$2:$G$1387) -> 0.036549317 | G9: =CORREL('Analysis Data'!$H$2:$H$1387,'Analysis Data'!$H$2:$H$1387) -> 1 | H9: =CORREL('Analysis Data'!$H$2:$H$1387,'Analysis Data'!$I$2:$I$1387) -> 0.011709819 | I9: =CORREL('Analysis Data'!$H$2:$H$1387,'Analysis Data'!$J$2:$J$1387) -> -0.0048556907 | J9: =CORREL('Analysis Data'!$H$2:$H$1387,'Analysis Data'!$K$2:$K$1387) -> 0.0083132341 | K9: =CORREL('Analysis Data'!$H$2:$H$1387,'Analysis Data'!$L$2:$L$1387) -> 0.10440063
A10: Demo4-5 | B10: =CORREL('Analysis Data'!$I$2:$I$1387,'Analysis Data'!$C$2:$C$1387) -> 0.19833063 | C10: =CORREL('Analysis Data'!$I$2:$I$1387,'Analysis Data'!$D$2:$D$1387) -> 0.087935982 | D10: =CORREL('Analysis Data'!$I$2:$I$1387,'Analysis Data'!$E$2:$E$1387) -> 0.13850847 | E10: =CORREL('Analysis Data'!$I$2:$I$1387,'Analysis Data'!$F$2:$F$1387) -> -0.00021542548 | F10: =CORREL('Analysis Data'!$I$2:$I$1387,'Analysis Data'!$G$2:$G$1387) -> -0.013208807 | G10: =CORREL('Analysis Data'!$I$2:$I$1387,'Analysis Data'!$H$2:$H$1387) -> 0.011709819 | H10: =CORREL('Analysis Data'!$I$2:$I$1387,'Analysis Data'!$I$2:$I$1387) -> 1 | I10: =CORREL('Analysis Data'!$I$2:$I$1387,'Analysis Data'!$J$2:$J$1387) -> 0.01364753 | J10: =CORREL('Analysis Data'!$I$2:$I$1387,'Analysis Data'!$K$2:$K$1387) -> -0.011987461 | K10: =CORREL('Analysis Data'!$I$2:$I$1387,'Analysis Data'!$L$2:$L$1387) -> -0.012467322
A11: Natural | B11: =CORREL('Analysis Data'!$J$2:$J$1387,'Analysis Data'!$C$2:$C$1387) -> 0.062784251 | C11: =CORREL('Analysis Data'!$J$2:$J$1387,'Analysis Data'!$D$2:$D$1387) -> -0.0048123855 | D11: =CORREL('Analysis Data'!$J$2:$J$1387,'Analysis Data'!$E$2:$E$1387) -> 0.089318908 | E11: =CORREL('Analysis Data'!$J$2:$J$1387,'Analysis Data'!$F$2:$F$1387) -> 0.081884463 | F11: =CORREL('Analysis Data'!$J$2:$J$1387,'Analysis Data'!$G$2:$G$1387) -> -0.0011064623 | G11: =CORREL('Analysis Data'!$J$2:$J$1387,'Analysis Data'!$H$2:$H$1387) -> -0.0048556907 | H11: =CORREL('Analysis Data'!$J$2:$J$1387,'Analysis Data'!$I$2:$I$1387) -> 0.01364753 | I11: =CORREL('Analysis Data'!$J$2:$J$1387,'Analysis Data'!$J$2:$J$1387) -> 1 | J11: =CORREL('Analysis Data'!$J$2:$J$1387,'Analysis Data'!$K$2:$K$1387) -> -0.085627579 | K11: =CORREL('Analysis Data'!$J$2:$J$1387,'Analysis Data'!$L$2:$L$1387) -> 0.05511849
A12: Fitness | B12: =CORREL('Analysis Data'!$K$2:$K$1387,'Analysis Data'!$C$2:$C$1387) -> -0.031771848 | C12: =CORREL('Analysis Data'!$K$2:$K$1387,'Analysis Data'!$D$2:$D$1387) -> 0.071174912 | D12: =CORREL('Analysis Data'!$K$2:$K$1387,'Analysis Data'!$E$2:$E$1387) -> 0.057511255 | E12: =CORREL('Analysis Data'!$K$2:$K$1387,'Analysis Data'!$F$2:$F$1387) -> -0.059635101 | F12: =CORREL('Analysis Data'!$K$2:$K$1387,'Analysis Data'!$G$2:$G$1387) -> 0.0066231384 | G12: =CORREL('Analysis Data'!$K$2:$K$1387,'Analysis Data'!$H$2:$H$1387) -> 0.0083132341 | H12: =CORREL('Analysis Data'!$K$2:$K$1387,'Analysis Data'!$I$2:$I$1387) -> -0.011987461 | I12: =CORREL('Analysis Data'!$K$2:$K$1387,'Analysis Data'!$J$2:$J$1387) -> -0.085627579 | J12: =CORREL('Analysis Data'!$K$2:$K$1387,'Analysis Data'!$K$2:$K$1387) -> 1 | K12: =CORREL('Analysis Data'!$K$2:$K$1387,'Analysis Data'!$L$2:$L$1387) -> -0.068781069
A13: Endcap x Rep | B13: =CORREL('Analysis Data'!$L$2:$L$1387,'Analysis Data'!$C$2:$C$1387) -> 0.74040731 | C13: =CORREL('Analysis Data'!$L$2:$L$1387,'Analysis Data'!$D$2:$D$1387) -> -0.058266802 | D13: =CORREL('Analysis Data'!$L$2:$L$1387,'Analysis Data'!$E$2:$E$1387) -> 0.14777439 | E13: =CORREL('Analysis Data'!$L$2:$L$1387,'Analysis Data'!$F$2:$F$1387) -> 0.81895777 | F13: =CORREL('Analysis Data'!$L$2:$L$1387,'Analysis Data'!$G$2:$G$1387) -> 0.094677756 | G13: =CORREL('Analysis Data'!$L$2:$L$1387,'Analysis Data'!$H$2:$H$1387) -> 0.10440063 | H13: =CORREL('Analysis Data'!$L$2:$L$1387,'Analysis Data'!$I$2:$I$1387) -> -0.012467322 | I13: =CORREL('Analysis Data'!$L$2:$L$1387,'Analysis Data'!$J$2:$J$1387) -> 0.05511849 | J13: =CORREL('Analysis Data'!$L$2:$L$1387,'Analysis Data'!$K$2:$K$1387) -> -0.068781069 | K13: =CORREL('Analysis Data'!$L$2:$L$1387,'Analysis Data'!$L$2:$L$1387) -> 1
A16: Reading: Sales correlates most with Endcap x Rep (0.74) and Endcap (0.59); Price has ~0 pairwise correlation with Sales, but a strongly negative partial effect once Sales Rep (r=0.33 with Price) is controlled. Predictors are only weakly correlated with each other (see VIF sheet).

Sheet Baseline Models
A1: BASELINE MODELS (0A, 0B, 0C) - single-predictor OLS using LINEST
A2: Unadjusted single-variable relationships. Price alone explains ~0% of variation; Endcap alone ~35%; Demo alone ~11%.
A3: Model 0A: Sales ~ Price
A6: INPUTS
A7: Dependent (Y) range | B7: 'Analysis Data'!C2:C1387
A8: Predictor (X) range | B8: 'Analysis Data'!D2:D1387
A10: CALCULATION: LINEST(Y,X,TRUE,TRUE) raw array (coefficients appear in REVERSE variable order; last column = intercept)
B11: Price | C11: Intercept
A12: Coefficient | B12: {=IFERROR(LINEST('Analysis Data'!$C$2:$C$1387,'Analysis Data'!$D$2:$D$1387,TRUE(),TRUE()),"")} -> -4.5058679 | C12: 272.32674
A13: Std error | B13: 6.4315502 | C13: 26.582768
A14: R² | SE(y) | B14: 0.00035451571 | C14: 111.01914
A15: F | df | B15: 0.49082375 | C15: 1384
A16: SSreg | SSres | B16: 6049.5252 | C16: 17058145
A19: OUTPUT: Regression statistics
A20: Multiple R | B20: =SQRT(INDEX('Baseline Models'!$B$12:$C$16,3,1)) -> 0.018828588
A21: R² | B21: =INDEX('Baseline Models'!$B$12:$C$16,3,1) -> 0.00035451571
A22: Adjusted R² | B22: =1-(1-'Baseline Models'!$B$21)*('Baseline Models'!$B$24-1)/'Baseline Models'!$B$26 -> -0.00036777149
A23: Standard error | B23: =INDEX('Baseline Models'!$B$12:$C$16,3,2) -> 111.01914
A24: Observations | B24: =COUNT('Analysis Data'!$C$2:$C$1387) -> 1386
A25: k (predictors) | B25: =1 -> 1
A26: df residual | B26: =INDEX('Baseline Models'!$B$12:$C$16,4,2) -> 1384
A27: F-statistic | B27: =INDEX('Baseline Models'!$B$12:$C$16,4,1) -> 0.49082375
A28: Significance F (model p-value) | B28: =_xlfn.F.DIST.RT('Baseline Models'!$B$27,'Baseline Models'!$B$25,'Baseline Models'!$B$26) -> 0.48367784
A29: SS regression | B29: =INDEX('Baseline Models'!$B$12:$C$16,5,1) -> 6049.5252
A30: SS residual | B30: =INDEX('Baseline Models'!$B$12:$C$16,5,2) -> 17058145
A31: SS total | B31: ='Baseline Models'!$B$29+'Baseline Models'!$B$30 -> 17064195
A33: OUTPUT: Coefficient table (t = b/SE; p = two-tailed T.DIST.2T; 95% CI = b ± T.INV.2T(0.05,df)·SE)
A34: Variable | B34: Coefficient | C34: Std error | D34: t-stat | E34: p-value | F34: Lower 95% | G34: Upper 95%
A35: Intercept | B35: =INDEX('Baseline Models'!$B$12:$C$16,1,2) -> 272.32674 | C35: =INDEX('Baseline Models'!$B$12:$C$16,2,2) -> 26.582768 | D35: =B35/C35 -> 10.244484 | E35: =_xlfn.T.DIST.2T(ABS(D35),'Baseline Models'!$B$26) -> 8.6387707e-24 | F35: =B35-_xlfn.T.INV.2T(0.05,'Baseline Models'!$B$26)*C35 -> 220.17986 | G35: =B35+_xlfn.T.INV.2T(0.05,'Baseline Models'!$B$26)*C35 -> 324.47361
A36: Price | B36: =INDEX('Baseline Models'!$B$12:$C$16,1,1) -> -4.5058679 | C36: =INDEX('Baseline Models'!$B$12:$C$16,2,1) -> 6.4315502 | D36: =B36/C36 -> -0.70058815 | E36: =_xlfn.T.DIST.2T(ABS(D36),'Baseline Models'!$B$26) -> 0.48367784 | F36: =B36-_xlfn.T.INV.2T(0.05,'Baseline Models'!$B$26)*C36 -> -17.122508 | G36: =B36+_xlfn.T.INV.2T(0.05,'Baseline Models'!$B$26)*C36 -> 8.1107726
A40: Model 0B: Sales ~ Demo
A43: INPUTS
A44: Dependent (Y) range | B44: 'Analysis Data'!C2:C1387
A45: Predictor (X) range | B45: 'Analysis Data'!G2:G1387
A47: CALCULATION: LINEST(Y,X,TRUE,TRUE) raw array (coefficients appear in REVERSE variable order; last column = intercept)
B48: Demo | C48: Intercept
A49: Coefficient | B49: {=IFERROR(LINEST('Analysis Data'!$C$2:$C$1387,'Analysis Data'!$G$2:$G$1387,TRUE(),TRUE()),"")} -> 155.79196 | C49: 244.71599
A50: Std error | B50: 12.005356 | C50: 2.9022575
A51: R² | SE(y) | B51: 0.10847672 | C51: 104.84342
A52: F | df | B52: 168.39918 | C52: 1384
A53: SSreg | SSres | B53: 1851068 | C53: 15213127
A56: OUTPUT: Regression statistics
A57: Multiple R | B57: =SQRT(INDEX('Baseline Models'!$B$49:$C$53,3,1)) -> 0.32935805
A58: R² | B58: =INDEX('Baseline Models'!$B$49:$C$53,3,1) -> 0.10847672
A59: Adjusted R² | B59: =1-(1-'Baseline Models'!$B$58)*('Baseline Models'!$B$61-1)/'Baseline Models'!$B$63 -> 0.10783256
A60: Standard error | B60: =INDEX('Baseline Models'!$B$49:$C$53,3,2) -> 104.84342
A61: Observations | B61: =COUNT('Analysis Data'!$C$2:$C$1387) -> 1386
A62: k (predictors) | B62: =1 -> 1
A63: df residual | B63: =INDEX('Baseline Models'!$B$49:$C$53,4,2) -> 1384
A64: F-statistic | B64: =INDEX('Baseline Models'!$B$49:$C$53,4,1) -> 168.39918
A65: Significance F (model p-value) | B65: =_xlfn.F.DIST.RT('Baseline Models'!$B$64,'Baseline Models'!$B$62,'Baseline Models'!$B$63) -> 2.0086572e-36
A66: SS regression | B66: =INDEX('Baseline Models'!$B$49:$C$53,5,1) -> 1851068
A67: SS residual | B67: =INDEX('Baseline Models'!$B$49:$C$53,5,2) -> 15213127
A68: SS total | B68: ='Baseline Models'!$B$66+'Baseline Models'!$B$67 -> 17064195
A70: OUTPUT: Coefficient table (t = b/SE; p = two-tailed T.DIST.2T; 95% CI = b ± T.INV.2T(0.05,df)·SE)
A71: Variable | B71: Coefficient | C71: Std error | D71: t-stat | E71: p-value | F71: Lower 95% | G71: Upper 95%
A72: Intercept | B72: =INDEX('Baseline Models'!$B$49:$C$53,1,2) -> 244.71599 | C72: =INDEX('Baseline Models'!$B$49:$C$53,2,2) -> 2.9022575 | D72: =B72/C72 -> 84.319187 | E72: =_xlfn.T.DIST.2T(ABS(D72),'Baseline Models'!$B$63) -> 0 | F72: =B72-_xlfn.T.INV.2T(0.05,'Baseline Models'!$B$63)*C72 -> 239.02269 | G72: =B72+_xlfn.T.INV.2T(0.05,'Baseline Models'!$B$63)*C72 -> 250.40929
A73: Demo | B73: =INDEX('Baseline Models'!$B$49:$C$53,1,1) -> 155.79196 | C73: =INDEX('Baseline Models'!$B$49:$C$53,2,1) -> 12.005356 | D73: =B73/C73 -> 12.976871 | E73: =_xlfn.T.DIST.2T(ABS(D73),'Baseline Models'!$B$63) -> 2.0086572e-36 | F73: =B73-_xlfn.T.INV.2T(0.05,'Baseline Models'!$B$63)*C73 -> 132.2413 | G73: =B73+_xlfn.T.INV.2T(0.05,'Baseline Models'!$B$63)*C73 -> 179.34262
A77: Model 0C: Sales ~ Endcap
A80: INPUTS
A81: Dependent (Y) range | B81: 'Analysis Data'!C2:C1387
A82: Predictor (X) range | B82: 'Analysis Data'!F2:F1387
A84: CALCULATION: LINEST(Y,X,TRUE,TRUE) raw array (coefficients appear in REVERSE variable order; last column = intercept)
B85: Endcap | C85: Intercept
A86: Coefficient | B86: {=IFERROR(LINEST('Analysis Data'!$C$2:$C$1387,'Analysis Data'!$F$2:$F$1387,TRUE(),TRUE()),"")} -> 343.22917 | C86: 240.69579
A87: Std error | B87: 12.520533 | C87: 2.4483818
A88: R² | SE(y) | B88: 0.35190494 | C88: 89.391086
A89: F | df | B89: 751.48918 | C89: 1384
A90: SSreg | SSres | B90: 6004974.4 | C90: 11059220
A93: OUTPUT: Regression statistics
A94: Multiple R | B94: =SQRT(INDEX('Baseline Models'!$B$86:$C$90,3,1)) -> 0.59321576
A95: R² | B95: =INDEX('Baseline Models'!$B$86:$C$90,3,1) -> 0.35190494
A96: Adjusted R² | B96: =1-(1-'Baseline Models'!$B$95)*('Baseline Models'!$B$98-1)/'Baseline Models'!$B$100 -> 0.35143666
A97: Standard error | B97: =INDEX('Baseline Models'!$B$86:$C$90,3,2) -> 89.391086
A98: Observations | B98: =COUNT('Analysis Data'!$C$2:$C$1387) -> 1386
A99: k (predictors) | B99: =1 -> 1
A100: df residual | B100: =INDEX('Baseline Models'!$B$86:$C$90,4,2) -> 1384
A101: F-statistic | B101: =INDEX('Baseline Models'!$B$86:$C$90,4,1) -> 751.48918
A102: Significance F (model p-value) | B102: =_xlfn.F.DIST.RT('Baseline Models'!$B$101,'Baseline Models'!$B$99,'Baseline Models'!$B$100) -> 1.6274053e-132
A103: SS regression | B103: =INDEX('Baseline Models'!$B$86:$C$90,5,1) -> 6004974.4
A104: SS residual | B104: =INDEX('Baseline Models'!$B$86:$C$90,5,2) -> 11059220
A105: SS total | B105: ='Baseline Models'!$B$103+'Baseline Models'!$B$104 -> 17064195
A107: OUTPUT: Coefficient table (t = b/SE; p = two-tailed T.DIST.2T; 95% CI = b ± T.INV.2T(0.05,df)·SE)
A108: Variable | B108: Coefficient | C108: Std error | D108: t-stat | E108: p-value | F108: Lower 95% | G108: Upper 95%
A109: Intercept | B109: =INDEX('Baseline Models'!$B$86:$C$90,1,2) -> 240.69579 | C109: =INDEX('Baseline Models'!$B$86:$C$90,2,2) -> 2.4483818 | D109: =B109/C109 -> 98.308113 | E109: =_xlfn.T.DIST.2T(ABS(D109),'Baseline Models'!$B$100) -> 0 | F109: =B109-_xlfn.T.INV.2T(0.05,'Baseline Models'!$B$100)*C109 -> 235.89285 | G109: =B109+_xlfn.T.INV.2T(0.05,'Baseline Models'!$B$100)*C109 -> 245.49873
A110: Endcap | B110: =INDEX('Baseline Models'!$B$86:$C$90,1,1) -> 343.22917 | C110: =INDEX('Baseline Models'!$B$86:$C$90,2,1) -> 12.520533 | D110: =B110/C110 -> 27.413303 | E110: =_xlfn.T.DIST.2T(ABS(D110),'Baseline Models'!$B$100) -> 1.6274053e-132 | F110: =B110-_xlfn.T.INV.2T(0.05,'Baseline Models'!$B$100)*C110 -> 318.66789 | G110: =B110+_xlfn.T.INV.2T(0.05,'Baseline Models'!$B$100)*C110 -> 367.79044

Sheet Full MLR
A1: Model 1: Full business-driven MLR (no interaction)
A2: Sales = b0 + b1 Price + b2 Rep + b3 Endcap + b4 Demo + b5 Demo1-3 + b6 Demo4-5 + b7 Natural + b8 Fitness
A4: INPUTS
A5: Dependent (Y) range | B5: 'Analysis Data'!C2:C1387
A6: Predictor (X) range | B6: 'Analysis Data'!D2:K1387
A8: CALCULATION: LINEST(Y,X,TRUE,TRUE) raw array (coefficients appear in REVERSE variable order; last column = intercept)
B9: Fitness | C9: Natural | D9: D45 | E9: D13 | F9: Demo | G9: Endcap | H9: Rep | I9: Price | J9: Intercept
A10: Coefficient | B10: {=IFERROR(LINEST('Analysis Data'!$C$2:$C$1387,'Analysis Data'!$D$2:$K$1387,TRUE(),TRUE()),"")} -> -1.0196712 | C10: -1.5941682 | D10: 67.569811 | E10: 73.517171 | F10: 111.13285 | G10: 305.10212 | H10: 77.436914 | I10: -28.535365 | J10: 298.48813
A11: Std error | B11: 1.0840229 | C11: 1.7764007 | D11: 6.5419732 | E11: 4.8953839 | F11: 7.4036983 | G11: 9.0557374 | H11: 3.8644528 | I11: 3.9521527 | J11: 16.183094
A12: R² | SE(y) | B12: 0.67263527 | C12: 63.693025
A13: F | df | B13: 353.66468 | C13: 1377
A14: SSreg | SSres | B14: 11477979 | C14: 5586215.6
A17: OUTPUT: Regression statistics
A18: Multiple R | B18: =SQRT(INDEX('Full MLR'!$B$10:$J$14,3,1)) -> 0.82014344
A19: R² | B19: =INDEX('Full MLR'!$B$10:$J$14,3,1) -> 0.67263527
A20: Adjusted R² | B20: =1-(1-'Full MLR'!$B$19)*('Full MLR'!$B$22-1)/'Full MLR'!$B$24 -> 0.67073336
A21: Standard error | B21: =INDEX('Full MLR'!$B$10:$J$14,3,2) -> 63.693025
A22: Observations | B22: =COUNT('Analysis Data'!$C$2:$C$1387) -> 1386
A23: k (predictors) | B23: =8 -> 8
A24: df residual | B24: =INDEX('Full MLR'!$B$10:$J$14,4,2) -> 1377
A25: F-statistic | B25: =INDEX('Full MLR'!$B$10:$J$14,4,1) -> 353.66468
A26: Significance F (model p-value) | B26: =_xlfn.F.DIST.RT('Full MLR'!$B$25,'Full MLR'!$B$23,'Full MLR'!$B$24) -> 0
A27: SS regression | B27: =INDEX('Full MLR'!$B$10:$J$14,5,1) -> 11477979
A28: SS residual | B28: =INDEX('Full MLR'!$B$10:$J$14,5,2) -> 5586215.6
A29: SS total | B29: ='Full MLR'!$B$27+'Full MLR'!$B$28 -> 17064195
A31: OUTPUT: Coefficient table (t = b/SE; p = two-tailed T.DIST.2T; 95% CI = b ± T.INV.2T(0.05,df)·SE)
A32: Variable | B32: Coefficient | C32: Std error | D32: t-stat | E32: p-value | F32: Lower 95% | G32: Upper 95%
A33: Intercept | B33: =INDEX('Full MLR'!$B$10:$J$14,1,9) -> 298.48813 | C33: =INDEX('Full MLR'!$B$10:$J$14,2,9) -> 16.183094 | D33: =B33/C33 -> 18.444442 | E33: =_xlfn.T.DIST.2T(ABS(D33),'Full MLR'!$B$24) -> 4.6234257e-68 | F33: =B33-_xlfn.T.INV.2T(0.05,'Full MLR'!$B$24)*C33 -> 266.74195 | G33: =B33+_xlfn.T.INV.2T(0.05,'Full MLR'!$B$24)*C33 -> 330.23432
A34: Price | B34: =INDEX('Full MLR'!$B$10:$J$14,1,8) -> -28.535365 | C34: =INDEX('Full MLR'!$B$10:$J$14,2,8) -> 3.9521527 | D34: =B34/C34 -> -7.2202082 | E34: =_xlfn.T.DIST.2T(ABS(D34),'Full MLR'!$B$24) -> 8.5557844e-13 | F34: =B34-_xlfn.T.INV.2T(0.05,'Full MLR'!$B$24)*C34 -> -36.288257 | G34: =B34+_xlfn.T.INV.2T(0.05,'Full MLR'!$B$24)*C34 -> -20.782474
A35: Rep | B35: =INDEX('Full MLR'!$B$10:$J$14,1,7) -> 77.436914 | C35: =INDEX('Full MLR'!$B$10:$J$14,2,7) -> 3.8644528 | D35: =B35/C35 -> 20.038261 | E35: =_xlfn.T.DIST.2T(ABS(D35),'Full MLR'!$B$24) -> 1.3901294e-78 | F35: =B35-_xlfn.T.INV.2T(0.05,'Full MLR'!$B$24)*C35 -> 69.856062 | G35: =B35+_xlfn.T.INV.2T(0.05,'Full MLR'!$B$24)*C35 -> 85.017765
A36: Endcap | B36: =INDEX('Full MLR'!$B$10:$J$14,1,6) -> 305.10212 | C36: =INDEX('Full MLR'!$B$10:$J$14,2,6) -> 9.0557374 | D36: =B36/C36 -> 33.691582 | E36: =_xlfn.T.DIST.2T(ABS(D36),'Full MLR'!$B$24) -> 5.4001244e-182 | F36: =B36-_xlfn.T.INV.2T(0.05,'Full MLR'!$B$24)*C36 -> 287.33759 | G36: =B36+_xlfn.T.INV.2T(0.05,'Full MLR'!$B$24)*C36 -> 322.86666
A37: Demo | B37: =INDEX('Full MLR'!$B$10:$J$14,1,5) -> 111.13285 | C37: =INDEX('Full MLR'!$B$10:$J$14,2,5) -> 7.4036983 | D37: =B37/C37 -> 15.010451 | E37: =_xlfn.T.DIST.2T(ABS(D37),'Full MLR'!$B$24) -> 2.7785284e-47 | F37: =B37-_xlfn.T.INV.2T(0.05,'Full MLR'!$B$24)*C37 -> 96.609101 | G37: =B37+_xlfn.T.INV.2T(0.05,'Full MLR'!$B$24)*C37 -> 125.6566
A38: D13 | B38: =INDEX('Full MLR'!$B$10:$J$14,1,4) -> 73.517171 | C38: =INDEX('Full MLR'!$B$10:$J$14,2,4) -> 4.8953839 | D38: =B38/C38 -> 15.017652 | E38: =_xlfn.T.DIST.2T(ABS(D38),'Full MLR'!$B$24) -> 2.5309771e-47 | F38: =B38-_xlfn.T.INV.2T(0.05,'Full MLR'!$B$24)*C38 -> 63.913954 | G38: =B38+_xlfn.T.INV.2T(0.05,'Full MLR'!$B$24)*C38 -> 83.120388
A39: D45 | B39: =INDEX('Full MLR'!$B$10:$J$14,1,3) -> 67.569811 | C39: =INDEX('Full MLR'!$B$10:$J$14,2,3) -> 6.5419732 | D39: =B39/C39 -> 10.328659 | E39: =_xlfn.T.DIST.2T(ABS(D39),'Full MLR'!$B$24) -> 3.873164e-24 | F39: =B39-_xlfn.T.INV.2T(0.05,'Full MLR'!$B$24)*C39 -> 54.736499 | G39: =B39+_xlfn.T.INV.2T(0.05,'Full MLR'!$B$24)*C39 -> 80.403123
A40: Natural | B40: =INDEX('Full MLR'!$B$10:$J$14,1,2) -> -1.5941682 | C40: =INDEX('Full MLR'!$B$10:$J$14,2,2) -> 1.7764007 | D40: =B40/C40 -> -0.89741477 | E40: =_xlfn.T.DIST.2T(ABS(D40),'Full MLR'!$B$24) -> 0.36965451 | F40: =B40-_xlfn.T.INV.2T(0.05,'Full MLR'!$B$24)*C40 -> -5.0789126 | G40: =B40+_xlfn.T.INV.2T(0.05,'Full MLR'!$B$24)*C40 -> 1.8905762
A41: Fitness | B41: =INDEX('Full MLR'!$B$10:$J$14,1,1) -> -1.0196712 | C41: =INDEX('Full MLR'!$B$10:$J$14,2,1) -> 1.0840229 | D41: =B41/C41 -> -0.94063617 | E41: =_xlfn.T.DIST.2T(ABS(D41),'Full MLR'!$B$24) -> 0.34705632 | F41: =B41-_xlfn.T.INV.2T(0.05,'Full MLR'!$B$24)*C41 -> -3.1461861 | G41: =B41+_xlfn.T.INV.2T(0.05,'Full MLR'!$B$24)*C41 -> 1.1068438

Sheet Variable Selection
A1: Model 2: after variable selection (Natural, Fitness removed), no interaction
A2: Predictors retained by forward stepwise (p-in 0.05 / p-out 0.10) and by backward elimination on the no-interaction pool.
A4: INPUTS
A5: Dependent (Y) range | B5: 'Analysis Data'!C2:C1387
A6: Predictor (X) range | B6: 'Analysis Data'!D2:I1387
A8: CALCULATION: LINEST(Y,X,TRUE,TRUE) raw array (coefficients appear in REVERSE variable order; last column = intercept)
B9: D45 | C9: D13 | D9: Demo | E9: Endcap | F9: Rep | G9: Price | H9: Intercept
A10: Coefficient | B10: {=IFERROR(LINEST('Analysis Data'!$C$2:$C$1387,'Analysis Data'!$D$2:$I$1387,TRUE(),TRUE()),"")} -> 67.700203 | C10: 73.663094 | D10: 111.26053 | E10: 304.95972 | F10: 76.951206 | G10: -28.609165 | H10: 294.18904
A11: Std error | B11: 6.5392132 | C11: 4.8912512 | D11: 7.4009667 | E11: 9.0142802 | F11: 3.8408042 | G11: 3.9447142 | H11: 15.787096
A12: R² | SE(y) | B12: 0.67226502 | C12: 63.682803
A13: F | df | B13: 471.44467 | C13: 1379
A14: SSreg | SSres | B14: 11471661 | C14: 5592533.6
A17: OUTPUT: Regression statistics
A18: Multiple R | B18: =SQRT(INDEX('Variable Selection'!$B$10:$H$14,3,1)) -> 0.81991769
A19: R² | B19: =INDEX('Variable Selection'!$B$10:$H$14,3,1) -> 0.67226502
A20: Adjusted R² | B20: =1-(1-'Variable Selection'!$B$19)*('Variable Selection'!$B$22-1)/'Variable Selection'!$B$24 -> 0.67083905
A21: Standard error | B21: =INDEX('Variable Selection'!$B$10:$H$14,3,2) -> 63.682803
A22: Observations | B22: =COUNT('Analysis Data'!$C$2:$C$1387) -> 1386
A23: k (predictors) | B23: =6 -> 6
A24: df residual | B24: =INDEX('Variable Selection'!$B$10:$H$14,4,2) -> 1379
A25: F-statistic | B25: =INDEX('Variable Selection'!$B$10:$H$14,4,1) -> 471.44467
A26: Significance F (model p-value) | B26: =_xlfn.F.DIST.RT('Variable Selection'!$B$25,'Variable Selection'!$B$23,'Variable Selection'!$B$24) -> 0
A27: SS regression | B27: =INDEX('Variable Selection'!$B$10:$H$14,5,1) -> 11471661
A28: SS residual | B28: =INDEX('Variable Selection'!$B$10:$H$14,5,2) -> 5592533.6
A29: SS total | B29: ='Variable Selection'!$B$27+'Variable Selection'!$B$28 -> 17064195
A31: OUTPUT: Coefficient table (t = b/SE; p = two-tailed T.DIST.2T; 95% CI = b ± T.INV.2T(0.05,df)·SE)
A32: Variable | B32: Coefficient | C32: Std error | D32: t-stat | E32: p-value | F32: Lower 95% | G32: Upper 95%
A33: Intercept | B33: =INDEX('Variable Selection'!$B$10:$H$14,1,7) -> 294.18904 | C33: =INDEX('Variable Selection'!$B$10:$H$14,2,7) -> 15.787096 | D33: =B33/C33 -> 18.634779 | E33: =_xlfn.T.DIST.2T(ABS(D33),'Variable Selection'!$B$24) -> 2.6593234e-69 | F33: =B33-_xlfn.T.INV.2T(0.05,'Variable Selection'!$B$24)*C33 -> 263.21971 | G33: =B33+_xlfn.T.INV.2T(0.05,'Variable Selection'!$B$24)*C33 -> 325.15836
A34: Price | B34: =INDEX('Variable Selection'!$B$10:$H$14,1,6) -> -28.609165 | C34: =INDEX('Variable Selection'!$B$10:$H$14,2,6) -> 3.9447142 | D34: =B34/C34 -> -7.2525317 | E34: =_xlfn.T.DIST.2T(ABS(D34),'Variable Selection'!$B$24) -> 6.7964865e-13 | F34: =B34-_xlfn.T.INV.2T(0.05,'Variable Selection'!$B$24)*C34 -> -36.347454 | G34: =B34+_xlfn.T.INV.2T(0.05,'Variable Selection'!$B$24)*C34 -> -20.870875
A35: Rep | B35: =INDEX('Variable Selection'!$B$10:$H$14,1,5) -> 76.951206 | C35: =INDEX('Variable Selection'!$B$10:$H$14,2,5) -> 3.8408042 | D35: =B35/C35 -> 20.035181 | E35: =_xlfn.T.DIST.2T(ABS(D35),'Variable Selection'!$B$24) -> 1.4149284e-78 | F35: =B35-_xlfn.T.INV.2T(0.05,'Variable Selection'!$B$24)*C35 -> 69.416755 | G35: =B35+_xlfn.T.INV.2T(0.05,'Variable Selection'!$B$24)*C35 -> 84.485657
A36: Endcap | B36: =INDEX('Variable Selection'!$B$10:$H$14,1,4) -> 304.95972 | C36: =INDEX('Variable Selection'!$B$10:$H$14,2,4) -> 9.0142802 | D36: =B36/C36 -> 33.830734 | E36: =_xlfn.T.DIST.2T(ABS(D36),'Variable Selection'!$B$24) -> 3.5438091e-183 | F36: =B36-_xlfn.T.INV.2T(0.05,'Variable Selection'!$B$24)*C36 -> 287.27653 | G36: =B36+_xlfn.T.INV.2T(0.05,'Variable Selection'!$B$24)*C36 -> 322.6429
A37: Demo | B37: =INDEX('Variable Selection'!$B$10:$H$14,1,3) -> 111.26053 | C37: =INDEX('Variable Selection'!$B$10:$H$14,2,3) -> 7.4009667 | D37: =B37/C37 -> 15.033243 | E37: =_xlfn.T.DIST.2T(ABS(D37),'Variable Selection'!$B$24) -> 2.0449656e-47 | F37: =B37-_xlfn.T.INV.2T(0.05,'Variable Selection'!$B$24)*C37 -> 96.742163 | G37: =B37+_xlfn.T.INV.2T(0.05,'Variable Selection'!$B$24)*C37 -> 125.7789
A38: D13 | B38: =INDEX('Variable Selection'!$B$10:$H$14,1,2) -> 73.663094 | C38: =INDEX('Variable Selection'!$B$10:$H$14,2,2) -> 4.8912512 | D38: =B38/C38 -> 15.060174 | E38: =_xlfn.T.DIST.2T(ABS(D38),'Variable Selection'!$B$24) -> 1.4416497e-47 | F38: =B38-_xlfn.T.INV.2T(0.05,'Variable Selection'!$B$24)*C38 -> 64.067996 | G38: =B38+_xlfn.T.INV.2T(0.05,'Variable Selection'!$B$24)*C38 -> 83.258192
A39: D45 | B39: =INDEX('Variable Selection'!$B$10:$H$14,1,1) -> 67.700203 | C39: =INDEX('Variable Selection'!$B$10:$H$14,2,1) -> 6.5392132 | D39: =B39/C39 -> 10.352959 | E39: =_xlfn.T.DIST.2T(ABS(D39),'Variable Selection'!$B$24) -> 3.0525429e-24 | F39: =B39-_xlfn.T.INV.2T(0.05,'Variable Selection'!$B$24)*C39 -> 54.872322 | G39: =B39+_xlfn.T.INV.2T(0.05,'Variable Selection'!$B$24)*C39 -> 80.528084
A43: PARTIAL F-TEST: are Natural Retailers and Fitness Centers jointly needed? (Model 1 vs Model 2)
A44: Partial F = [(R²full - R²reduced)/q] / [(1 - R²full)/df_full]
A45: q (variables dropped) | B45: 2
A46: Partial F | B46: =(('Full MLR'!$B$19-'Variable Selection'!$B$19)/B45)/((1-'Full MLR'!$B$19)/'Full MLR'!$B$24) -> 0.77869214
A47: p-value | B47: =_xlfn.F.DIST.RT(B46,B45,'Full MLR'!$B$24) -> 0.45920795
A48: Decision (p-out = 0.10) | B48: =IF(B47>0.1,"Remove both","Keep") -> Remove both
A51: STEPWISE / BACKWARD LOG (computed in Python/statsmodels with partial F-tests; course rule p-in 0.05, p-out 0.10). Static values.
A52: A. Forward stepwise - pool of 8 predictors (no interaction)
A53: Step | B53: Action | C53: Variable | D53: Partial F | E53: p-value | F53: R² | G53: Adj R²
A54: 1 | B54: Enter | C54: Endcap | D54: 751.48918 | E54: 1.6274053e-132 | F54: 0.35190494 | G54: 0.35143666
A55: 2 | B55: Enter | C55: Rep | D55: 514.583 | E55: 4.1369646e-97 | F55: 0.52765414 | G55: 0.52697107
A56: 3 | B56: Enter | C56: D13 | D56: 190.67108 | E56: 1.0041687e-40 | F56: 0.58492148 | G56: 0.58402045
A57: 4 | B57: Enter | C57: Demo | D57: 192.76966 | E57: 3.9934913e-41 | F57: 0.63576409 | G57: 0.63470909
A58: 5 | B58: Enter | C58: D45 | D58: 97.344788 | E58: 3.1062999e-22 | F58: 0.65976422 | G58: 0.65853148
A59: 6 | B59: Enter | C59: Price | D59: 52.599216 | E59: 6.7964865e-13 | F59: 0.67226502 | G59: 0.67083905
A60: Final set: Endcap, Rep, D13, Demo, D45, Price
A63: B. Forward stepwise - pool of 8 predictors + Endcap x Rep
A64: Step | B64: Action | C64: Variable | D64: Partial F | E64: p-value | F64: R² | G64: Adj R²
A65: 1 | B65: Enter | C65: EndRep | D65: 1679.3225 | E65: 4.81252e-241 | F65: 0.54820298 | G65: 0.54787654
A66: 2 | B66: Enter | C66: Rep | D66: 490.0203 | E66: 3.444643e-93 | F66: 0.66640229 | G66: 0.66591986
A67: 3 | B67: Enter | C67: D13 | D67: 277.20125 | E67: 7.23455e-57 | F67: 0.72213616 | G67: 0.72153298
A68: 4 | B68: Enter | C68: Demo | D68: 278.27504 | E68: 4.6562418e-57 | F68: 0.76873637 | G68: 0.76806653
A69: 5 | B69: Enter | C69: D45 | D69: 203.49251 | E69: 3.6047174e-43 | F69: 0.79845575 | G69: 0.79772552
A70: 6 | B70: Enter | C70: Price | D70: 52.564254 | E70: 6.9140345e-13 | F70: 0.80585606 | G70: 0.80501135
A71: Final set: EndRep, Rep, D13, Demo, D45, Price
A74: C. Backward elimination (p-out 0.10) - 9 candidates incl. interaction
A75: Step | B75: Action | C75: Variable | D75: Partial F | E75: p-value | F75: R² | G75: Adj R²
A76: 1 | B76: Remove | C76: Endcap | D76: 0.001474224 | E76: 0.96937782 | F76: 0.80586819 | G76: 0.80474033
A77: 2 | B77: Remove | C77: Natural | D77: 0.0253602 | E77: 0.87349616 | F77: 0.80586461 | G77: 0.80487844
A78: 3 | B78: Remove | C78: Fitness | D78: 0.060681332 | E78: 0.80545898 | F78: 0.80585606 | G78: 0.80501135
A79: Final set: Price, Rep, Demo, D13, D45, EndRep
A82: Judgement: stepwise B and backward elimination drop the Endcap MAIN effect (p=0.96) once the interaction is present. The final model keeps the main effect because (i) the course keeps main effects alongside an interaction, (ii) the Endcap coefficient is then directly interpretable as the Endcap effect where Sales Rep = 0, and (iii) dropping it changes nothing material (see Model Comparison and Interaction Analysis).

Sheet Interaction Analysis
A1: Model 3: Full MLR + Endcap x Sales Rep
A2: Interaction variable EndRep = Endcap x Sales Rep (Analysis Data column L).
A4: INPUTS
A5: Dependent (Y) range | B5: 'Analysis Data'!C2:C1387
A6: Predictor (X) range | B6: 'Analysis Data'!D2:L1387
A8: CALCULATION: LINEST(Y,X,TRUE,TRUE) raw array (coefficients appear in REVERSE variable order; last column = intercept)
B9: EndRep | C9: Fitness | D9: Natural | E9: D45 | F9: D13 | G9: Demo | H9: Endcap | I9: Rep | J9: Price | K9: Intercept
A10: Coefficient | B10: {=IFERROR(LINEST('Analysis Data'!$C$2:$C$1387,'Analysis Data'!$D$2:$L$1387,TRUE(),TRUE()),"")} -> 454.06397 | C10: 0.21625304 | D10: 0.2133152 | E10: 74.584401 | F10: 73.387812 | G10: 106.76653 | H10: 0.46542443 | I10: 59.375305 | J10: -22.087416 | K10: 275.85608
A11: Std error | B11: 14.77576 | C11: 0.8360485 | D11: 1.3697195 | E11: 5.0447972 | F11: 3.7711773 | G11: 5.7052327 | H11: 12.121809 | I11: 3.0344582 | J11: 3.0517754 | K11: 12.488434
A12: R² | SE(y) | B12: 0.8058684 | C12: 49.06613
A13: F | df | B13: 634.66392 | C13: 1376
A14: SSreg | SSres | B14: 13751495 | C14: 3312699.5
A17: OUTPUT: Regression statistics
A18: Multiple R | B18: =SQRT(INDEX('Interaction Analysis'!$B$10:$K$14,3,1)) -> 0.89770173
A19: R² | B19: =INDEX('Interaction Analysis'!$B$10:$K$14,3,1) -> 0.8058684
A20: Adjusted R² | B20: =1-(1-'Interaction Analysis'!$B$19)*('Interaction Analysis'!$B$22-1)/'Interaction Analysis'!$B$24 -> 0.80459864
A21: Standard error | B21: =INDEX('Interaction Analysis'!$B$10:$K$14,3,2) -> 49.06613
A22: Observations | B22: =COUNT('Analysis Data'!$C$2:$C$1387) -> 1386
A23: k (predictors) | B23: =9 -> 9
A24: df residual | B24: =INDEX('Interaction Analysis'!$B$10:$K$14,4,2) -> 1376
A25: F-statistic | B25: =INDEX('Interaction Analysis'!$B$10:$K$14,4,1) -> 634.66392
A26: Significance F (model p-value) | B26: =_xlfn.F.DIST.RT('Interaction Analysis'!$B$25,'Interaction Analysis'!$B$23,'Interaction Analysis'!$B$24) -> 0
A27: SS regression | B27: =INDEX('Interaction Analysis'!$B$10:$K$14,5,1) -> 13751495
A28: SS residual | B28: =INDEX('Interaction Analysis'!$B$10:$K$14,5,2) -> 3312699.5
A29: SS total | B29: ='Interaction Analysis'!$B$27+'Interaction Analysis'!$B$28 -> 17064195
A31: OUTPUT: Coefficient table (t = b/SE; p = two-tailed T.DIST.2T; 95% CI = b ± T.INV.2T(0.05,df)·SE)
A32: Variable | B32: Coefficient | C32: Std error | D32: t-stat | E32: p-value | F32: Lower 95% | G32: Upper 95%
A33: Intercept | B33: =INDEX('Interaction Analysis'!$B$10:$K$14,1,10) -> 275.85608 | C33: =INDEX('Interaction Analysis'!$B$10:$K$14,2,10) -> 12.488434 | D33: =B33/C33 -> 22.088925 | E33: =_xlfn.T.DIST.2T(ABS(D33),'Interaction Analysis'!$B$24) -> 8.6722552e-93 | F33: =B33-_xlfn.T.INV.2T(0.05,'Interaction Analysis'!$B$24)*C33 -> 251.35765 | G33: =B33+_xlfn.T.INV.2T(0.05,'Interaction Analysis'!$B$24)*C33 -> 300.35451
A34: Price | B34: =INDEX('Interaction Analysis'!$B$10:$K$14,1,9) -> -22.087416 | C34: =INDEX('Interaction Analysis'!$B$10:$K$14,2,9) -> 3.0517754 | D34: =B34/C34 -> -7.2375628 | E34: =_xlfn.T.DIST.2T(ABS(D34),'Interaction Analysis'!$B$24) -> 7.5675458e-13 | F34: =B34-_xlfn.T.INV.2T(0.05,'Interaction Analysis'!$B$24)*C34 -> -28.074052 | G34: =B34+_xlfn.T.INV.2T(0.05,'Interaction Analysis'!$B$24)*C34 -> -16.10078
A35: Rep | B35: =INDEX('Interaction Analysis'!$B$10:$K$14,1,8) -> 59.375305 | C35: =INDEX('Interaction Analysis'!$B$10:$K$14,2,8) -> 3.0344582 | D35: =B35/C35 -> 19.56702 | E35: =_xlfn.T.DIST.2T(ABS(D35),'Interaction Analysis'!$B$24) -> 2.0487046e-75 | F35: =B35-_xlfn.T.INV.2T(0.05,'Interaction Analysis'!$B$24)*C35 -> 53.42264 | G35: =B35+_xlfn.T.INV.2T(0.05,'Interaction Analysis'!$B$24)*C35 -> 65.32797
A36: Endcap | B36: =INDEX('Interaction Analysis'!$B$10:$K$14,1,7) -> 0.46542443 | C36: =INDEX('Interaction Analysis'!$B$10:$K$14,2,7) -> 12.121809 | D36: =B36/C36 -> 0.038395625 | E36: =_xlfn.T.DIST.2T(ABS(D36),'Interaction Analysis'!$B$24) -> 0.96937782 | F36: =B36-_xlfn.T.INV.2T(0.05,'Interaction Analysis'!$B$24)*C36 -> -23.313801 | G36: =B36+_xlfn.T.INV.2T(0.05,'Interaction Analysis'!$B$24)*C36 -> 24.24465
A37: Demo | B37: =INDEX('Interaction Analysis'!$B$10:$K$14,1,6) -> 106.76653 | C37: =INDEX('Interaction Analysis'!$B$10:$K$14,2,6) -> 5.7052327 | D37: =B37/C37 -> 18.713791 | E37: =_xlfn.T.DIST.2T(ABS(D37),'Interaction Analysis'!$B$24) -> 8.4619323e-70 | F37: =B37-_xlfn.T.INV.2T(0.05,'Interaction Analysis'!$B$24)*C37 -> 95.574637 | G37: =B37+_xlfn.T.INV.2T(0.05,'Interaction Analysis'!$B$24)*C37 -> 117.95843
A38: D13 | B38: =INDEX('Interaction Analysis'!$B$10:$K$14,1,5) -> 73.387812 | C38: =INDEX('Interaction Analysis'!$B$10:$K$14,2,5) -> 3.7711773 | D38: =B38/C38 -> 19.460186 | E38: =_xlfn.T.DIST.2T(ABS(D38),'Interaction Analysis'!$B$24) -> 1.0530993e-74 | F38: =B38-_xlfn.T.INV.2T(0.05,'Interaction Analysis'!$B$24)*C38 -> 65.989933 | G38: =B38+_xlfn.T.INV.2T(0.05,'Interaction Analysis'!$B$24)*C38 -> 80.785691
A39: D45 | B39: =INDEX('Interaction Analysis'!$B$10:$K$14,1,4) -> 74.584401 | C39: =INDEX('Interaction Analysis'!$B$10:$K$14,2,4) -> 5.0447972 | D39: =B39/C39 -> 14.78442 | E39: =_xlfn.T.DIST.2T(ABS(D39),'Interaction Analysis'!$B$24) -> 5.1416344e-46 | F39: =B39-_xlfn.T.INV.2T(0.05,'Interaction Analysis'!$B$24)*C39 -> 64.688075 | G39: =B39+_xlfn.T.INV.2T(0.05,'Interaction Analysis'!$B$24)*C39 -> 84.480726
A40: Natural | B40: =INDEX('Interaction Analysis'!$B$10:$K$14,1,3) -> 0.2133152 | C40: =INDEX('Interaction Analysis'!$B$10:$K$14,2,3) -> 1.3697195 | D40: =B40/C40 -> 0.15573641 | E40: =_xlfn.T.DIST.2T(ABS(D40),'Interaction Analysis'!$B$24) -> 0.87626364 | F40: =B40-_xlfn.T.INV.2T(0.05,'Interaction Analysis'!$B$24)*C40 -> -2.4736492 | G40: =B40+_xlfn.T.INV.2T(0.05,'Interaction Analysis'!$B$24)*C40 -> 2.9002796
A41: Fitness | B41: =INDEX('Interaction Analysis'!$B$10:$K$14,1,2) -> 0.21625304 | C41: =INDEX('Interaction Analysis'!$B$10:$K$14,2,2) -> 0.8360485 | D41: =B41/C41 -> 0.25866088 | E41: =_xlfn.T.DIST.2T(ABS(D41),'Interaction Analysis'!$B$24) -> 0.79593559 | F41: =B41-_xlfn.T.INV.2T(0.05,'Interaction Analysis'!$B$24)*C41 -> -1.4238145 | G41: =B41+_xlfn.T.INV.2T(0.05,'Interaction Analysis'!$B$24)*C41 -> 1.8563206
A42: EndRep | B42: =INDEX('Interaction Analysis'!$B$10:$K$14,1,1) -> 454.06397 | C42: =INDEX('Interaction Analysis'!$B$10:$K$14,2,1) -> 14.77576 | D42: =B42/C42 -> 30.730329 | E42: =_xlfn.T.DIST.2T(ABS(D42),'Interaction Analysis'!$B$24) -> 2.4864291e-158 | F42: =B42-_xlfn.T.INV.2T(0.05,'Interaction Analysis'!$B$24)*C42 -> 425.07852 | G42: =B42+_xlfn.T.INV.2T(0.05,'Interaction Analysis'!$B$24)*C42 -> 483.04943
A46: Restricted model: final model WITHOUT Endcap main effect
A47: Price, Rep, Demo, Demo1-3, Demo4-5, EndRep (Analysis Data AC:AH)
A49: INPUTS
A50: Dependent (Y) range | B50: 'Analysis Data'!C2:C1387
A51: Predictor (X) range | B51: 'Analysis Data'!AC2:AH1387
A53: CALCULATION: LINEST(Y,X,TRUE,TRUE) raw array (coefficients appear in REVERSE variable order; last column = intercept)
B54: EndRep | C54: D45 | D54: D13 | E54: Demo | F54: Rep | G54: Price | H54: Intercept
A55: Coefficient | B55: {=IFERROR(LINEST('Analysis Data'!$C$2:$C$1387,'Analysis Data'!$AC$2:$AH$1387,TRUE(),TRUE()),"")} -> 454.42284 | C55: 74.561374 | D55: 73.377352 | E55: 106.75871 | F55: 59.44196 | G55: -22.064787 | H55: 276.58334
A56: Std error | B56: 8.4662594 | C56: 5.0345727 | D56: 3.7617506 | E56: 5.6969274 | F56: 2.98539 | G56: 3.0433681 | H56: 12.162682
A57: R² | SE(y) | B57: 0.80585606 | C57: 49.014286
A58: F | df | B58: 953.99624 | C58: 1379
A59: SSreg | SSres | B59: 13751285 | C59: 3312910
A62: OUTPUT: Regression statistics
A63: Multiple R | B63: =SQRT(INDEX('Interaction Analysis'!$B$55:$H$59,3,1)) -> 0.89769486
A64: R² | B64: =INDEX('Interaction Analysis'!$B$55:$H$59,3,1) -> 0.80585606
A65: Adjusted R² | B65: =1-(1-'Interaction Analysis'!$B$64)*('Interaction Analysis'!$B$67-1)/'Interaction Analysis'!$B$69 -> 0.80501135
A66: Standard error | B66: =INDEX('Interaction Analysis'!$B$55:$H$59,3,2) -> 49.014286
A67: Observations | B67: =COUNT('Analysis Data'!$C$2:$C$1387) -> 1386
A68: k (predictors) | B68: =6 -> 6
A69: df residual | B69: =INDEX('Interaction Analysis'!$B$55:$H$59,4,2) -> 1379
A70: F-statistic | B70: =INDEX('Interaction Analysis'!$B$55:$H$59,4,1) -> 953.99624
A71: Significance F (model p-value) | B71: =_xlfn.F.DIST.RT('Interaction Analysis'!$B$70,'Interaction Analysis'!$B$68,'Interaction Analysis'!$B$69) -> 0
A72: SS regression | B72: =INDEX('Interaction Analysis'!$B$55:$H$59,5,1) -> 13751285
A73: SS residual | B73: =INDEX('Interaction Analysis'!$B$55:$H$59,5,2) -> 3312910
A74: SS total | B74: ='Interaction Analysis'!$B$72+'Interaction Analysis'!$B$73 -> 17064195
A76: OUTPUT: Coefficient table (t = b/SE; p = two-tailed T.DIST.2T; 95% CI = b ± T.INV.2T(0.05,df)·SE)
A77: Variable | B77: Coefficient | C77: Std error | D77: t-stat | E77: p-value | F77: Lower 95% | G77: Upper 95%
A78: Intercept | B78: =INDEX('Interaction Analysis'!$B$55:$H$59,1,7) -> 276.58334 | C78: =INDEX('Interaction Analysis'!$B$55:$H$59,2,7) -> 12.162682 | D78: =B78/C78 -> 22.740325 | E78: =_xlfn.T.DIST.2T(ABS(D78),'Interaction Analysis'!$B$69) -> 1.7950718e-97 | F78: =B78-_xlfn.T.INV.2T(0.05,'Interaction Analysis'!$B$69)*C78 -> 252.72398 | G78: =B78+_xlfn.T.INV.2T(0.05,'Interaction Analysis'!$B$69)*C78 -> 300.4427
A79: Price | B79: =INDEX('Interaction Analysis'!$B$55:$H$59,1,6) -> -22.064787 | C79: =INDEX('Interaction Analysis'!$B$55:$H$59,2,6) -> 3.0433681 | D79: =B79/C79 -> -7.250121 | E79: =_xlfn.T.DIST.2T(ABS(D79),'Interaction Analysis'!$B$69) -> 6.9140345e-13 | F79: =B79-_xlfn.T.INV.2T(0.05,'Interaction Analysis'!$B$69)*C79 -> -28.034919 | G79: =B79+_xlfn.T.INV.2T(0.05,'Interaction Analysis'!$B$69)*C79 -> -16.094655
A80: Rep | B80: =INDEX('Interaction Analysis'!$B$55:$H$59,1,5) -> 59.44196 | C80: =INDEX('Interaction Analysis'!$B$55:$H$59,2,5) -> 2.98539 | D80: =B80/C80 -> 19.910953 | E80: =_xlfn.T.DIST.2T(ABS(D80),'Interaction Analysis'!$B$69) -> 9.741131e-78 | F80: =B80-_xlfn.T.INV.2T(0.05,'Interaction Analysis'!$B$69)*C80 -> 53.585563 | G80: =B80+_xlfn.T.INV.2T(0.05,'Interaction Analysis'!$B$69)*C80 -> 65.298357
A81: Demo | B81: =INDEX('Interaction Analysis'!$B$55:$H$59,1,4) -> 106.75871 | C81: =INDEX('Interaction Analysis'!$B$55:$H$59,2,4) -> 5.6969274 | D81: =B81/C81 -> 18.7397 | E81: =_xlfn.T.DIST.2T(ABS(D81),'Interaction Analysis'!$B$69) -> 5.5384308e-70 | F81: =B81-_xlfn.T.INV.2T(0.05,'Interaction Analysis'!$B$69)*C81 -> 95.583127 | G81: =B81+_xlfn.T.INV.2T(0.05,'Interaction Analysis'!$B$69)*C81 -> 117.93429
A82: D13 | B82: =INDEX('Interaction Analysis'!$B$55:$H$59,1,3) -> 73.377352 | C82: =INDEX('Interaction Analysis'!$B$55:$H$59,2,3) -> 3.7617506 | D82: =B82/C82 -> 19.506172 | E82: =_xlfn.T.DIST.2T(ABS(D82),'Interaction Analysis'!$B$69) -> 4.9969397e-75 | F82: =B82-_xlfn.T.INV.2T(0.05,'Interaction Analysis'!$B$69)*C82 -> 65.99798 | G82: =B82+_xlfn.T.INV.2T(0.05,'Interaction Analysis'!$B$69)*C82 -> 80.756725
A83: D45 | B83: =INDEX('Interaction Analysis'!$B$55:$H$59,1,2) -> 74.561374 | C83: =INDEX('Interaction Analysis'!$B$55:$H$59,2,2) -> 5.0345727 | D83: =B83/C83 -> 14.809871 | E83: =_xlfn.T.DIST.2T(ABS(D83),'Interaction Analysis'!$B$69) -> 3.6519115e-46 | F83: =B83-_xlfn.T.INV.2T(0.05,'Interaction Analysis'!$B$69)*C83 -> 64.685125 | G83: =B83+_xlfn.T.INV.2T(0.05,'Interaction Analysis'!$B$69)*C83 -> 84.437624
A84: EndRep | B84: =INDEX('Interaction Analysis'!$B$55:$H$59,1,1) -> 454.42284 | C84: =INDEX('Interaction Analysis'!$B$55:$H$59,2,1) -> 8.4662594 | D84: =B84/C84 -> 53.674571 | E84: =_xlfn.T.DIST.2T(ABS(D84),'Interaction Analysis'!$B$69) -> 0 | F84: =B84-_xlfn.T.INV.2T(0.05,'Interaction Analysis'!$B$69)*C84 -> 437.8147 | G84: =B84+_xlfn.T.INV.2T(0.05,'Interaction Analysis'!$B$69)*C84 -> 471.03098
A88: PARTIAL F-TEST FOR Endcap x Sales Rep
A89: Comparison | B89: R² restricted | C89: R² full | D89: q | E89: df full | F89: Partial F | G89: p-value | H89: Decision
A90: Model 1 -> Model 3 (add Endcap x Rep to full model) | B90: ='Full MLR'!$B$19 -> 0.67263527 | C90: ='Interaction Analysis'!$B$19 -> 0.8058684 | D90: 1 | E90: ='Interaction Analysis'!$B$24 -> 1376 | F90: =((C90-B90)/D90)/((1-C90)/E90) -> 944.35313 | G90: =_xlfn.F.DIST.RT(F90,D90,E90) -> 2.4864291e-158 | H90: =IF(G90<0.05,"Significant","Not significant") -> Significant
A91: Model 2 -> Final (add Endcap x Rep to reduced model) | B91: ='Variable Selection'!$B$19 -> 0.67226502 | C91: ='Final Model'!$B$19 -> 0.80585644 | D91: 1 | E91: ='Final Model'!$B$24 -> 1378 | F91: =((C91-B91)/D91)/((1-C91)/E91) -> 948.21055 | G91: =_xlfn.F.DIST.RT(F91,D91,E91) -> 7.0499844e-159 | H91: =IF(G91<0.05,"Significant","Not significant") -> Significant
A92: Final without Endcap main -> Final (is Endcap main effect needed?) | B92: ='Interaction Analysis'!$B$64 -> 0.80585606 | C92: ='Final Model'!$B$19 -> 0.80585644 | D92: 1 | E92: ='Final Model'!$B$24 -> 1378 | F92: =((C92-B92)/D92)/((1-C92)/E92) -> 0.002638815 | G92: =_xlfn.F.DIST.RT(F92,D92,E92) -> 0.95903861 | H92: =IF(G92<0.05,"Significant","Not significant") -> Not significant
A93: Final -> Model 3 (are Natural & Fitness needed given interaction?) | B93: ='Final Model'!$B$19 -> 0.80585644 | C93: ='Interaction Analysis'!$B$19 -> 0.8058684 | D93: 2 | E93: ='Interaction Analysis'!$B$24 -> 1376 | F93: =((C93-B93)/D93)/((1-C93)/E93) -> 0.042387664 | G93: =_xlfn.F.DIST.RT(F93,D93,E93) -> 0.95849938 | H93: =IF(G93<0.05,"Significant","Not significant") -> Not significant
A96: OTHER CANDIDATE INTERACTIONS (each added one at a time to the final model; Python partial F, static)
A97: Interaction | B97: Coefficient | C97: Partial F (1 df) | D97: p-value | E97: Adj R² with term
A98: Price x Sales Rep | B98: 4.6909807 | C98: 0.55535006 | D98: 0.45626704 | E98: 0.80480724
A99: Demo x Sales Rep | B99: -4.6045162 | C99: 0.086716347 | D99: 0.76843828 | E99: 0.80474081
A100: Demo1-3 x Sales Rep | B100: -11.18831 | C100: 1.4274319 | D100: 0.23238975 | E100: 0.80493073
A101: Demo4-5 x Sales Rep | B101: -8.4916325 | C101: 0.4885594 | D101: 0.48468867 | E101: 0.80479777
A102: Price x Endcap | B102: 6.4342728 | C102: 0.24021219 | D102: 0.62413098 | E102: 0.80476257
A103: Demo x Endcap | B103: 22.315774 | C103: 1.2405932 | D103: 0.26555115 | E103: 0.80490428
A106: INTERPRETATION TABLE (final model; price held at sample mean, no demo)
A107: Quantity | B107: Estimate | C107: Std error | D107: Meaning
A108: Endcap coefficient (Sales Rep = 0) | B108: ='Final Model'!$B$36 -> 0.62038277 | C108: ='Final Model'!$C$36 -> 12.076894 | D108: Endcap effect in stores WITHOUT a regional rep (only 17 such observations)
A109: Interaction coefficient | B109: ='Final Model'!$B$40 -> 453.8033 | C109: ='Final Model'!$C$40 -> 14.73721 | D109: Additional endcap effect when Sales Rep = 1
A110: Combined Endcap effect (Sales Rep = 1) | B110: ='Final Model'!$B$36+'Final Model'!$B$40 -> 454.42368 | C110: =SQRT('Final Model'!$B$21^2*('Final Model'!$E$62+'Final Model'!$I$66+2*'Final Model'!$I$62)) -> 8.4693385 | D110: Endcap effect in stores WITH a regional rep (36 observations)
A111: Predicted weekly units (price at mean, no demo):
A112: Cell | B112: Predicted units
A113: No rep, no endcap | B113: ='Final Model'!$B$33+'Final Model'!$B$34*AVERAGE('Analysis Data'!$D$2:$D$1387)+'Final Model'!$B$35*0+'Final Model'!$B$36*0+'Final Model'!$B$40*0 -> 185.94494
A114: No rep, endcap | B114: ='Final Model'!$B$33+'Final Model'!$B$34*AVERAGE('Analysis Data'!$D$2:$D$1387)+'Final Model'!$B$35*0+'Final Model'!$B$36*1+'Final Model'!$B$40*0 -> 186.56532
A115: Rep, no endcap | B115: ='Final Model'!$B$33+'Final Model'!$B$34*AVERAGE('Analysis Data'!$D$2:$D$1387)+'Final Model'!$B$35*1+'Final Model'!$B$36*0+'Final Model'!$B$40*0 -> 245.4067
A116: Rep, endcap | B116: ='Final Model'!$B$33+'Final Model'!$B$34*AVERAGE('Analysis Data'!$D$2:$D$1387)+'Final Model'!$B$35*1+'Final Model'!$B$36*1+'Final Model'!$B$40*1 -> 699.83038

Sheet Final Model
A1: PREFERRED FINAL MODEL
A2: Sales = b0 + b1 Price + b2 Sales Rep + b3 Endcap + b4 Demo + b5 Demo1-3 + b6 Demo4-5 + b7 (Endcap x Sales Rep)
A4: INPUTS
A5: Dependent (Y) range | B5: 'Analysis Data'!C2:C1387
A6: Predictor (X) range | B6: 'Analysis Data'!O2:U1387
A8: CALCULATION: LINEST(Y,X,TRUE,TRUE) raw array (coefficients appear in REVERSE variable order; last column = intercept)
B9: EndRep | C9: D45 | D9: D13 | E9: Demo | F9: Endcap | G9: Rep | H9: Price | I9: Intercept
A10: Coefficient | B10: {=IFERROR(LINEST('Analysis Data'!$C$2:$C$1387,'Analysis Data'!$O$2:$U$1387,TRUE(),TRUE()),"")} -> 453.8033 | C10: 74.551964 | D10: 73.369792 | E10: 106.7527 | F10: 0.62038277 | G10: 59.461761 | H10: -22.066351 | I10: 276.57349
A11: Std error | B11: 14.73721 | C11: 5.0397248 | D11: 3.7659884 | E11: 5.7001901 | F11: 12.076894 | G11: 3.0112427 | H11: 3.0446216 | I11: 12.168591
A12: R² | SE(y) | B12: 0.80585644 | C12: 49.032021
A13: F | df | B13: 817.12003 | C13: 1378
A14: SSreg | SSres | B14: 13751291 | C14: 3312903.6
A17: OUTPUT: Regression statistics
A18: Multiple R | B18: =SQRT(INDEX('Final Model'!$B$10:$I$14,3,1)) -> 0.89769507
A19: R² | B19: =INDEX('Final Model'!$B$10:$I$14,3,1) -> 0.80585644
A20: Adjusted R² | B20: =1-(1-'Final Model'!$B$19)*('Final Model'!$B$22-1)/'Final Model'!$B$24 -> 0.80487022
A21: Standard error | B21: =INDEX('Final Model'!$B$10:$I$14,3,2) -> 49.032021
A22: Observations | B22: =COUNT('Analysis Data'!$C$2:$C$1387) -> 1386
A23: k (predictors) | B23: =7 -> 7
A24: df residual | B24: =INDEX('Final Model'!$B$10:$I$14,4,2) -> 1378
A25: F-statistic | B25: =INDEX('Final Model'!$B$10:$I$14,4,1) -> 817.12003
A26: Significance F (model p-value) | B26: =_xlfn.F.DIST.RT('Final Model'!$B$25,'Final Model'!$B$23,'Final Model'!$B$24) -> 0
A27: SS regression | B27: =INDEX('Final Model'!$B$10:$I$14,5,1) -> 13751291
A28: SS residual | B28: =INDEX('Final Model'!$B$10:$I$14,5,2) -> 3312903.6
A29: SS total | B29: ='Final Model'!$B$27+'Final Model'!$B$28 -> 17064195
A31: OUTPUT: Coefficient table (t = b/SE; p = two-tailed T.DIST.2T; 95% CI = b ± T.INV.2T(0.05,df)·SE)
A32: Variable | B32: Coefficient | C32: Std error | D32: t-stat | E32: p-value | F32: Lower 95% | G32: Upper 95%
A33: Intercept | B33: =INDEX('Final Model'!$B$10:$I$14,1,8) -> 276.57349 | C33: =INDEX('Final Model'!$B$10:$I$14,2,8) -> 12.168591 | D33: =B33/C33 -> 22.728472 | E33: =_xlfn.T.DIST.2T(ABS(D33),'Final Model'!$B$24) -> 2.235281e-97 | F33: =B33-_xlfn.T.INV.2T(0.05,'Final Model'!$B$24)*C33 -> 252.70253 | G33: =B33+_xlfn.T.INV.2T(0.05,'Final Model'!$B$24)*C33 -> 300.44446
A34: Price | B34: =INDEX('Final Model'!$B$10:$I$14,1,7) -> -22.066351 | C34: =INDEX('Final Model'!$B$10:$I$14,2,7) -> 3.0446216 | D34: =B34/C34 -> -7.2476499 | E34: =_xlfn.T.DIST.2T(ABS(D34),'Final Model'!$B$24) -> 7.03912e-13 | F34: =B34-_xlfn.T.INV.2T(0.05,'Final Model'!$B$24)*C34 -> -28.038946 | G34: =B34+_xlfn.T.INV.2T(0.05,'Final Model'!$B$24)*C34 -> -16.093757
A35: Rep | B35: =INDEX('Final Model'!$B$10:$I$14,1,6) -> 59.461761 | C35: =INDEX('Final Model'!$B$10:$I$14,2,6) -> 3.0112427 | D35: =B35/C35 -> 19.746585 | E35: =_xlfn.T.DIST.2T(ABS(D35),'Final Model'!$B$24) -> 1.2561872e-76 | F35: =B35-_xlfn.T.INV.2T(0.05,'Final Model'!$B$24)*C35 -> 53.554645 | G35: =B35+_xlfn.T.INV.2T(0.05,'Final Model'!$B$24)*C35 -> 65.368876
A36: Endcap | B36: =INDEX('Final Model'!$B$10:$I$14,1,5) -> 0.62038277 | C36: =INDEX('Final Model'!$B$10:$I$14,2,5) -> 12.076894 | D36: =B36/C36 -> 0.051369398 | E36: =_xlfn.T.DIST.2T(ABS(D36),'Final Model'!$B$24) -> 0.95903861 | F36: =B36-_xlfn.T.INV.2T(0.05,'Final Model'!$B$24)*C36 -> -23.070703 | G36: =B36+_xlfn.T.INV.2T(0.05,'Final Model'!$B$24)*C36 -> 24.311469
A37: Demo | B37: =INDEX('Final Model'!$B$10:$I$14,1,4) -> 106.7527 | C37: =INDEX('Final Model'!$B$10:$I$14,2,4) -> 5.7001901 | D37: =B37/C37 -> 18.727919 | E37: =_xlfn.T.DIST.2T(ABS(D37),'Final Model'!$B$24) -> 6.6868354e-70 | F37: =B37-_xlfn.T.INV.2T(0.05,'Final Model'!$B$24)*C37 -> 95.570708 | G37: =B37+_xlfn.T.INV.2T(0.05,'Final Model'!$B$24)*C37 -> 117.93469
A38: D13 | B38: =INDEX('Final Model'!$B$10:$I$14,1,3) -> 73.369792 | C38: =INDEX('Final Model'!$B$10:$I$14,2,3) -> 3.7659884 | D38: =B38/C38 -> 19.482214 | E38: =_xlfn.T.DIST.2T(ABS(D38),'Final Model'!$B$24) -> 7.3129943e-75 | F38: =B38-_xlfn.T.INV.2T(0.05,'Final Model'!$B$24)*C38 -> 65.982102 | G38: =B38+_xlfn.T.INV.2T(0.05,'Final Model'!$B$24)*C38 -> 80.757483
A39: D45 | B39: =INDEX('Final Model'!$B$10:$I$14,1,2) -> 74.551964 | C39: =INDEX('Final Model'!$B$10:$I$14,2,2) -> 5.0397248 | D39: =B39/C39 -> 14.792864 | E39: =_xlfn.T.DIST.2T(ABS(D39),'Final Model'!$B$24) -> 4.5661721e-46 | F39: =B39-_xlfn.T.INV.2T(0.05,'Final Model'!$B$24)*C39 -> 64.665601 | G39: =B39+_xlfn.T.INV.2T(0.05,'Final Model'!$B$24)*C39 -> 84.438326
A40: EndRep | B40: =INDEX('Final Model'!$B$10:$I$14,1,1) -> 453.8033 | C40: =INDEX('Final Model'!$B$10:$I$14,2,1) -> 14.73721 | D40: =B40/C40 -> 30.793028 | E40: =_xlfn.T.DIST.2T(ABS(D40),'Final Model'!$B$24) -> 7.0499844e-159 | F40: =B40-_xlfn.T.INV.2T(0.05,'Final Model'!$B$24)*C40 -> 424.89351 | G40: =B40+_xlfn.T.INV.2T(0.05,'Final Model'!$B$24)*C40 -> 482.71309
A43: CALCULATION: coefficient row (constant first) used for fitted values
B44: const | C44: Price | D44: Rep | E44: Endcap | F44: Demo | G44: D13 | H44: D45 | I44: EndRep
A45: Coefficients (forward order) | B45: ='Final Model'!$B$33 -> 276.57349 | C45: ='Final Model'!$B$34 -> -22.066351 | D45: ='Final Model'!$B$35 -> 59.461761 | E45: ='Final Model'!$B$36 -> 0.62038277 | F45: ='Final Model'!$B$37 -> 106.7527 | G45: ='Final Model'!$B$38 -> 73.369792 | H45: ='Final Model'!$B$39 -> 74.551964 | I45: ='Final Model'!$B$40 -> 453.8033
A48: CALCULATION: X'X (design matrix incl. constant)
B49: {=MMULT(TRANSPOSE('Analysis Data'!$N$2:$U$1387),'Analysis Data'!$N$2:$U$1387)} -> 1386 | C49: 5692.4308 | D49: 762 | E49: 53 | F49: 81 | G49: 217 | H49: 105 | I49: 36
B50: 5692.4308 | C50: 23677.307 | D50: 3234.761 | E50: 209.38263 | F50: 340.46278 | G50: 887.71346 | H50: 446.19803 | I50: 141.89955
B51: 762 | C51: 3234.761 | D51: 762 | E51: 36 | F51: 69 | G51: 180 | H51: 83 | I51: 36
B52: 53 | C52: 209.38263 | D52: 36 | E52: 53 | F52: 8 | G52: 17 | H52: 4 | I52: 36
B53: 81 | C53: 340.46278 | D53: 69 | E53: 8 | F53: 81 | G53: 17 | H53: 5 | I53: 7
B54: 217 | C54: 887.71346 | D54: 180 | E54: 17 | F54: 17 | G54: 217 | H54: 18 | I54: 14
B55: 105 | C55: 446.19803 | D55: 83 | E55: 4 | F55: 5 | G55: 18 | H55: 105 | I55: 2
B56: 36 | C56: 141.89955 | D56: 36 | E56: 36 | F56: 7 | G56: 14 | H56: 2 | I56: 36
A58: CALCULATION: (X'X)^-1 (rows/cols: const, Price, Rep, Endcap, Demo, D13, D45, EndRep)
B59: {=MINVERSE(B49:I56)} -> 0.061591537 | C59: -0.015198412 | D59: 0.0035667572 | E59: -0.00096266536 | F59: 5.8751632e-05 | G59: -0.0021318921 | H59: 0.00064089259 | I59: -0.0035067054
B60: -0.015198412 | C60: 0.003855734 | D60: -0.0012964406 | E60: -0.00015298167 | F60: -8.1227818e-05 | G60: 0.00045606187 | H60: -0.00025503901 | I60: 0.0013024702
B61: 0.0035667572 | C61: -0.0012964406 | D61: 0.0037716548 | E61: 0.0019363037 | F61: -0.00092368395 | G61: -0.0011801242 | H61: -0.00080008524 | I61: -0.0034816036
B62: -0.00096266536 | C62: -0.00015298167 | D62: 0.0019363037 | E62: 0.060666777 | F62: -0.000587879 | G62: -0.00073929374 | H62: -0.00092023517 | I62: -0.060584478
B63: 5.8751632e-05 | C63: -8.1227818e-05 | D63: -0.00092368395 | E63: -0.000587879 | F63: 0.013515095 | G63: 5.1407257e-05 | H63: 0.0004036761 | I63: -0.00089736998
B64: -0.0021318921 | C64: 0.00045606187 | D64: -0.0011801242 | E64: -0.00073929374 | F64: 5.1407257e-05 | G64: 0.0058992713 | H64: 0.00014223902 | I64: -5.8387215e-05
B65: 0.00064089259 | C65: -0.00025503901 | D65: -0.00080008524 | E65: -0.00092023517 | F65: 0.0004036761 | G65: 0.00014223902 | H65: 0.010564624 | I65: 0.001363972
B66: -0.0035067054 | C66: 0.0013024702 | D66: -0.0034816036 | E66: -0.060584478 | F66: -0.00089736998 | G66: -5.8387215e-05 | H66: 0.001363972 | I66: 0.090338096
A69: Final equation (Excel): see coefficient table. Interaction term is Endcap*SalesRep.

Sheet Demo Analysis
A1: DEMO ANALYSIS (Questions 3 and 6): effect of in-store demos on weekly sales, from the final model
A2: Summary (rows 4-9) is formula-linked to the Final Model sheet; restricted models used for partial F-tests are further down this sheet.
A4: Variable | B4: Coefficient (units) | C4: Std error | D4: t | E4: p-value | F4: Lower 95% | G4: Upper 95% | H4: Significant at 5%?
A5: Demo (current week) | B5: ='Final Model'!$B$37 -> 106.7527 | C5: ='Final Model'!$C$37 -> 5.7001901 | D5: ='Final Model'!$D$37 -> 18.727919 | E5: ='Final Model'!$E$37 -> 6.6868354e-70 | F5: ='Final Model'!$F$37 -> 95.570708 | G5: ='Final Model'!$G$37 -> 117.93469 | H5: =IF(E5<0.05,"Yes","No") -> Yes
A6: Demo1-3 (1-3 weeks ago) | B6: ='Final Model'!$B$38 -> 73.369792 | C6: ='Final Model'!$C$38 -> 3.7659884 | D6: ='Final Model'!$D$38 -> 19.482214 | E6: ='Final Model'!$E$38 -> 7.3129943e-75 | F6: ='Final Model'!$F$38 -> 65.982102 | G6: ='Final Model'!$G$38 -> 80.757483 | H6: =IF(E6<0.05,"Yes","No") -> Yes
A7: Demo4-5 (4-5 weeks ago) | B7: ='Final Model'!$B$39 -> 74.551964 | C7: ='Final Model'!$C$39 -> 5.0397248 | D7: ='Final Model'!$D$39 -> 14.792864 | E7: ='Final Model'!$E$39 -> 4.5661721e-46 | F7: ='Final Model'!$F$39 -> 64.665601 | G7: ='Final Model'!$G$39 -> 84.438326 | H7: =IF(E7<0.05,"Yes","No") -> Yes
A9: JOINT AND COMPARISON TESTS
A10: Test | B10: Statistic | C10: p-value | D10: Interpretation
A11: Joint F: Demo1-3 = Demo4-5 = 0 (lags, q=2) | B11: =(('Final Model'!$B$19-'Demo Analysis'!$B$59)/2)/((1-'Final Model'!$B$19)/'Final Model'!$B$24) -> 294.09564 | C11: =_xlfn.F.DIST.RT(B11,2,'Final Model'!$B$24) -> 4.3108023e-107 | D11: Lagged demo effects are jointly significant
A12: Joint F: all three demo variables = 0 (q=3) | B12: =(('Final Model'!$B$19-'Demo Analysis'!$B$100)/3)/((1-'Final Model'!$B$19)/'Final Model'!$B$24) -> 305.74791 | C12: =_xlfn.F.DIST.RT(B12,3,'Final Model'!$B$24) -> 4.024972e-152 | D12: Demo program has a significant effect overall
A13: Demo4-5 minus Demo1-3 (units): difference | B13: ='Final Model'!$B$39-'Final Model'!$B$38 -> 1.1821715 | D13: Standard error → t → p below
A14: Std error of difference | B14: ='Final Model'!$B$21*SQRT('Final Model'!$G$64+'Final Model'!$H$65-2*'Final Model'!$H$64) -> 6.2367916
A15: t-stat / p-value (H0: no decay between weeks 1-3 and 4-5) | B15: =B13/B14 -> 0.18954803 | C15: =_xlfn.T.DIST.2T(ABS(B15),'Final Model'!$B$24) -> 0.84969123 | D15: No evidence the lift decays between 1-3 and 4-5 weeks
A16: Current-week Demo minus Demo1-3 (units) | B16: ='Final Model'!$B$37-'Final Model'!$B$38 -> 33.382904 | C16: =_xlfn.T.DIST.2T(ABS(B16/('Final Model'!$B$21*SQRT('Final Model'!$F$63+'Final Model'!$G$64-2*'Final Model'!$G$63))),'Final Model'!$B$24) -> 1.0754818e-06 | D16: Current-week lift is larger than the later-week lift
A18: ILLUSTRATIVE CUMULATIVE UNITS PER DEMOED STORE (assumes a store stays in each flag for the full window; no cost data available)
A19: Demo week + 3 weeks of Demo1-3 | B19: =B5+3*B6 -> 326.86207
A20: ... + 2 further weeks of Demo4-5 (observable window) | B20: =B5+3*B6+2*B7 -> 475.966
A21: ROI cannot be computed: demo cost and unit margin are not in the data supplied.
A22: Duration finding: Demo4-5 is defined as "at least 4-5 weeks ago" and the data end 11 weeks in, so the dataset shows the lift persists AT LEAST 4-5 weeks after a demo with no measurable decay; it cannot show when it ends.
A41: Restricted model for partial F: final model WITHOUT Demo1-3 and Demo4-5
A42: Price, Rep, Endcap, EndRep, Demo (Analysis Data W:AA)
A44: INPUTS
A45: Dependent (Y) range | B45: 'Analysis Data'!C2:C1387
A46: Predictor (X) range | B46: 'Analysis Data'!W2:AA1387
A48: CALCULATION: LINEST(Y,X,TRUE,TRUE) raw array (coefficients appear in REVERSE variable order; last column = intercept)
B49: Demo | C49: EndRep | D49: Endcap | E49: Rep | F49: Price | G49: Intercept
A50: Coefficient | B50: {=IFERROR(LINEST('Analysis Data'!$C$2:$C$1387,'Analysis Data'!$W$2:$AA$1387,TRUE(),TRUE()),"")} -> 103.33993 | C50: 445.11989 | D50: 16.034044 | E50: 79.456803 | F50: -25.905043 | G50: 298.31706
A51: Std error | B51: 6.8000005 | C51: 17.573671 | D51: 14.39528 | E51: 3.4521744 | F51: 3.614354 | G51: 14.428401
A52: R² | SE(y) | B52: 0.72298739 | C52: 58.526578
A53: F | df | B53: 720.34452 | C53: 1380
A54: SSreg | SSres | B54: 12337198 | C54: 4726997.2
A57: OUTPUT: Regression statistics
A58: Multiple R | B58: =SQRT(INDEX('Demo Analysis'!$B$50:$G$54,3,1)) -> 0.85028665
A59: R² | B59: =INDEX('Demo Analysis'!$B$50:$G$54,3,1) -> 0.72298739
A60: Adjusted R² | B60: =1-(1-'Demo Analysis'!$B$59)*('Demo Analysis'!$B$62-1)/'Demo Analysis'!$B$64 -> 0.72198372
A61: Standard error | B61: =INDEX('Demo Analysis'!$B$50:$G$54,3,2) -> 58.526578
A62: Observations | B62: =COUNT('Analysis Data'!$C$2:$C$1387) -> 1386
A63: k (predictors) | B63: =5 -> 5
A64: df residual | B64: =INDEX('Demo Analysis'!$B$50:$G$54,4,2) -> 1380
A65: F-statistic | B65: =INDEX('Demo Analysis'!$B$50:$G$54,4,1) -> 720.34452
A66: Significance F (model p-value) | B66: =_xlfn.F.DIST.RT('Demo Analysis'!$B$65,'Demo Analysis'!$B$63,'Demo Analysis'!$B$64) -> 0
A67: SS regression | B67: =INDEX('Demo Analysis'!$B$50:$G$54,5,1) -> 12337198
A68: SS residual | B68: =INDEX('Demo Analysis'!$B$50:$G$54,5,2) -> 4726997.2
A69: SS total | B69: ='Demo Analysis'!$B$67+'Demo Analysis'!$B$68 -> 17064195
A71: OUTPUT: Coefficient table (t = b/SE; p = two-tailed T.DIST.2T; 95% CI = b ± T.INV.2T(0.05,df)·SE)
A72: Variable | B72: Coefficient | C72: Std error | D72: t-stat | E72: p-value | F72: Lower 95% | G72: Upper 95%
A73: Intercept | B73: =INDEX('Demo Analysis'!$B$50:$G$54,1,6) -> 298.31706 | C73: =INDEX('Demo Analysis'!$B$50:$G$54,2,6) -> 14.428401 | D73: =B73/C73 -> 20.675683 | E73: =_xlfn.T.DIST.2T(ABS(D73),'Demo Analysis'!$B$64) -> 6.0145519e-83 | F73: =B73-_xlfn.T.INV.2T(0.05,'Demo Analysis'!$B$64)*C73 -> 270.01308 | G73: =B73+_xlfn.T.INV.2T(0.05,'Demo Analysis'!$B$64)*C73 -> 326.62103
A74: Price | B74: =INDEX('Demo Analysis'!$B$50:$G$54,1,5) -> -25.905043 | C74: =INDEX('Demo Analysis'!$B$50:$G$54,2,5) -> 3.614354 | D74: =B74/C74 -> -7.1672678 | E74: =_xlfn.T.DIST.2T(ABS(D74),'Demo Analysis'!$B$64) -> 1.2421827e-12 | F74: =B74-_xlfn.T.INV.2T(0.05,'Demo Analysis'!$B$64)*C74 -> -32.995265 | G74: =B74+_xlfn.T.INV.2T(0.05,'Demo Analysis'!$B$64)*C74 -> -18.814821
A75: Rep | B75: =INDEX('Demo Analysis'!$B$50:$G$54,1,4) -> 79.456803 | C75: =INDEX('Demo Analysis'!$B$50:$G$54,2,4) -> 3.4521744 | D75: =B75/C75 -> 23.016451 | E75: =_xlfn.T.DIST.2T(ABS(D75),'Demo Analysis'!$B$64) -> 1.7833205e-99 | F75: =B75-_xlfn.T.INV.2T(0.05,'Demo Analysis'!$B$64)*C75 -> 72.684726 | G75: =B75+_xlfn.T.INV.2T(0.05,'Demo Analysis'!$B$64)*C75 -> 86.22888
A76: Endcap | B76: =INDEX('Demo Analysis'!$B$50:$G$54,1,3) -> 16.034044 | C76: =INDEX('Demo Analysis'!$B$50:$G$54,2,3) -> 14.39528 | D76: =B76/C76 -> 1.1138404 | E76: =_xlfn.T.DIST.2T(ABS(D76),'Demo Analysis'!$B$64) -> 0.26554164 | F76: =B76-_xlfn.T.INV.2T(0.05,'Demo Analysis'!$B$64)*C76 -> -12.204954 | G76: =B76+_xlfn.T.INV.2T(0.05,'Demo Analysis'!$B$64)*C76 -> 44.273043
A77: EndRep | B77: =INDEX('Demo Analysis'!$B$50:$G$54,1,2) -> 445.11989 | C77: =INDEX('Demo Analysis'!$B$50:$G$54,2,2) -> 17.573671 | D77: =B77/C77 -> 25.328794 | E77: =_xlfn.T.DIST.2T(ABS(D77),'Demo Analysis'!$B$64) -> 1.4964836e-116 | F77: =B77-_xlfn.T.INV.2T(0.05,'Demo Analysis'!$B$64)*C77 -> 410.6459 | G77: =B77+_xlfn.T.INV.2T(0.05,'Demo Analysis'!$B$64)*C77 -> 479.59389
A78: Demo | B78: =INDEX('Demo Analysis'!$B$50:$G$54,1,1) -> 103.33993 | C78: =INDEX('Demo Analysis'!$B$50:$G$54,2,1) -> 6.8000005 | D78: =B78/C78 -> 15.197047 | E78: =_xlfn.T.DIST.2T(ABS(D78),'Demo Analysis'!$B$64) -> 2.4084996e-48 | F78: =B78-_xlfn.T.INV.2T(0.05,'Demo Analysis'!$B$64)*C78 -> 90.000475 | G78: =B78+_xlfn.T.INV.2T(0.05,'Demo Analysis'!$B$64)*C78 -> 116.67939
A82: Restricted model for partial F: final model WITHOUT any demo variable
A83: Price, Rep, Endcap, EndRep (Analysis Data W:Z)
A85: INPUTS
A86: Dependent (Y) range | B86: 'Analysis Data'!C2:C1387
A87: Predictor (X) range | B87: 'Analysis Data'!W2:Z1387
A89: CALCULATION: LINEST(Y,X,TRUE,TRUE) raw array (coefficients appear in REVERSE variable order; last column = intercept)
B90: EndRep | C90: Endcap | D90: Rep | E90: Price | F90: Intercept
A91: Coefficient | B91: {=IFERROR(LINEST('Analysis Data'!$C$2:$C$1387,'Analysis Data'!$W$2:$Z$1387,TRUE(),TRUE()),"")} -> 452.38383 | C91: 20.221823 | D91: 86.223977 | E91: -25.330408 | F91: 297.92703
A92: Std error | B92: 18.973437 | C92: 15.544787 | D92: 3.6973757 | E92: 3.9034726 | F92: 15.583383
A93: R² | SE(y) | B93: 0.67662787 | C93: 63.211683
A94: F | df | B94: 722.40539 | C94: 1381
A95: SSreg | SSres | B95: 11546110 | C95: 5518085.1
A98: OUTPUT: Regression statistics
A99: Multiple R | B99: =SQRT(INDEX('Demo Analysis'!$B$91:$F$95,3,1)) -> 0.82257393
A100: R² | B100: =INDEX('Demo Analysis'!$B$91:$F$95,3,1) -> 0.67662787
A101: Adjusted R² | B101: =1-(1-'Demo Analysis'!$B$100)*('Demo Analysis'!$B$103-1)/'Demo Analysis'!$B$105 -> 0.67569124
A102: Standard error | B102: =INDEX('Demo Analysis'!$B$91:$F$95,3,2) -> 63.211683
A103: Observations | B103: =COUNT('Analysis Data'!$C$2:$C$1387) -> 1386
A104: k (predictors) | B104: =4 -> 4
A105: df residual | B105: =INDEX('Demo Analysis'!$B$91:$F$95,4,2) -> 1381
A106: F-statistic | B106: =INDEX('Demo Analysis'!$B$91:$F$95,4,1) -> 722.40539
A107: Significance F (model p-value) | B107: =_xlfn.F.DIST.RT('Demo Analysis'!$B$106,'Demo Analysis'!$B$104,'Demo Analysis'!$B$105) -> 0
A108: SS regression | B108: =INDEX('Demo Analysis'!$B$91:$F$95,5,1) -> 11546110
A109: SS residual | B109: =INDEX('Demo Analysis'!$B$91:$F$95,5,2) -> 5518085.1
A110: SS total | B110: ='Demo Analysis'!$B$108+'Demo Analysis'!$B$109 -> 17064195
A112: OUTPUT: Coefficient table (t = b/SE; p = two-tailed T.DIST.2T; 95% CI = b ± T.INV.2T(0.05,df)·SE)
A113: Variable | B113: Coefficient | C113: Std error | D113: t-stat | E113: p-value | F113: Lower 95% | G113: Upper 95%
A114: Intercept | B114: =INDEX('Demo Analysis'!$B$91:$F$95,1,5) -> 297.92703 | C114: =INDEX('Demo Analysis'!$B$91:$F$95,2,5) -> 15.583383 | D114: =B114/C114 -> 19.118251 | E114: =_xlfn.T.DIST.2T(ABS(D114),'Demo Analysis'!$B$105) -> 1.7999402e-72 | F114: =B114-_xlfn.T.INV.2T(0.05,'Demo Analysis'!$B$105)*C114 -> 267.35737 | G114: =B114+_xlfn.T.INV.2T(0.05,'Demo Analysis'!$B$105)*C114 -> 328.49669
A115: Price | B115: =INDEX('Demo Analysis'!$B$91:$F$95,1,4) -> -25.330408 | C115: =INDEX('Demo Analysis'!$B$91:$F$95,2,4) -> 3.9034726 | D115: =B115/C115 -> -6.4891982 | E115: =_xlfn.T.DIST.2T(ABS(D115),'Demo Analysis'!$B$105) -> 1.1997163e-10 | F115: =B115-_xlfn.T.INV.2T(0.05,'Demo Analysis'!$B$105)*C115 -> -32.987784 | G115: =B115+_xlfn.T.INV.2T(0.05,'Demo Analysis'!$B$105)*C115 -> -17.673031
A116: Rep | B116: =INDEX('Demo Analysis'!$B$91:$F$95,1,3) -> 86.223977 | C116: =INDEX('Demo Analysis'!$B$91:$F$95,2,3) -> 3.6973757 | D116: =B116/C116 -> 23.320318 | E116: =_xlfn.T.DIST.2T(ABS(D116),'Demo Analysis'!$B$105) -> 1.084192e-101 | F116: =B116-_xlfn.T.INV.2T(0.05,'Demo Analysis'!$B$105)*C116 -> 78.970897 | G116: =B116+_xlfn.T.INV.2T(0.05,'Demo Analysis'!$B$105)*C116 -> 93.477057
A117: Endcap | B117: =INDEX('Demo Analysis'!$B$91:$F$95,1,2) -> 20.221823 | C117: =INDEX('Demo Analysis'!$B$91:$F$95,2,2) -> 15.544787 | D117: =B117/C117 -> 1.3008749 | E117: =_xlfn.T.DIST.2T(ABS(D117),'Demo Analysis'!$B$105) -> 0.1935183 | F117: =B117-_xlfn.T.INV.2T(0.05,'Demo Analysis'!$B$105)*C117 -> -10.272125 | G117: =B117+_xlfn.T.INV.2T(0.05,'Demo Analysis'!$B$105)*C117 -> 50.715771
A118: EndRep | B118: =INDEX('Demo Analysis'!$B$91:$F$95,1,1) -> 452.38383 | C118: =INDEX('Demo Analysis'!$B$91:$F$95,2,1) -> 18.973437 | D118: =B118/C118 -> 23.843009 | E118: =_xlfn.T.DIST.2T(ABS(D118),'Demo Analysis'!$B$105) -> 1.6293821e-105 | F118: =B118-_xlfn.T.INV.2T(0.05,'Demo Analysis'!$B$105)*C118 -> 415.16396 | G118: =B118+_xlfn.T.INV.2T(0.05,'Demo Analysis'!$B$105)*C118 -> 489.6037

Sheet Endcap Analysis
A1: ENDCAP ANALYSIS (Question 4)
A3: Step 1 - Unadjusted comparison (see Descriptive Stats)
A4: Group | B4: Mean Sales | C4: N
A5: No endcap | B5: =AVERAGEIF('Analysis Data'!$F$2:$F$1387,0,'Analysis Data'!$C$2:$C$1387) -> 240.69579 | C5: =COUNTIF('Analysis Data'!$F$2:$F$1387,0) -> 1333
A6: Endcap | B6: =AVERAGEIF('Analysis Data'!$F$2:$F$1387,1,'Analysis Data'!$C$2:$C$1387) -> 583.92496 | C6: =COUNTIF('Analysis Data'!$F$2:$F$1387,1) -> 53
A7: Unadjusted difference | B7: =B6-B5 -> 343.22917
A9: Step 2 - Single-predictor regression (Model 0C) coefficient | B9: ='Baseline Models'!$B$110 -> 343.22917
A11: Step 3 - Regression-adjusted effects from final model
A12: Effect | B12: Estimate | C12: Std error | D12: t | E12: p-value | F12: Lower 95% | G12: Upper 95%
A13: Endcap when Sales Rep = 0 (Endcap coefficient) | B13: ='Final Model'!$B$36 -> 0.62038277 | C13: ='Final Model'!$C$36 -> 12.076894 | D13: ='Final Model'!$D$36 -> 0.051369398 | E13: ='Final Model'!$E$36 -> 0.95903861 | F13: ='Final Model'!$F$36 -> -23.070703 | G13: ='Final Model'!$G$36 -> 24.311469
A14: Interaction (extra effect when Sales Rep = 1) | B14: ='Final Model'!$B$40 -> 453.8033 | C14: ='Final Model'!$C$40 -> 14.73721 | D14: ='Final Model'!$D$40 -> 30.793028 | E14: ='Final Model'!$E$40 -> 7.0499844e-159 | F14: ='Final Model'!$F$40 -> 424.89351 | G14: ='Final Model'!$G$40 -> 482.71309
A15: Combined Endcap effect when Sales Rep = 1 | B15: ='Final Model'!$B$36+'Final Model'!$B$40 -> 454.42368 | C15: ='Final Model'!$B$21*SQRT('Final Model'!$E$62+'Final Model'!$I$66+2*'Final Model'!$I$62) -> 8.4693385 | D15: =B15/C15 -> 53.655156 | E15: =_xlfn.T.DIST.2T(ABS(D15),'Final Model'!$B$24) -> 0 | F15: =B15-_xlfn.T.INV.2T(0.05,'Final Model'!$B$24)*C15 -> 437.80949 | G15: =B15+_xlfn.T.INV.2T(0.05,'Final Model'!$B$24)*C15 -> 471.03787
A17: Step 4 - Predicted weekly units (price at mean, no demo): see Interaction Analysis sheet
A19: Cell counts | B19: N | C19: Mean Sales
A20: No rep, no endcap | B20: =COUNTIFS('Analysis Data'!$E$2:$E$1387,0,'Analysis Data'!$F$2:$F$1387,0) -> 607 | C20: =AVERAGEIFS('Analysis Data'!$C$2:$C$1387,'Analysis Data'!$E$2:$E$1387,0,'Analysis Data'!$F$2:$F$1387,0) -> 198.18336
A21: No rep, endcap | B21: =COUNTIFS('Analysis Data'!$E$2:$E$1387,0,'Analysis Data'!$F$2:$F$1387,1) -> 17 | C21: =AVERAGEIFS('Analysis Data'!$C$2:$C$1387,'Analysis Data'!$E$2:$E$1387,0,'Analysis Data'!$F$2:$F$1387,1) -> 217.59744
A22: Rep, no endcap | B22: =COUNTIFS('Analysis Data'!$E$2:$E$1387,1,'Analysis Data'!$F$2:$F$1387,0) -> 726 | C22: =AVERAGEIFS('Analysis Data'!$C$2:$C$1387,'Analysis Data'!$E$2:$E$1387,1,'Analysis Data'!$F$2:$F$1387,0) -> 276.23993
A23: Rep, endcap | B23: =COUNTIFS('Analysis Data'!$E$2:$E$1387,1,'Analysis Data'!$F$2:$F$1387,1) -> 36 | C23: =AVERAGEIFS('Analysis Data'!$C$2:$C$1387,'Analysis Data'!$E$2:$E$1387,1,'Analysis Data'!$F$2:$F$1387,1) -> 756.91295
A25: Reading: raw endcap gap (~343 units) mixes two groups. Adjusted for the others, endcaps in stores WITHOUT a regional rep show no detectable lift (+0.6 units; CI roughly -23 to +24, based on only 17 obs); in stores WITH a regional rep the lift is ≈ +454 units per store-week. Endcap is a conditional association: targeting of endcaps to strong stores cannot be ruled out (see report Limitations).

Sheet Residual Diagnostics
A1: Obs | B1: Store | C1: Date | D1: Sales | E1: Fitted | F1: Residual | G1: Standardized resid (e/SE) | H1: Residual² | J1: Rank | K1: Sorted std resid | L1: Observed cum prob | M1: Expected cum prob (Normal) | O1: SUMMARY (final model)
A2: =ROW()-1 -> 1 | B2: ='Analysis Data'!A2 -> Biscayne (aka Aventura) | C2: ='Analysis Data'!B2 -> 40302 | D2: ='Analysis Data'!C2 -> 150.70209 | E2: =SUMPRODUCT('Final Model'!$B$45:$I$45,'Analysis Data'!N2:U2) -> 179.70221 | F2: =D2-E2 -> -29.000123 | G2: =F2/'Final Model'!$B$21 -> -0.59145275 | H2: =F2^2 -> 841.00715 | J2: =A2 -> 1 | K2: =SMALL($G$2:$G$1387,J2) -> -3.4237562 | L2: =(J2-0.5)/1386 -> 0.00036075036 | M2: =_xlfn.NORM.DIST(K2,AVERAGE($G$2:$G$1387),_xlfn.STDEV.S($G$2:$G$1387),TRUE()) -> 0.00029908675 | O2: Mean residual (should be ~0) | P2: =AVERAGE(F2:F1387) -> -2.3571973e-14
A3: =ROW()-1 -> 2 | B3: ='Analysis Data'!A3 -> Biscayne (aka Aventura) | C3: ='Analysis Data'!B3 -> 40309 | D3: ='Analysis Data'!C3 -> 197.4038 | E3: =SUMPRODUCT('Final Model'!$B$45:$I$45,'Analysis Data'!N3:U3) -> 188.35901 | F3: =D3-E3 -> 9.0447868 | G3: =F3/'Final Model'!$B$21 -> 0.18446694 | H3: =F3^2 -> 81.808168 | J3: =A3 -> 2 | K3: =SMALL($G$2:$G$1387,J3) -> -3.0483725 | L3: =(J3-0.5)/1386 -> 0.0010822511 | M3: =_xlfn.NORM.DIST(K3,AVERAGE($G$2:$G$1387),_xlfn.STDEV.S($G$2:$G$1387),TRUE()) -> 0.0011211626 | O3: Std dev of residuals | P3: =_xlfn.STDEV.S(F2:F1387) -> 48.907956
A4: =ROW()-1 -> 3 | B4: ='Analysis Data'!A4 -> Biscayne (aka Aventura) | C4: ='Analysis Data'!B4 -> 40316 | D4: ='Analysis Data'!C4 -> 235.10617 | E4: =SUMPRODUCT('Final Model'!$B$45:$I$45,'Analysis Data'!N4:U4) -> 192.51767 | F4: =D4-E4 -> 42.588502 | G4: =F4/'Final Model'!$B$21 -> 0.8685855 | H4: =F4^2 -> 1813.7805 | J4: =A4 -> 3 | K4: =SMALL($G$2:$G$1387,J4) -> -3.0041351 | L4: =(J4-0.5)/1386 -> 0.0018037518 | M4: =_xlfn.NORM.DIST(K4,AVERAGE($G$2:$G$1387),_xlfn.STDEV.S($G$2:$G$1387),TRUE()) -> 0.0012987079 | O4: Skewness | P4: =SKEW(F2:F1387) -> -0.010106499
A5: =ROW()-1 -> 4 | B5: ='Analysis Data'!A5 -> Biscayne (aka Aventura) | C5: ='Analysis Data'!B5 -> 40323 | D5: ='Analysis Data'!C5 -> 226.69243 | E5: =SUMPRODUCT('Final Model'!$B$45:$I$45,'Analysis Data'!N5:U5) -> 191.94904 | F5: =D5-E5 -> 34.743391 | G5: =F5/'Final Model'!$B$21 -> 0.70858575 | H5: =F5^2 -> 1207.1032 | J5: =A5 -> 4 | K5: =SMALL($G$2:$G$1387,J5) -> -2.8644922 | L5: =(J5-0.5)/1386 -> 0.0025252525 | M5: =_xlfn.NORM.DIST(K5,AVERAGE($G$2:$G$1387),_xlfn.STDEV.S($G$2:$G$1387),TRUE()) -> 0.0020409733 | O5: Excess kurtosis | P5: =KURT(F2:F1387) -> 0.053002936
A6: =ROW()-1 -> 5 | B6: ='Analysis Data'!A6 -> Biscayne (aka Aventura) | C6: ='Analysis Data'!B6 -> 40330 | D6: ='Analysis Data'!C6 -> 257.68815 | E6: =SUMPRODUCT('Final Model'!$B$45:$I$45,'Analysis Data'!N6:U6) -> 190.45956 | F6: =D6-E6 -> 67.228593 | G6: =F6/'Final Model'!$B$21 -> 1.3711161 | H6: =F6^2 -> 4519.6837 | J6: =A6 -> 5 | K6: =SMALL($G$2:$G$1387,J6) -> -2.8337016 | L6: =(J6-0.5)/1386 -> 0.0032467532 | M6: =_xlfn.NORM.DIST(K6,AVERAGE($G$2:$G$1387),_xlfn.STDEV.S($G$2:$G$1387),TRUE()) -> 0.0022493922 | O6: Durbin-Watson d | P6: =SUMXMY2(F3:F1387,F2:F1386)/SUMSQ(F2:F1387) -> 2.0916164
A7: =ROW()-1 -> 6 | B7: ='Analysis Data'!A7 -> Biscayne (aka Aventura) | C7: ='Analysis Data'!B7 -> 40337 | D7: ='Analysis Data'!C7 -> 132.95719 | E7: =SUMPRODUCT('Final Model'!$B$45:$I$45,'Analysis Data'!N7:U7) -> 177.32583 | F7: =D7-E7 -> -44.368645 | G7: =F7/'Final Model'!$B$21 -> -0.90489122 | H7: =F7^2 -> 1968.5767 | J7: =A7 -> 6 | K7: =SMALL($G$2:$G$1387,J7) -> -2.8303732 | L7: =(J7-0.5)/1386 -> 0.003968254 | M7: =_xlfn.NORM.DIST(K7,AVERAGE($G$2:$G$1387),_xlfn.STDEV.S($G$2:$G$1387),TRUE()) -> 0.0022730396 | O7: Min std resid | P7: =MIN(G2:G1387) -> -3.4237562
A8: =ROW()-1 -> 7 | B8: ='Analysis Data'!A8 -> Biscayne (aka Aventura) | C8: ='Analysis Data'!B8 -> 40344 | D8: ='Analysis Data'!C8 -> 221.88997 | E8: =SUMPRODUCT('Final Model'!$B$45:$I$45,'Analysis Data'!N8:U8) -> 185.73368 | F8: =D8-E8 -> 36.156288 | G8: =F8/'Final Model'!$B$21 -> 0.73740155 | H8: =F8^2 -> 1307.2772 | J8: =A8 -> 7 | K8: =SMALL($G$2:$G$1387,J8) -> -2.7999218 | L8: =(J8-0.5)/1386 -> 0.0046897547 | M8: =_xlfn.NORM.DIST(K8,AVERAGE($G$2:$G$1387),_xlfn.STDEV.S($G$2:$G$1387),TRUE()) -> 0.0025000733 | O8: Max std resid | P8: =MAX(G2:G1387) -> 3.7245607
A9: =ROW()-1 -> 8 | B9: ='Analysis Data'!A9 -> Biscayne (aka Aventura) | C9: ='Analysis Data'!B9 -> 40351 | D9: ='Analysis Data'!C9 -> 245.88136 | E9: =SUMPRODUCT('Final Model'!$B$45:$I$45,'Analysis Data'!N9:U9) -> 185.73368 | F9: =D9-E9 -> 60.147676 | G9: =F9/'Final Model'!$B$21 -> 1.226702 | H9: =F9^2 -> 3617.7429 | J9: =A9 -> 8 | K9: =SMALL($G$2:$G$1387,J9) -> -2.7380969 | L9: =(J9-0.5)/1386 -> 0.0054112554 | M9: =_xlfn.NORM.DIST(K9,AVERAGE($G$2:$G$1387),_xlfn.STDEV.S($G$2:$G$1387),TRUE()) -> 0.0030251519 | O9: Breusch-Pagan: R² of e² on X | P9: =INDEX(R14:Y18,3,1) -> 0.0094983701
A10: =ROW()-1 -> 9 | B10: ='Analysis Data'!A10 -> Biscayne (aka Aventura) | C10: ='Analysis Data'!B10 -> 40358 | D10: ='Analysis Data'!C10 -> 156.10253 | E10: =SUMPRODUCT('Final Model'!$B$45:$I$45,'Analysis Data'!N10:U10) -> 185.73368 | F10: =D10-E10 -> -29.631146 | G10: =F10/'Final Model'!$B$21 -> -0.60432234 | H10: =F10^2 -> 878.00479 | J10: =A10 -> 9 | K10: =SMALL($G$2:$G$1387,J10) -> -2.6861785 | L10: =(J10-0.5)/1386 -> 0.0061327561 | M10: =_xlfn.NORM.DIST(K10,AVERAGE($G$2:$G$1387),_xlfn.STDEV.S($G$2:$G$1387),TRUE()) -> 0.0035406928 | O10: Breusch-Pagan LM = n·R² | P10: =1386*P9 -> 13.164741
A11: =ROW()-1 -> 10 | B11: ='Analysis Data'!A11 -> Biscayne (aka Aventura) | C11: ='Analysis Data'!B11 -> 40365 | D11: ='Analysis Data'!C11 -> 200.10397 | E11: =SUMPRODUCT('Final Model'!$B$45:$I$45,'Analysis Data'!N11:U11) -> 193.88352 | F11: =D11-E11 -> 6.2204462 | G11: =F11/'Final Model'!$B$21 -> 0.12686498 | H11: =F11^2 -> 38.693951 | J11: =A11 -> 10 | K11: =SMALL($G$2:$G$1387,J11) -> -2.5774199 | L11: =(J11-0.5)/1386 -> 0.0068542569 | M11: =_xlfn.NORM.DIST(K11,AVERAGE($G$2:$G$1387),_xlfn.STDEV.S($G$2:$G$1387),TRUE()) -> 0.0048836841 | O11: Breusch-Pagan p-value (chi-sq, k df) | P11: =_xlfn.CHISQ.DIST.RT(P10,7) -> 0.068194799
A12: =ROW()-1 -> 11 | B12: ='Analysis Data'!A12 -> Biscayne (aka Aventura) | C12: ='Analysis Data'!B12 -> 40372 | D12: ='Analysis Data'!C12 -> 128.396 | E12: =SUMPRODUCT('Final Model'!$B$45:$I$45,'Analysis Data'!N12:U12) -> 188.03226 | F12: =D12-E12 -> -59.636256 | G12: =F12/'Final Model'!$B$21 -> -1.2162716 | H12: =F12^2 -> 3556.483 | J12: =A12 -> 11 | K12: =SMALL($G$2:$G$1387,J12) -> -2.5618008 | L12: =(J12-0.5)/1386 -> 0.0075757576 | M12: =_xlfn.NORM.DIST(K12,AVERAGE($G$2:$G$1387),_xlfn.STDEV.S($G$2:$G$1387),TRUE()) -> 0.0051099436 | O12: Corr(Fitted, Residual) (should be ~0) | P12: =CORREL(E2:E1387,F2:F1387) -> -2.8197627e-16
A13: =ROW()-1 -> 12 | B13: ='Analysis Data'!A13 -> Boca Raton | C13: ='Analysis Data'!B13 -> 40302 | D13: ='Analysis Data'!C13 -> 142.77821 | E13: =SUMPRODUCT('Final Model'!$B$45:$I$45,'Analysis Data'!N13:U13) -> 179.70221 | F13: =D13-E13 -> -36.924001 | G13: =F13/'Final Model'!$B$21 -> -0.75305893 | H13: =F13^2 -> 1363.3819 | J13: =A13 -> 12 | K13: =SMALL($G$2:$G$1387,J13) -> -2.5229689 | L13: =(J13-0.5)/1386 -> 0.0082972583 | M13: =_xlfn.NORM.DIST(K13,AVERAGE($G$2:$G$1387),_xlfn.STDEV.S($G$2:$G$1387),TRUE()) -> 0.0057133929 | R13: Aux regression LINEST (e² on predictors) - Breusch-Pagan
A14: =ROW()-1 -> 13 | B14: ='Analysis Data'!A14 -> Boca Raton | C14: ='Analysis Data'!B14 -> 40309 | D14: ='Analysis Data'!C14 -> 237.54455 | E14: =SUMPRODUCT('Final Model'!$B$45:$I$45,'Analysis Data'!N14:U14) -> 183.11247 | F14: =D14-E14 -> 54.432089 | G14: =F14/'Final Model'!$B$21 -> 1.1101335 | H14: =F14^2 -> 2962.8523 | J14: =A14 -> 13 | K14: =SMALL($G$2:$G$1387,J14) -> -2.4877414 | L14: =(J14-0.5)/1386 -> 0.009018759 | M14: =_xlfn.NORM.DIST(K14,AVERAGE($G$2:$G$1387),_xlfn.STDEV.S($G$2:$G$1387),TRUE()) -> 0.0063147006 | O14: Python reference values (statsmodels) | R14: {=IFERROR(LINEST($H$2:$H$1387,'Analysis Data'!$O$2:$U$1387,TRUE(),TRUE()),"")} -> 529.4029 | S14: 753.01553 | T14: -218.2578 | U14: 121.62402 | V14: -797.9059 | W14: -193.02749 | X14: 493.30941 | Y14: 457.09606
A15: =ROW()-1 -> 14 | B15: ='Analysis Data'!A15 -> Boca Raton | C15: ='Analysis Data'!B15 -> 40316 | D15: ='Analysis Data'!C15 -> 141.5333 | E15: =SUMPRODUCT('Final Model'!$B$45:$I$45,'Analysis Data'!N15:U15) -> 192.51767 | F15: =D15-E15 -> -50.984372 | G15: =F15/'Final Model'!$B$21 -> -1.0398179 | H15: =F15^2 -> 2599.4062 | J15: =A15 -> 14 | K15: =SMALL($G$2:$G$1387,J15) -> -2.4854349 | L15: =(J15-0.5)/1386 -> 0.0097402597 | M15: =_xlfn.NORM.DIST(K15,AVERAGE($G$2:$G$1387),_xlfn.STDEV.S($G$2:$G$1387),TRUE()) -> 0.0063559582 | O15: Durbin-Watson | P15: 2.0916164 | R15: 1026.3185 | S15: 350.973 | T15: 262.26834 | U15: 396.96866 | V15: 841.05063 | W15: 209.70686 | X15: 212.03141 | Y15: 847.43656
A16: =ROW()-1 -> 15 | B16: ='Analysis Data'!A16 -> Boca Raton | C16: ='Analysis Data'!B16 -> 40323 | D16: ='Analysis Data'!C16 -> 158.07395 | E16: =SUMPRODUCT('Final Model'!$B$45:$I$45,'Analysis Data'!N16:U16) -> 192.51767 | F16: =D16-E16 -> -34.44372 | G16: =F16/'Final Model'!$B$21 -> -0.70247401 | H16: =F16^2 -> 1186.3698 | J16: =A16 -> 15 | K16: =SMALL($G$2:$G$1387,J16) -> -2.4688741 | L16: =(J16-0.5)/1386 -> 0.01046176 | M16: =_xlfn.NORM.DIST(K16,AVERAGE($G$2:$G$1387),_xlfn.STDEV.S($G$2:$G$1387),TRUE()) -> 0.0066592553 | O16: BP LM / p | P16: 13.164741 | Q16: 0.068194799 | R16: 0.0094983701 | S16: 3414.6538
A17: =ROW()-1 -> 16 | B17: ='Analysis Data'!A17 -> Boca Raton | C17: ='Analysis Data'!B17 -> 40330 | D17: ='Analysis Data'!C17 -> 255.11774 | E17: =SUMPRODUCT('Final Model'!$B$45:$I$45,'Analysis Data'!N17:U17) -> 187.08065 | F17: =D17-E17 -> 68.037096 | G17: =F17/'Final Model'!$B$21 -> 1.3876054 | H17: =F17^2 -> 4629.0464 | J17: =A17 -> 16 | K17: =SMALL($G$2:$G$1387,J17) -> -2.3955176 | L17: =(J17-0.5)/1386 -> 0.011183261 | M17: =_xlfn.NORM.DIST(K17,AVERAGE($G$2:$G$1387),_xlfn.STDEV.S($G$2:$G$1387),TRUE()) -> 0.0081618999 | R17: 1.8877526 | S17: 1378
A18: =ROW()-1 -> 17 | B18: ='Analysis Data'!A18 -> Boca Raton | C18: ='Analysis Data'!B18 -> 40337 | D18: ='Analysis Data'!C18 -> 129.79363 | E18: =SUMPRODUCT('Final Model'!$B$45:$I$45,'Analysis Data'!N18:U18) -> 179.84932 | F18: =D18-E18 -> -50.055694 | G18: =F18/'Final Model'!$B$21 -> -1.0208776 | H18: =F18^2 -> 2505.5725 | J18: =A18 -> 17 | K18: =SMALL($G$2:$G$1387,J18) -> -2.3681527 | L18: =(J18-0.5)/1386 -> 0.011904762 | M18: =_xlfn.NORM.DIST(K18,AVERAGE($G$2:$G$1387),_xlfn.STDEV.S($G$2:$G$1387),TRUE()) -> 0.0087944646 | O18: Lag-1 residual corr within store (Python) | P18: -0.063651161 | R18: 1.5407652e+08 | S18: 1.6067288e+10
A19: =ROW()-1 -> 18 | B19: ='Analysis Data'!A19 -> Boca Raton | C19: ='Analysis Data'!B19 -> 40344 | D19: ='Analysis Data'!C19 -> 137.76429 | E19: =SUMPRODUCT('Final Model'!$B$45:$I$45,'Analysis Data'!N19:U19) -> 180.39178 | F19: =D19-E19 -> -42.6275 | G19: =F19/'Final Model'!$B$21 -> -0.86938085 | H19: =F19^2 -> 1817.1037 | J19: =A19 -> 18 | K19: =SMALL($G$2:$G$1387,J19) -> -2.3502581 | L19: =(J19-0.5)/1386 -> 0.012626263 | M19: =_xlfn.NORM.DIST(K19,AVERAGE($G$2:$G$1387),_xlfn.STDEV.S($G$2:$G$1387),TRUE()) -> 0.009230991
A20: =ROW()-1 -> 19 | B20: ='Analysis Data'!A20 -> Boca Raton | C20: ='Analysis Data'!B20 -> 40351 | D20: ='Analysis Data'!C20 -> 306.79382 | E20: =SUMPRODUCT('Final Model'!$B$45:$I$45,'Analysis Data'!N20:U20) -> 180.39178 | F20: =D20-E20 -> 126.40203 | G20: =F20/'Final Model'!$B$21 -> 2.5779487 | H20: =F20^2 -> 15977.474 | J20: =A20 -> 19 | K20: =SMALL($G$2:$G$1387,J20) -> -2.3012157 | L20: =(J20-0.5)/1386 -> 0.013347763 | M20: =_xlfn.NORM.DIST(K20,AVERAGE($G$2:$G$1387),_xlfn.STDEV.S($G$2:$G$1387),TRUE()) -> 0.010525929 | O20: Course DW decision: d near 2 and between dU and 4-dU => no first-order autocorrelation; d well below 2 => positive autocorrelation. Note rows are ordered store, then week.
A21: =ROW()-1 -> 20 | B21: ='Analysis Data'!A21 -> Boca Raton | C21: ='Analysis Data'!B21 -> 40358 | D21: ='Analysis Data'!C21 -> 103.31902 | E21: =SUMPRODUCT('Final Model'!$B$45:$I$45,'Analysis Data'!N21:U21) -> 180.39178 | F21: =D21-E21 -> -77.072762 | G21: =F21/'Final Model'!$B$21 -> -1.5718863 | H21: =F21^2 -> 5940.2106 | J21: =A21 -> 20 | K21: =SMALL($G$2:$G$1387,J21) -> -2.2959931 | L21: =(J21-0.5)/1386 -> 0.014069264 | M21: =_xlfn.NORM.DIST(K21,AVERAGE($G$2:$G$1387),_xlfn.STDEV.S($G$2:$G$1387),TRUE()) -> 0.010672738
A22: =ROW()-1 -> 21 | B22: ='Analysis Data'!A22 -> Boca Raton | C22: ='Analysis Data'!B22 -> 40365 | D22: ='Analysis Data'!C22 -> 240.22518 | E22: =SUMPRODUCT('Final Model'!$B$45:$I$45,'Analysis Data'!N22:U22) -> 188.03226 | F22: =D22-E22 -> 52.192918 | G22: =F22/'Final Model'!$B$21 -> 1.064466 | H22: =F22^2 -> 2724.1007 | J22: =A22 -> 21 | K22: =SMALL($G$2:$G$1387,J22) -> -2.2387827 | L22: =(J22-0.5)/1386 -> 0.014790765 | M22: =_xlfn.NORM.DIST(K22,AVERAGE($G$2:$G$1387),_xlfn.STDEV.S($G$2:$G$1387),TRUE()) -> 0.012401353
A23: =ROW()-1 -> 22 | B23: ='Analysis Data'!A23 -> Boca Raton | C23: ='Analysis Data'!B23 -> 40372 | D23: ='Analysis Data'!C23 -> 190.0248 | E23: =SUMPRODUCT('Final Model'!$B$45:$I$45,'Analysis Data'!N23:U23) -> 188.03226 | F23: =D23-E23 -> 1.9925421 | G23: =F23/'Final Model'!$B$21 -> 0.040637569 | H23: =F23^2 -> 3.9702241 | J23: =A23 -> 22 | K23: =SMALL($G$2:$G$1387,J23) -> -2.2235941 | L23: =(J23-0.5)/1386 -> 0.015512266 | M23: =_xlfn.NORM.DIST(K23,AVERAGE($G$2:$G$1387),_xlfn.STDEV.S($G$2:$G$1387),TRUE()) -> 0.012899146
A24: =ROW()-1 -> 23 | B24: ='Analysis Data'!A24 -> Coral Gables | C24: ='Analysis Data'!B24 -> 40302 | D24: ='Analysis Data'!C24 -> 149.76787 | E24: =SUMPRODUCT('Final Model'!$B$45:$I$45,'Analysis Data'!N24:U24) -> 176.86511 | F24: =D24-E24 -> -27.097237 | G24: =F24/'Final Model'!$B$21 -> -0.5526437 | H24: =F24^2 -> 734.26028 | J24: =A24 -> 23 | K24: =SMALL($G$2:$G$1387,J24) -> -2.1796928 | L24: =(J24-0.5)/1386 -> 0.016233766 | M24: =_xlfn.NORM.DIST(K24,AVERAGE($G$2:$G$1387),_xlfn.STDEV.S($G$2:$G$1387),TRUE()) -> 0.014436285
A25: =ROW()-1 -> 24 | B25: ='Analysis Data'!A25 -> Coral Gables | C25: ='Analysis Data'!B25 -> 40309 | D25: ='Analysis Data'!C25 -> 223.61276 | E25: =SUMPRODUCT('Final Model'!$B$45:$I$45,'Analysis Data'!N25:U25) -> 194.48667 | F25: =D25-E25 -> 29.126093 | G25: =F25/'Final Model'!$B$21 -> 0.59402187 | H25: =F25^2 -> 848.32928 | J25: =A25 -> 24 | K25: =SMALL($G$2:$G$1387,J25) -> -2.1368359 | L25: =(J25-0.5)/1386 -> 0.016955267 | M25: =_xlfn.NORM.DIST(K25,AVERAGE($G$2:$G$1387),_xlfn.STDEV.S($G$2:$G$1387),TRUE()) -> 0.016086428
A26: =ROW()-1 -> 25 | B26: ='Analysis Data'!A26 -> Coral Gables | C26: ='Analysis Data'!B26 -> 40316 | D26: ='Analysis Data'!C26 -> 216.3697 | E26: =SUMPRODUCT('Final Model'!$B$45:$I$45,'Analysis Data'!N26:U26) -> 192.86178 | F26: =D26-E26 -> 23.507915 | G26: =F26/'Final Model'!$B$21 -> 0.47944006 | H26: =F26^2 -> 552.62205 | J26: =A26 -> 25 | K26: =SMALL($G$2:$G$1387,J26) -> -2.1258685 | L26: =(J26-0.5)/1386 -> 0.017676768 | M26: =_xlfn.NORM.DIST(K26,AVERAGE($G$2:$G$1387),_xlfn.STDEV.S($G$2:$G$1387),TRUE()) -> 0.016533816
A27: =ROW()-1 -> 26 | B27: ='Analysis Data'!A27 -> Coral Gables | C27: ='Analysis Data'!B27 -> 40323 | D27: ='Analysis Data'!C27 -> 205.53494 | E27: =SUMPRODUCT('Final Model'!$B$45:$I$45,'Analysis Data'!N27:U27) -> 190.42646 | F27: =D27-E27 -> 15.108482 | G27: =F27/'Final Model'!$B$21 -> 0.30813501 | H27: =F27^2 -> 228.26623 | J27: =A27 -> 26 | K27: =SMALL($G$2:$G$1387,J27) -> -2.1136395 | L27: =(J27-0.5)/1386 -> 0.018398268 | M27: =_xlfn.NORM.DIST(K27,AVERAGE($G$2:$G$1387),_xlfn.STDEV.S($G$2:$G$1387),TRUE()) -> 0.017045184
A28: =ROW()-1 -> 27 | B28: ='Analysis Data'!A28 -> Coral Gables | C28: ='Analysis Data'!B28 -> 40330 | D28: ='Analysis Data'!C28 -> 131.62653 | E28: =SUMPRODUCT('Final Model'!$B$45:$I$45,'Analysis Data'!N28:U28) -> 187.35188 | F28: =D28-E28 -> -55.72535 | G28: =F28/'Final Model'!$B$21 -> -1.1365094 | H28: =F28^2 -> 3105.3147 | J28: =A28 -> 27 | K28: =SMALL($G$2:$G$1387,J28) -> -2.0748945 | L28: =(J28-0.5)/1386 -> 0.019119769 | M28: =_xlfn.NORM.DIST(K28,AVERAGE($G$2:$G$1387),_xlfn.STDEV.S($G$2:$G$1387),TRUE()) -> 0.018755528
A29: =ROW()-1 -> 28 | B29: ='Analysis Data'!A29 -> Coral Gables | C29: ='Analysis Data'!B29 -> 40337 | D29: ='Analysis Data'!C29 -> 199.93391 | E29: =SUMPRODUCT('Final Model'!$B$45:$I$45,'Analysis Data'!N29:U29) -> 179.95482 | F29: =D29-E29 -> 19.979089 | G29: =F29/'Final Model'!$B$21 -> 0.40747024 | H29: =F29^2 -> 399.16401 | J29: =A29 -> 28 | K29: =SMALL($G$2:$G$1387,J29) -> -2.0291685 | L29: =(J29-0.5)/1386 -> 0.01984127 | M29: =_xlfn.NORM.DIST(K29,AVERAGE($G$2:$G$1387),_xlfn.STDEV.S($G$2:$G$1387),TRUE()) -> 0.020959877
A30: =ROW()-1 -> 29 | B30: ='Analysis Data'!A30 -> Coral Gables | C30: ='Analysis Data'!B30 -> 40344 | D30: ='Analysis Data'!C30 -> 217.95189 | E30: =SUMPRODUCT('Final Model'!$B$45:$I$45,'Analysis Data'!N30:U30) -> 181.01217 | F30: =D30-E30 -> 36.939722 | G30: =F30/'Final Model'!$B$21 -> 0.75337957 | H30: =F30^2 -> 1364.5431 | J30: =A30 -> 29 | K30: =SMALL($G$2:$G$1387,J30) -> -2.0059579 | L30: =(J30-0.5)/1386 -> 0.020562771 | M30: =_xlfn.NORM.DIST(K30,AVERAGE($G$2:$G$1387),_xlfn.STDEV.S($G$2:$G$1387),TRUE()) -> 0.02216028
A31: =ROW()-1 -> 30 | B31: ='Analysis Data'!A31 -> Coral Gables | C31: ='Analysis Data'!B31 -> 40351 | D31: ='Analysis Data'!C31 -> 139.61353 | E31: =SUMPRODUCT('Final Model'!$B$45:$I$45,'Analysis Data'!N31:U31) -> 180.32259 | F31: =D31-E31 -> -40.709062 | G31: =F31/'Final Model'!$B$21 -> -0.83025464 | H31: =F31^2 -> 1657.2278 | J31: =A31 -> 30 | K31: =SMALL($G$2:$G$1387,J31) -> -1.9828676 | L31: =(J31-0.5)/1386 -> 0.021284271 | M31: =_xlfn.NORM.DIST(K31,AVERAGE($G$2:$G$1387),_xlfn.STDEV.S($G$2:$G$1387),TRUE()) -> 0.023411511
A32: =ROW()-1 -> 31 | B32: ='Analysis Data'!A32 -> Coral Gables | C32: ='Analysis Data'!B32 -> 40358 | D32: ='Analysis Data'!C32 -> 106.41657 | E32: =SUMPRODUCT('Final Model'!$B$45:$I$45,'Analysis Data'!N32:U32) -> 177.43699 | F32: =D32-E32 -> -71.020428 | G32: =F32/'Final Model'!$B$21 -> -1.44845 | H32: =F32^2 -> 5043.9013 | J32: =A32 -> 31 | K32: =SMALL($G$2:$G$1387,J32) -> -1.9636939 | L32: =(J32-0.5)/1386 -> 0.022005772 | M32: =_xlfn.NORM.DIST(K32,AVERAGE($G$2:$G$1387),_xlfn.STDEV.S($G$2:$G$1387),TRUE()) -> 0.0244952
... A1387: =ROW()-1 -> 1386 | B1387: ='Analysis Data'!A1387 -> Veterans | C1387: ='Analysis Data'!B1387 -> 40372 | D1387: ='Analysis Data'!C1387 -> 166.89303 | E1387: =SUMPRODUCT('Final Model'!$B$45:$I$45,'Analysis Data'!N1387:U1387) -> 184.11548 | F1387: =D1387-E1387 -> -17.222456 | G1387: =F1387/'Final Model'!$B$21 -> -0.35124915 | H1387: =F1387^2 -> 296.61298 | J1387: =A1387 -> 1386 | K1387: =SMALL($G$2:$G$1387,J1387) -> 3.7245607 | L1387: =(J1387-0.5)/1386 -> 0.99963925 | M1387: =_xlfn.NORM.DIST(K1387,AVERAGE($G$2:$G$1387),_xlfn.STDEV.S($G$2:$G$1387),TRUE()) -> 0.99990577

Sheet VIF
A1: MULTICOLLINEARITY: correlation-matrix inverse method (VIF_j = j-th diagonal of inverse correlation matrix; Tolerance = 1/VIF). Course rule of thumb: VIF > 4 (some authors 10) signals concern.
A3: Final model predictors
B4: Price | C4: Rep | D4: Endcap | E4: Demo | F4: D13 | G4: D45 | H4: EndRep
A5: Price | B5: =CORREL('Analysis Data'!$O$2:$O$1387,'Analysis Data'!$O$2:$O$1387) -> 1 | C5: =CORREL('Analysis Data'!$O$2:$O$1387,'Analysis Data'!$P$2:$P$1387) -> 0.32890041 | D5: =CORREL('Analysis Data'!$O$2:$O$1387,'Analysis Data'!$Q$2:$Q$1387) -> -0.067293565 | E5: =CORREL('Analysis Data'!$O$2:$O$1387,'Analysis Data'!$R$2:$R$1387) -> 0.051664462 | F5: =CORREL('Analysis Data'!$O$2:$O$1387,'Analysis Data'!$S$2:$S$1387) -> -0.01509762 | G5: =CORREL('Analysis Data'!$O$2:$O$1387,'Analysis Data'!$T$2:$T$1387) -> 0.087935982 | H5: =CORREL('Analysis Data'!$O$2:$O$1387,'Analysis Data'!$U$2:$U$1387) -> -0.058266802
A6: Rep | B6: =CORREL('Analysis Data'!$P$2:$P$1387,'Analysis Data'!$O$2:$O$1387) -> 0.32890041 | C6: =CORREL('Analysis Data'!$P$2:$P$1387,'Analysis Data'!$P$2:$P$1387) -> 1 | D6: =CORREL('Analysis Data'!$P$2:$P$1387,'Analysis Data'!$Q$2:$Q$1387) -> 0.0518869 | E6: =CORREL('Analysis Data'!$P$2:$P$1387,'Analysis Data'!$R$2:$R$1387) -> 0.1512641 | F6: =CORREL('Analysis Data'!$P$2:$P$1387,'Analysis Data'!$S$2:$S$1387) -> 0.24222744 | G6: =CORREL('Analysis Data'!$P$2:$P$1387,'Analysis Data'!$T$2:$T$1387) -> 0.13850847 | H6: =CORREL('Analysis Data'!$P$2:$P$1387,'Analysis Data'!$U$2:$U$1387) -> 0.14777439
A7: Endcap | B7: =CORREL('Analysis Data'!$Q$2:$Q$1387,'Analysis Data'!$O$2:$O$1387) -> -0.067293565 | C7: =CORREL('Analysis Data'!$Q$2:$Q$1387,'Analysis Data'!$P$2:$P$1387) -> 0.0518869 | D7: =CORREL('Analysis Data'!$Q$2:$Q$1387,'Analysis Data'!$Q$2:$Q$1387) -> 1 | E7: =CORREL('Analysis Data'!$Q$2:$Q$1387,'Analysis Data'!$R$2:$R$1387) -> 0.078630074 | F7: =CORREL('Analysis Data'!$Q$2:$Q$1387,'Analysis Data'!$S$2:$S$1387) -> 0.090093443 | G7: =CORREL('Analysis Data'!$Q$2:$Q$1387,'Analysis Data'!$T$2:$T$1387) -> -0.00021542548 | H7: =CORREL('Analysis Data'!$Q$2:$Q$1387,'Analysis Data'!$U$2:$U$1387) -> 0.81895777
A8: Demo | B8: =CORREL('Analysis Data'!$R$2:$R$1387,'Analysis Data'!$O$2:$O$1387) -> 0.051664462 | C8: =CORREL('Analysis Data'!$R$2:$R$1387,'Analysis Data'!$P$2:$P$1387) -> 0.1512641 | D8: =CORREL('Analysis Data'!$R$2:$R$1387,'Analysis Data'!$Q$2:$Q$1387) -> 0.078630074 | E8: =CORREL('Analysis Data'!$R$2:$R$1387,'Analysis Data'!$R$2:$R$1387) -> 1 | F8: =CORREL('Analysis Data'!$R$2:$R$1387,'Analysis Data'!$S$2:$S$1387) -> 0.036549317 | G8: =CORREL('Analysis Data'!$R$2:$R$1387,'Analysis Data'!$T$2:$T$1387) -> -0.013208807 | H8: =CORREL('Analysis Data'!$R$2:$R$1387,'Analysis Data'!$U$2:$U$1387) -> 0.094677756
A9: D13 | B9: =CORREL('Analysis Data'!$S$2:$S$1387,'Analysis Data'!$O$2:$O$1387) -> -0.01509762 | C9: =CORREL('Analysis Data'!$S$2:$S$1387,'Analysis Data'!$P$2:$P$1387) -> 0.24222744 | D9: =CORREL('Analysis Data'!$S$2:$S$1387,'Analysis Data'!$Q$2:$Q$1387) -> 0.090093443 | E9: =CORREL('Analysis Data'!$S$2:$S$1387,'Analysis Data'!$R$2:$R$1387) -> 0.036549317 | F9: =CORREL('Analysis Data'!$S$2:$S$1387,'Analysis Data'!$S$2:$S$1387) -> 1 | G9: =CORREL('Analysis Data'!$S$2:$S$1387,'Analysis Data'!$T$2:$T$1387) -> 0.011709819 | H9: =CORREL('Analysis Data'!$S$2:$S$1387,'Analysis Data'!$U$2:$U$1387) -> 0.10440063
A10: D45 | B10: =CORREL('Analysis Data'!$T$2:$T$1387,'Analysis Data'!$O$2:$O$1387) -> 0.087935982 | C10: =CORREL('Analysis Data'!$T$2:$T$1387,'Analysis Data'!$P$2:$P$1387) -> 0.13850847 | D10: =CORREL('Analysis Data'!$T$2:$T$1387,'Analysis Data'!$Q$2:$Q$1387) -> -0.00021542548 | E10: =CORREL('Analysis Data'!$T$2:$T$1387,'Analysis Data'!$R$2:$R$1387) -> -0.013208807 | F10: =CORREL('Analysis Data'!$T$2:$T$1387,'Analysis Data'!$S$2:$S$1387) -> 0.011709819 | G10: =CORREL('Analysis Data'!$T$2:$T$1387,'Analysis Data'!$T$2:$T$1387) -> 1 | H10: =CORREL('Analysis Data'!$T$2:$T$1387,'Analysis Data'!$U$2:$U$1387) -> -0.012467322
A11: EndRep | B11: =CORREL('Analysis Data'!$U$2:$U$1387,'Analysis Data'!$O$2:$O$1387) -> -0.058266802 | C11: =CORREL('Analysis Data'!$U$2:$U$1387,'Analysis Data'!$P$2:$P$1387) -> 0.14777439 | D11: =CORREL('Analysis Data'!$U$2:$U$1387,'Analysis Data'!$Q$2:$Q$1387) -> 0.81895777 | E11: =CORREL('Analysis Data'!$U$2:$U$1387,'Analysis Data'!$R$2:$R$1387) -> 0.094677756 | F11: =CORREL('Analysis Data'!$U$2:$U$1387,'Analysis Data'!$S$2:$S$1387) -> 0.10440063 | G11: =CORREL('Analysis Data'!$U$2:$U$1387,'Analysis Data'!$T$2:$T$1387) -> -0.012467322 | H11: =CORREL('Analysis Data'!$U$2:$U$1387,'Analysis Data'!$U$2:$U$1387) -> 1
A13: Inverse of correlation matrix
B14: {=MINVERSE(B5:H11)} -> 1.1488715 | C14: -0.41449853 | D14: -0.018853544 | E14: -0.01224484 | F14: 0.10650291 | G14: -0.0433687 | H14: 0.13313324
B15: -0.41449853 | C15: 1.2939225 | D15: 0.25605487 | E15: -0.14940933 | F15: -0.29571365 | G15: -0.14598627 | H15: -0.38185986
B16: -0.018853544 | C16: 0.25605487 | D16: 3.0923861 | E16: -0.036654348 | F16: -0.071407516 | G16: -0.064722878 | H16: -2.5613521
B17: -0.01224484 | C17: -0.14940933 | D17: -0.036654348 | E17: 1.0307454 | F17: 0.0060735987 | G17: 0.034728561 | H17: -0.046406007
B18: 0.10650291 | C18: -0.29571365 | D18: -0.071407516 | E18: 0.0060735987 | F18: 1.0797156 | G18: 0.018956661 | H18: -0.0046774568
B19: -0.0433687 | C19: -0.14598627 | D19: -0.064722878 | E19: 0.034728561 | F19: 0.018956661 | G19: 1.0252488 | H19: 0.079566378
B20: 0.13313324 | C20: -0.38185986 | D20: -2.5613521 | E20: -0.046406007 | F20: -0.0046774568 | G20: 0.079566378 | H20: 3.1676995
A22: Variable | B22: VIF | C22: Tolerance | D22: Flag (VIF>4)
A23: Price | B23: =B14 -> 1.1488715 | C23: =1/B23 -> 0.87041937 | D23: =IF(B23>4,"Check","OK") -> OK
A24: Rep | B24: =C15 -> 1.2939225 | C24: =1/B24 -> 0.77284381 | D24: =IF(B24>4,"Check","OK") -> OK
A25: Endcap | B25: =D16 -> 3.0923861 | C25: =1/B25 -> 0.32337488 | D25: =IF(B25>4,"Check","OK") -> OK
A26: Demo | B26: =E17 -> 1.0307454 | C26: =1/B26 -> 0.9701717 | D26: =IF(B26>4,"Check","OK") -> OK
A27: D13 | B27: =F18 -> 1.0797156 | C27: =1/B27 -> 0.92616981 | D27: =IF(B27>4,"Check","OK") -> OK
A28: D45 | B28: =G19 -> 1.0252488 | C28: =1/B28 -> 0.97537302 | D28: =IF(B28>4,"Check","OK") -> OK
A29: EndRep | B29: =H20 -> 3.1676995 | C29: =1/B29 -> 0.31568651 | D29: =IF(B29>4,"Check","OK") -> OK
A32: Model 1 (Full MLR) predictors
B33: Price | C33: Rep | D33: Endcap | E33: Demo | F33: D13 | G33: D45 | H33: Natural | I33: Fitness
A34: Price | B34: =CORREL('Analysis Data'!$D$2:$D$1387,'Analysis Data'!$D$2:$D$1387) -> 1 | C34: =CORREL('Analysis Data'!$D$2:$D$1387,'Analysis Data'!$E$2:$E$1387) -> 0.32890041 | D34: =CORREL('Analysis Data'!$D$2:$D$1387,'Analysis Data'!$F$2:$F$1387) -> -0.067293565 | E34: =CORREL('Analysis Data'!$D$2:$D$1387,'Analysis Data'!$G$2:$G$1387) -> 0.051664462 | F34: =CORREL('Analysis Data'!$D$2:$D$1387,'Analysis Data'!$H$2:$H$1387) -> -0.01509762 | G34: =CORREL('Analysis Data'!$D$2:$D$1387,'Analysis Data'!$I$2:$I$1387) -> 0.087935982 | H34: =CORREL('Analysis Data'!$D$2:$D$1387,'Analysis Data'!$J$2:$J$1387) -> -0.0048123855 | I34: =CORREL('Analysis Data'!$D$2:$D$1387,'Analysis Data'!$K$2:$K$1387) -> 0.071174912
A35: Rep | B35: =CORREL('Analysis Data'!$E$2:$E$1387,'Analysis Data'!$D$2:$D$1387) -> 0.32890041 | C35: =CORREL('Analysis Data'!$E$2:$E$1387,'Analysis Data'!$E$2:$E$1387) -> 1 | D35: =CORREL('Analysis Data'!$E$2:$E$1387,'Analysis Data'!$F$2:$F$1387) -> 0.0518869 | E35: =CORREL('Analysis Data'!$E$2:$E$1387,'Analysis Data'!$G$2:$G$1387) -> 0.1512641 | F35: =CORREL('Analysis Data'!$E$2:$E$1387,'Analysis Data'!$H$2:$H$1387) -> 0.24222744 | G35: =CORREL('Analysis Data'!$E$2:$E$1387,'Analysis Data'!$I$2:$I$1387) -> 0.13850847 | H35: =CORREL('Analysis Data'!$E$2:$E$1387,'Analysis Data'!$J$2:$J$1387) -> 0.089318908 | I35: =CORREL('Analysis Data'!$E$2:$E$1387,'Analysis Data'!$K$2:$K$1387) -> 0.057511255
A36: Endcap | B36: =CORREL('Analysis Data'!$F$2:$F$1387,'Analysis Data'!$D$2:$D$1387) -> -0.067293565 | C36: =CORREL('Analysis Data'!$F$2:$F$1387,'Analysis Data'!$E$2:$E$1387) -> 0.0518869 | D36: =CORREL('Analysis Data'!$F$2:$F$1387,'Analysis Data'!$F$2:$F$1387) -> 1 | E36: =CORREL('Analysis Data'!$F$2:$F$1387,'Analysis Data'!$G$2:$G$1387) -> 0.078630074 | F36: =CORREL('Analysis Data'!$F$2:$F$1387,'Analysis Data'!$H$2:$H$1387) -> 0.090093443 | G36: =CORREL('Analysis Data'!$F$2:$F$1387,'Analysis Data'!$I$2:$I$1387) -> -0.00021542548 | H36: =CORREL('Analysis Data'!$F$2:$F$1387,'Analysis Data'!$J$2:$J$1387) -> 0.081884463 | I36: =CORREL('Analysis Data'!$F$2:$F$1387,'Analysis Data'!$K$2:$K$1387) -> -0.059635101
A37: Demo | B37: =CORREL('Analysis Data'!$G$2:$G$1387,'Analysis Data'!$D$2:$D$1387) -> 0.051664462 | C37: =CORREL('Analysis Data'!$G$2:$G$1387,'Analysis Data'!$E$2:$E$1387) -> 0.1512641 | D37: =CORREL('Analysis Data'!$G$2:$G$1387,'Analysis Data'!$F$2:$F$1387) -> 0.078630074 | E37: =CORREL('Analysis Data'!$G$2:$G$1387,'Analysis Data'!$G$2:$G$1387) -> 1 | F37: =CORREL('Analysis Data'!$G$2:$G$1387,'Analysis Data'!$H$2:$H$1387) -> 0.036549317 | G37: =CORREL('Analysis Data'!$G$2:$G$1387,'Analysis Data'!$I$2:$I$1387) -> -0.013208807 | H37: =CORREL('Analysis Data'!$G$2:$G$1387,'Analysis Data'!$J$2:$J$1387) -> -0.0011064623 | I37: =CORREL('Analysis Data'!$G$2:$G$1387,'Analysis Data'!$K$2:$K$1387) -> 0.0066231384
A38: D13 | B38: =CORREL('Analysis Data'!$H$2:$H$1387,'Analysis Data'!$D$2:$D$1387) -> -0.01509762 | C38: =CORREL('Analysis Data'!$H$2:$H$1387,'Analysis Data'!$E$2:$E$1387) -> 0.24222744 | D38: =CORREL('Analysis Data'!$H$2:$H$1387,'Analysis Data'!$F$2:$F$1387) -> 0.090093443 | E38: =CORREL('Analysis Data'!$H$2:$H$1387,'Analysis Data'!$G$2:$G$1387) -> 0.036549317 | F38: =CORREL('Analysis Data'!$H$2:$H$1387,'Analysis Data'!$H$2:$H$1387) -> 1 | G38: =CORREL('Analysis Data'!$H$2:$H$1387,'Analysis Data'!$I$2:$I$1387) -> 0.011709819 | H38: =CORREL('Analysis Data'!$H$2:$H$1387,'Analysis Data'!$J$2:$J$1387) -> -0.0048556907 | I38: =CORREL('Analysis Data'!$H$2:$H$1387,'Analysis Data'!$K$2:$K$1387) -> 0.0083132341
A39: D45 | B39: =CORREL('Analysis Data'!$I$2:$I$1387,'Analysis Data'!$D$2:$D$1387) -> 0.087935982 | C39: =CORREL('Analysis Data'!$I$2:$I$1387,'Analysis Data'!$E$2:$E$1387) -> 0.13850847 | D39: =CORREL('Analysis Data'!$I$2:$I$1387,'Analysis Data'!$F$2:$F$1387) -> -0.00021542548 | E39: =CORREL('Analysis Data'!$I$2:$I$1387,'Analysis Data'!$G$2:$G$1387) -> -0.013208807 | F39: =CORREL('Analysis Data'!$I$2:$I$1387,'Analysis Data'!$H$2:$H$1387) -> 0.011709819 | G39: =CORREL('Analysis Data'!$I$2:$I$1387,'Analysis Data'!$I$2:$I$1387) -> 1 | H39: =CORREL('Analysis Data'!$I$2:$I$1387,'Analysis Data'!$J$2:$J$1387) -> 0.01364753 | I39: =CORREL('Analysis Data'!$I$2:$I$1387,'Analysis Data'!$K$2:$K$1387) -> -0.011987461
A40: Natural | B40: =CORREL('Analysis Data'!$J$2:$J$1387,'Analysis Data'!$D$2:$D$1387) -> -0.0048123855 | C40: =CORREL('Analysis Data'!$J$2:$J$1387,'Analysis Data'!$E$2:$E$1387) -> 0.089318908 | D40: =CORREL('Analysis Data'!$J$2:$J$1387,'Analysis Data'!$F$2:$F$1387) -> 0.081884463 | E40: =CORREL('Analysis Data'!$J$2:$J$1387,'Analysis Data'!$G$2:$G$1387) -> -0.0011064623 | F40: =CORREL('Analysis Data'!$J$2:$J$1387,'Analysis Data'!$H$2:$H$1387) -> -0.0048556907 | G40: =CORREL('Analysis Data'!$J$2:$J$1387,'Analysis Data'!$I$2:$I$1387) -> 0.01364753 | H40: =CORREL('Analysis Data'!$J$2:$J$1387,'Analysis Data'!$J$2:$J$1387) -> 1 | I40: =CORREL('Analysis Data'!$J$2:$J$1387,'Analysis Data'!$K$2:$K$1387) -> -0.085627579
A41: Fitness | B41: =CORREL('Analysis Data'!$K$2:$K$1387,'Analysis Data'!$D$2:$D$1387) -> 0.071174912 | C41: =CORREL('Analysis Data'!$K$2:$K$1387,'Analysis Data'!$E$2:$E$1387) -> 0.057511255 | D41: =CORREL('Analysis Data'!$K$2:$K$1387,'Analysis Data'!$F$2:$F$1387) -> -0.059635101 | E41: =CORREL('Analysis Data'!$K$2:$K$1387,'Analysis Data'!$G$2:$G$1387) -> 0.0066231384 | F41: =CORREL('Analysis Data'!$K$2:$K$1387,'Analysis Data'!$H$2:$H$1387) -> 0.0083132341 | G41: =CORREL('Analysis Data'!$K$2:$K$1387,'Analysis Data'!$I$2:$I$1387) -> -0.011987461 | H41: =CORREL('Analysis Data'!$K$2:$K$1387,'Analysis Data'!$J$2:$J$1387) -> -0.085627579 | I41: =CORREL('Analysis Data'!$K$2:$K$1387,'Analysis Data'!$K$2:$K$1387) -> 1
A43: Inverse of correlation matrix
B44: {=MINVERSE(B34:I41)} -> 1.1472236 | C44: -0.39948437 | D44: 0.083262885 | E44: -0.0095923032 | F44: 0.10808435 | G44: -0.047977487 | H44: 0.031061095 | I44: -0.052463739
B45: -0.39948437 | C45: 1.2628989 | D45: -0.046834186 | E45: -0.15730679 | F45: -0.30046472 | G45: -0.13744742 | H45: -0.11535289 | I45: -0.054975931
B46: 0.083262885 | C46: -0.046834186 | D46: 1.030402 | E46: -0.075798241 | F46: -0.078279337 | G46: 0.00097024358 | H46: -0.075738019 | I46: 0.052894533
B47: -0.0095923032 | C47: -0.15730679 | D47: -0.075798241 | E47: 1.0304952 | F47: 0.0068013266 | G47: 0.035868272 | H47: 0.020941898 | I47: 0.00055092701
B48: 0.10808435 | C48: -0.30046472 | D48: -0.078279337 | E48: 0.0068013266 | F48: 1.0811869 | G48: 0.018989644 | H48: 0.038716535 | I48: -0.00057135185
B49: -0.047977487 | C49: -0.13744742 | D49: 0.00097024358 | E49: 0.035868272 | F49: 0.018989644 | G49: 1.0237855 | H49: 0.00011817246 | I49: 0.023264709
B50: 0.031061095 | C50: -0.11535289 | D50: -0.075738019 | E50: 0.020941898 | F50: 0.038716535 | G50: 0.00011817246 | H50: 1.0243271 | I50: 0.087158183
B51: -0.052463739 | C51: -0.054975931 | D51: 0.052894533 | E51: 0.00055092701 | F51: -0.00057135185 | G51: 0.023264709 | H51: 0.087158183 | I51: 1.0177933
A53: Variable | B53: VIF | C53: Tolerance | D53: Flag (VIF>4)
A54: Price | B54: =B44 -> 1.1472236 | C54: =1/B54 -> 0.87166969 | D54: =IF(B54>4,"Check","OK") -> OK
A55: Rep | B55: =C45 -> 1.2628989 | C55: =1/B55 -> 0.79182903 | D55: =IF(B55>4,"Check","OK") -> OK
A56: Endcap | B56: =D46 -> 1.030402 | C56: =1/B56 -> 0.97049505 | D56: =IF(B56>4,"Check","OK") -> OK
A57: Demo | B57: =E47 -> 1.0304952 | C57: =1/B57 -> 0.97040725 | D57: =IF(B57>4,"Check","OK") -> OK
A58: D13 | B58: =F48 -> 1.0811869 | C58: =1/B58 -> 0.9249095 | D58: =IF(B58>4,"Check","OK") -> OK
A59: D45 | B59: =G49 -> 1.0237855 | C59: =1/B59 -> 0.97676713 | D59: =IF(B59>4,"Check","OK") -> OK
A60: Natural | B60: =H50 -> 1.0243271 | C60: =1/B60 -> 0.97625062 | D60: =IF(B60>4,"Check","OK") -> OK
A61: Fitness | B61: =I51 -> 1.0177933 | C61: =1/B61 -> 0.98251773 | D61: =IF(B61>4,"Check","OK") -> OK
A62: Reading: all VIFs <1.4 except Endcap (3.1) and Endcap x Rep (3.2), whose overlap is structural (interaction with its own component) and below the course threshold of 4. No multicollinearity concern.

Sheet Outliers
A1: OUTLIER ANALYSIS: largest studentized residuals (formula-driven from Influence sheet)
A3: Counts
A4: |studentized resid| > 2 | B4: =COUNTIF(Influence!I2:I1387,">2") -> 64
A5: |studentized resid| > 3 | B5: =COUNTIF(Influence!I2:I1387,">3") -> 5
A6: Expected beyond ±2 if normal (≈4.55% of n) | B6: =0.0455*1386 -> 63.063
A7: Expected beyond ±3 if normal (≈0.27% of n) | B7: =0.0027*1386 -> 3.7422
A9: Rank | B9: |Stud resid| | C9: Obs # | D9: Store | E9: Date | F9: Sales | G9: Fitted | H9: Residual
A10: 1 | B10: =LARGE(Influence!$I$2:$I$1387,A10) -> 3.7284 | C10: =MATCH(B10,Influence!$I$2:$I$1387,0) -> 436 | D10: =INDEX('Residual Diagnostics'!$B$2:$B$1387,C10) -> South Loop | E10: =INDEX('Residual Diagnostics'!$C$2:$C$1387,C10) -> 40344 | F10: =INDEX('Residual Diagnostics'!$D$2:$D$1387,C10) -> 428.2595 | G10: =INDEX('Residual Diagnostics'!$E$2:$E$1387,C10) -> 245.63677 | H10: =INDEX('Residual Diagnostics'!$F$2:$F$1387,C10) -> 182.62274
A11: 2 | B11: =LARGE(Influence!$I$2:$I$1387,A11) -> 3.4278074 | C11: =MATCH(B11,Influence!$I$2:$I$1387,0) -> 353 | D11: =INDEX('Residual Diagnostics'!$B$2:$B$1387,C11) -> Lakeview | E11: =INDEX('Residual Diagnostics'!$C$2:$C$1387,C11) -> 40302 | F11: =INDEX('Residual Diagnostics'!$D$2:$D$1387,C11) -> 66.386653 | G11: =INDEX('Residual Diagnostics'!$E$2:$E$1387,C11) -> 234.26034 | H11: =INDEX('Residual Diagnostics'!$F$2:$F$1387,C11) -> -167.87368
A12: 3 | B12: =LARGE(Influence!$I$2:$I$1387,A12) -> 3.2007059 | C12: =MATCH(B12,Influence!$I$2:$I$1387,0) -> 938 | D12: =INDEX('Residual Diagnostics'!$B$2:$B$1387,C12) -> Mill Plain | E12: =INDEX('Residual Diagnostics'!$C$2:$C$1387,C12) -> 40316 | F12: =INDEX('Residual Diagnostics'!$D$2:$D$1387,C12) -> 469.6665 | G12: =INDEX('Residual Diagnostics'!$E$2:$E$1387,C12) -> 313.51533 | H12: =INDEX('Residual Diagnostics'!$F$2:$F$1387,C12) -> 156.15117
A13: 4 | B13: =LARGE(Influence!$I$2:$I$1387,A13) -> 3.0684631 | C13: =MATCH(B13,Influence!$I$2:$I$1387,0) -> 458 | D13: =INDEX('Residual Diagnostics'!$B$2:$B$1387,C13) -> Wheaton | E13: =INDEX('Residual Diagnostics'!$C$2:$C$1387,C13) -> 40344 | F13: =INDEX('Residual Diagnostics'!$D$2:$D$1387,C13) -> 196.44881 | G13: =INDEX('Residual Diagnostics'!$E$2:$E$1387,C13) -> 345.91667 | H13: =INDEX('Residual Diagnostics'!$F$2:$F$1387,C13) -> -149.46786
A14: 5 | B14: =LARGE(Influence!$I$2:$I$1387,A14) -> 3.0249282 | C14: =MATCH(B14,Influence!$I$2:$I$1387,0) -> 762 | D14: =INDEX('Residual Diagnostics'!$B$2:$B$1387,C14) -> Stevens Creek (aka Cupertino) | E14: =INDEX('Residual Diagnostics'!$C$2:$C$1387,C14) -> 40316 | F14: =INDEX('Residual Diagnostics'!$D$2:$D$1387,C14) -> 237.75002 | G14: =INDEX('Residual Diagnostics'!$E$2:$E$1387,C14) -> 385.04883 | H14: =INDEX('Residual Diagnostics'!$F$2:$F$1387,C14) -> -147.29881
A15: 6 | B15: =LARGE(Influence!$I$2:$I$1387,A15) -> 2.8686673 | C15: =MATCH(B15,Influence!$I$2:$I$1387,0) -> 325 | D15: =INDEX('Residual Diagnostics'!$B$2:$B$1387,C15) -> Galleria | E15: =INDEX('Residual Diagnostics'!$C$2:$C$1387,C15) -> 40337 | F15: =INDEX('Residual Diagnostics'!$D$2:$D$1387,C15) -> 112.29142 | G15: =INDEX('Residual Diagnostics'!$E$2:$E$1387,C15) -> 252.74326 | H15: =INDEX('Residual Diagnostics'!$F$2:$F$1387,C15) -> -140.45184
A16: 7 | B16: =LARGE(Influence!$I$2:$I$1387,A16) -> 2.8531726 | C16: =MATCH(B16,Influence!$I$2:$I$1387,0) -> 751 | D16: =INDEX('Residual Diagnostics'!$B$2:$B$1387,C16) -> SoMa | E16: =INDEX('Residual Diagnostics'!$C$2:$C$1387,C16) -> 40316 | F16: =INDEX('Residual Diagnostics'!$D$2:$D$1387,C16) -> 247.3412 | G16: =INDEX('Residual Diagnostics'!$E$2:$E$1387,C16) -> 386.28332 | H16: =INDEX('Residual Diagnostics'!$F$2:$F$1387,C16) -> -138.94212
A17: 8 | B17: =LARGE(Influence!$I$2:$I$1387,A17) -> 2.8469231 | C17: =MATCH(B17,Influence!$I$2:$I$1387,0) -> 881 | D17: =INDEX('Residual Diagnostics'!$B$2:$B$1387,C17) -> White Plains | E17: =INDEX('Residual Diagnostics'!$C$2:$C$1387,C17) -> 40302 | F17: =INDEX('Residual Diagnostics'!$D$2:$D$1387,C17) -> 120.51899 | G17: =INDEX('Residual Diagnostics'!$E$2:$E$1387,C17) -> 259.29791 | H17: =INDEX('Residual Diagnostics'!$F$2:$F$1387,C17) -> -138.77892
A18: 9 | B18: =LARGE(Influence!$I$2:$I$1387,A18) -> 2.8022844 | C18: =MATCH(B18,Influence!$I$2:$I$1387,0) -> 270 | D18: =INDEX('Residual Diagnostics'!$B$2:$B$1387,C18) -> Short Pump | E18: =INDEX('Residual Diagnostics'!$C$2:$C$1387,C18) -> 40337 | F18: =INDEX('Residual Diagnostics'!$D$2:$D$1387,C18) -> 51.733293 | G18: =INDEX('Residual Diagnostics'!$E$2:$E$1387,C18) -> 189.01912 | H18: =INDEX('Residual Diagnostics'!$F$2:$F$1387,C18) -> -137.28582
A19: 10 | B19: =LARGE(Influence!$I$2:$I$1387,A19) -> 2.7410617 | C19: =MATCH(B19,Influence!$I$2:$I$1387,0) -> 560 | D19: =INDEX('Residual Diagnostics'!$B$2:$B$1387,C19) -> Newtonville | E19: =INDEX('Residual Diagnostics'!$C$2:$C$1387,C19) -> 40365 | F19: =INDEX('Residual Diagnostics'!$D$2:$D$1387,C19) -> 47.559852 | G19: =INDEX('Residual Diagnostics'!$E$2:$E$1387,C19) -> 181.81428 | H19: =INDEX('Residual Diagnostics'!$F$2:$F$1387,C19) -> -134.25442
A22: Reading: the largest studentized residual is ≈3.7; only 5 of 1,386 observations exceed 3 (≈3.7 expected under normality). No pattern of data-entry error; no observation is removed. Sensitivity: dropping flagged points leaves all key coefficients essentially unchanged (Influence / Model Comparison).

Sheet Influence
A1: Obs | B1: Leverage h | C1: Residual | D1: Studentized resid (internal) | E1: Studentized resid (deleted) | F1: Cook's D | G1: Mahalanobis D² | H1: DFFITS (standardized) | I1: |Stud. resid| | J1: Lev > 2(k+1)/n | K1: Cook > 4/(n-k-1) | L1: Mahal > 10 | M1: |DFFITS| > 2√((k+1)/n) | O1: THRESHOLDS (course notes)
A2: =ROW()-1 -> 1 | B2: =SUMPRODUCT(MMULT('Analysis Data'!N2:U2,'Final Model'!$B$59:$I$66),'Analysis Data'!N2:U2) -> 0.002457571 | C2: ='Residual Diagnostics'!F2 -> -29.000123 | D2: =C2/('Final Model'!$B$21*SQRT(1-B2)) -> -0.59218086 | E2: =D2*SQRT(('Final Model'!$B$24-1)/('Final Model'!$B$24-D2^2)) -> -0.59204129 | F2: =D2^2/($P$3+1)*B2/(1-B2) -> 0.00010799246 | G2: =($P$2-1)*(B2-1/$P$2) -> 2.4044573 | H2: =E2*SQRT(B2/(1-B2)) -> -0.029385923 | I2: =ABS(D2) -> 0.59218086 | J2: =IF(B2>$P$4,1,0) -> 0 | K2: =IF(F2>$P$6,1,0) -> 0 | L2: =IF(G2>$P$9,1,0) -> 0 | M2: =IF(ABS(H2)>$P$8,1,0) -> 0 | O2: n | P2: =COUNT('Analysis Data'!$C$2:$C$1387) -> 1386
A3: =ROW()-1 -> 2 | B3: =SUMPRODUCT(MMULT('Analysis Data'!N3:U3,'Final Model'!$B$59:$I$66),'Analysis Data'!N3:U3) -> 0.0016949693 | C3: ='Residual Diagnostics'!F3 -> 9.0447868 | D3: =C3/('Final Model'!$B$21*SQRT(1-B3)) -> 0.18462347 | E3: =D3*SQRT(('Final Model'!$B$24-1)/('Final Model'!$B$24-D3^2)) -> 0.18455875 | F3: =D3^2/($P$3+1)*B3/(1-B3) -> 7.2340653e-06 | G3: =($P$2-1)*(B3-1/$P$2) -> 1.348254 | H3: =E3*SQRT(B3/(1-B3)) -> 0.0076047324 | I3: =ABS(D3) -> 0.18462347 | J3: =IF(B3>$P$4,1,0) -> 0 | K3: =IF(F3>$P$6,1,0) -> 0 | L3: =IF(G3>$P$9,1,0) -> 0 | M3: =IF(ABS(H3)>$P$8,1,0) -> 0 | O3: k | P3: 7
A4: =ROW()-1 -> 3 | B4: =SUMPRODUCT(MMULT('Analysis Data'!N4:U4,'Final Model'!$B$59:$I$66),'Analysis Data'!N4:U4) -> 0.0017506418 | C4: ='Residual Diagnostics'!F4 -> 42.588502 | D4: =C4/('Final Model'!$B$21*SQRT(1-B4)) -> 0.86934679 | E4: =D4*SQRT(('Final Model'!$B$24-1)/('Final Model'!$B$24-D4^2)) -> 0.86926971 | F4: =D4^2/($P$3+1)*B4/(1-B4) -> 0.00016567401 | G4: =($P$2-1)*(B4-1/$P$2) -> 1.4253604 | H4: =E4*SQRT(B4/(1-B4)) -> 0.036402707 | I4: =ABS(D4) -> 0.86934679 | J4: =IF(B4>$P$4,1,0) -> 0 | K4: =IF(F4>$P$6,1,0) -> 0 | L4: =IF(G4>$P$9,1,0) -> 0 | M4: =IF(ABS(H4)>$P$8,1,0) -> 0 | O4: Leverage 2(k+1)/n | P4: =2*(P3+1)/P2 -> 0.011544012
A5: =ROW()-1 -> 4 | B5: =SUMPRODUCT(MMULT('Analysis Data'!N5:U5,'Final Model'!$B$59:$I$66),'Analysis Data'!N5:U5) -> 0.0017268645 | C5: ='Residual Diagnostics'!F5 -> 34.743391 | D5: =C5/('Final Model'!$B$21*SQRT(1-B5)) -> 0.70919836 | E5: =D5*SQRT(('Final Model'!$B$24-1)/('Final Model'!$B$24-D5^2)) -> 0.7090704 | F5: =D5^2/($P$3+1)*B5/(1-B5) -> 0.00010875628 | G5: =($P$2-1)*(B5-1/$P$2) -> 1.3924288 | H5: =E5*SQRT(B5/(1-B5)) -> 0.029491291 | I5: =ABS(D5) -> 0.70919836 | J5: =IF(B5>$P$4,1,0) -> 0 | K5: =IF(F5>$P$6,1,0) -> 0 | L5: =IF(G5>$P$9,1,0) -> 0 | M5: =IF(ABS(H5)>$P$8,1,0) -> 0 | O5: Leverage 3(k+1)/n | P5: =3*(P3+1)/P2 -> 0.017316017
A6: =ROW()-1 -> 5 | B6: =SUMPRODUCT(MMULT('Analysis Data'!N6:U6,'Final Model'!$B$59:$I$66),'Analysis Data'!N6:U6) -> 0.0016888564 | C6: ='Residual Diagnostics'!F6 -> 67.228593 | D6: =C6/('Final Model'!$B$21*SQRT(1-B6)) -> 1.3722754 | E6: =D6*SQRT(('Final Model'!$B$24-1)/('Final Model'!$B$24-D6^2)) -> 1.3727156 | F6: =D6^2/($P$3+1)*B6/(1-B6) -> 0.00039821661 | G6: =($P$2-1)*(B6-1/$P$2) -> 1.3397877 | H6: =E6*SQRT(B6/(1-B6)) -> 0.056460405 | I6: =ABS(D6) -> 1.3722754 | J6: =IF(B6>$P$4,1,0) -> 0 | K6: =IF(F6>$P$6,1,0) -> 0 | L6: =IF(G6>$P$9,1,0) -> 0 | M6: =IF(ABS(H6)>$P$8,1,0) -> 0 | O6: Cook 4/(n-k-1) | P6: =4/(P2-P3-1) -> 0.0029027576
A7: =ROW()-1 -> 6 | B7: =SUMPRODUCT(MMULT('Analysis Data'!N7:U7,'Final Model'!$B$59:$I$66),'Analysis Data'!N7:U7) -> 0.002874529 | C7: ='Residual Diagnostics'!F7 -> -44.368645 | D7: =C7/('Final Model'!$B$21*SQRT(1-B7)) -> -0.9061946 | E7: =D7*SQRT(('Final Model'!$B$24-1)/('Final Model'!$B$24-D7^2)) -> -0.90613577 | F7: =D7^2/($P$3+1)*B7/(1-B7) -> 0.00029591695 | G7: =($P$2-1)*(B7-1/$P$2) -> 2.9819442 | H7: =E7*SQRT(B7/(1-B7)) -> -0.048652114 | I7: =ABS(D7) -> 0.9061946 | J7: =IF(B7>$P$4,1,0) -> 0 | K7: =IF(F7>$P$6,1,0) -> 0 | L7: =IF(G7>$P$9,1,0) -> 0 | M7: =IF(ABS(H7)>$P$8,1,0) -> 0 | O7: Cook 1 | P7: 1
A8: =ROW()-1 -> 7 | B8: =SUMPRODUCT(MMULT('Analysis Data'!N8:U8,'Final Model'!$B$59:$I$66),'Analysis Data'!N8:U8) -> 0.0018008548 | C8: ='Residual Diagnostics'!F8 -> 36.156288 | D8: =C8/('Final Model'!$B$21*SQRT(1-B8)) -> 0.73806642 | E8: =D8*SQRT(('Final Model'!$B$24-1)/('Final Model'!$B$24-D8^2)) -> 0.73794444 | F8: =D8^2/($P$3+1)*B8/(1-B8) -> 0.0001228464 | G8: =($P$2-1)*(B8-1/$P$2) -> 1.4949054 | H8: =E8*SQRT(B8/(1-B8)) -> 0.031344 | I8: =ABS(D8) -> 0.73806642 | J8: =IF(B8>$P$4,1,0) -> 0 | K8: =IF(F8>$P$6,1,0) -> 0 | L8: =IF(G8>$P$9,1,0) -> 0 | M8: =IF(ABS(H8)>$P$8,1,0) -> 0 | O8: DFFITS 2*sqrt((k+1)/n) | P8: =2*SQRT((P3+1)/P2) -> 0.15194744
A9: =ROW()-1 -> 8 | B9: =SUMPRODUCT(MMULT('Analysis Data'!N9:U9,'Final Model'!$B$59:$I$66),'Analysis Data'!N9:U9) -> 0.0018008548 | C9: ='Residual Diagnostics'!F9 -> 60.147676 | D9: =C9/('Final Model'!$B$21*SQRT(1-B9)) -> 1.227808 | E9: =D9*SQRT(('Final Model'!$B$24-1)/('Final Model'!$B$24-D9^2)) -> 1.2280343 | F9: =D9^2/($P$3+1)*B9/(1-B9) -> 0.00033996362 | G9: =($P$2-1)*(B9-1/$P$2) -> 1.4949054 | H9: =E9*SQRT(B9/(1-B9)) -> 0.052160442 | I9: =ABS(D9) -> 1.227808 | J9: =IF(B9>$P$4,1,0) -> 0 | K9: =IF(F9>$P$6,1,0) -> 0 | L9: =IF(G9>$P$9,1,0) -> 0 | M9: =IF(ABS(H9)>$P$8,1,0) -> 0 | O9: Mahalanobis | P9: 10
A10: =ROW()-1 -> 9 | B10: =SUMPRODUCT(MMULT('Analysis Data'!N10:U10,'Final Model'!$B$59:$I$66),'Analysis Data'!N10:U10) -> 0.0018008548 | C10: ='Residual Diagnostics'!F10 -> -29.631146 | D10: =C10/('Final Model'!$B$21*SQRT(1-B10)) -> -0.60486723 | E10: =D10*SQRT(('Final Model'!$B$24-1)/('Final Model'!$B$24-D10^2)) -> -0.604728 | F10: =D10^2/($P$3+1)*B10/(1-B10) -> 8.2507159e-05 | G10: =($P$2-1)*(B10-1/$P$2) -> 1.4949054 | H10: =E10*SQRT(B10/(1-B10)) -> -0.025685666 | I10: =ABS(D10) -> 0.60486723 | J10: =IF(B10>$P$4,1,0) -> 0 | K10: =IF(F10>$P$6,1,0) -> 0 | L10: =IF(G10>$P$9,1,0) -> 0 | M10: =IF(ABS(H10)>$P$8,1,0) -> 0
A11: =ROW()-1 -> 10 | B11: =SUMPRODUCT(MMULT('Analysis Data'!N11:U11,'Final Model'!$B$59:$I$66),'Analysis Data'!N11:U11) -> 0.0018286773 | C11: ='Residual Diagnostics'!F11 -> 6.2204462 | D11: =C11/('Final Model'!$B$21*SQRT(1-B11)) -> 0.12698114 | E11: =D11*SQRT(('Final Model'!$B$24-1)/('Final Model'!$B$24-D11^2)) -> 0.1269358 | F11: =D11^2/($P$3+1)*B11/(1-B11) -> 3.6924993e-06 | G11: =($P$2-1)*(B11-1/$P$2) -> 1.5334396 | H11: =E11*SQRT(B11/(1-B11)) -> 0.0054331301 | I11: =ABS(D11) -> 0.12698114 | J11: =IF(B11>$P$4,1,0) -> 0 | K11: =IF(F11>$P$6,1,0) -> 0 | L11: =IF(G11>$P$9,1,0) -> 0 | M11: =IF(ABS(H11)>$P$8,1,0) -> 0 | O11: FLAG COUNTS
A12: =ROW()-1 -> 11 | B12: =SUMPRODUCT(MMULT('Analysis Data'!N12:U12,'Final Model'!$B$59:$I$66),'Analysis Data'!N12:U12) -> 0.0017022006 | C12: ='Residual Diagnostics'!F12 -> -59.636256 | D12: =C12/('Final Model'!$B$21*SQRT(1-B12)) -> -1.2173081 | E12: =D12*SQRT(('Final Model'!$B$24-1)/('Final Model'!$B$24-D12^2)) -> -1.2175212 | F12: =D12^2/($P$3+1)*B12/(1-B12) -> 0.00031583604 | G12: =($P$2-1)*(B12-1/$P$2) -> 1.3582694 | H12: =E12*SQRT(B12/(1-B12)) -> -0.050274971 | I12: =ABS(D12) -> 1.2173081 | J12: =IF(B12>$P$4,1,0) -> 0 | K12: =IF(F12>$P$6,1,0) -> 0 | L12: =IF(G12>$P$9,1,0) -> 0 | M12: =IF(ABS(H12)>$P$8,1,0) -> 0 | O12: Leverage > 2(k+1)/n | P12: =SUM(J2:J1387) -> 171
A13: =ROW()-1 -> 12 | B13: =SUMPRODUCT(MMULT('Analysis Data'!N13:U13,'Final Model'!$B$59:$I$66),'Analysis Data'!N13:U13) -> 0.002457571 | C13: ='Residual Diagnostics'!F13 -> -36.924001 | D13: =C13/('Final Model'!$B$21*SQRT(1-B13)) -> -0.75398599 | E13: =D13*SQRT(('Final Model'!$B$24-1)/('Final Model'!$B$24-D13^2)) -> -0.75386788 | F13: =D13^2/($P$3+1)*B13/(1-B13) -> 0.00017506981 | G13: =($P$2-1)*(B13-1/$P$2) -> 2.4044573 | H13: =E13*SQRT(B13/(1-B13)) -> -0.037418174 | I13: =ABS(D13) -> 0.75398599 | J13: =IF(B13>$P$4,1,0) -> 0 | K13: =IF(F13>$P$6,1,0) -> 0 | L13: =IF(G13>$P$9,1,0) -> 0 | M13: =IF(ABS(H13)>$P$8,1,0) -> 0 | O13: Leverage > 3(k+1)/n | P13: =COUNTIF(B2:B1387,">"&P5) -> 63
A14: =ROW()-1 -> 13 | B14: =SUMPRODUCT(MMULT('Analysis Data'!N14:U14,'Final Model'!$B$59:$I$66),'Analysis Data'!N14:U14) -> 0.0020154729 | C14: ='Residual Diagnostics'!F14 -> 54.432089 | D14: =C14/('Final Model'!$B$21*SQRT(1-B14)) -> 1.1112539 | E14: =D14*SQRT(('Final Model'!$B$24-1)/('Final Model'!$B$24-D14^2)) -> 1.1113487 | F14: =D14^2/($P$3+1)*B14/(1-B14) -> 0.00031173802 | G14: =($P$2-1)*(B14-1/$P$2) -> 1.7921515 | H14: =E14*SQRT(B14/(1-B14)) -> 0.049943265 | I14: =ABS(D14) -> 1.1112539 | J14: =IF(B14>$P$4,1,0) -> 0 | K14: =IF(F14>$P$6,1,0) -> 0 | L14: =IF(G14>$P$9,1,0) -> 0 | M14: =IF(ABS(H14)>$P$8,1,0) -> 0 | O14: Cook's D > 4/(n-k-1) | P14: =SUM(K2:K1387) -> 76
A15: =ROW()-1 -> 14 | B15: =SUMPRODUCT(MMULT('Analysis Data'!N15:U15,'Final Model'!$B$59:$I$66),'Analysis Data'!N15:U15) -> 0.0017506418 | C15: ='Residual Diagnostics'!F15 -> -50.984372 | D15: =C15/('Final Model'!$B$21*SQRT(1-B15)) -> -1.0407293 | E15: =D15*SQRT(('Final Model'!$B$24-1)/('Final Model'!$B$24-D15^2)) -> -1.0407607 | F15: =D15^2/($P$3+1)*B15/(1-B15) -> 0.00023743449 | G15: =($P$2-1)*(B15-1/$P$2) -> 1.4253604 | H15: =E15*SQRT(B15/(1-B15)) -> -0.043584293 | I15: =ABS(D15) -> 1.0407293 | J15: =IF(B15>$P$4,1,0) -> 0 | K15: =IF(F15>$P$6,1,0) -> 0 | L15: =IF(G15>$P$9,1,0) -> 0 | M15: =IF(ABS(H15)>$P$8,1,0) -> 0 | O15: Cook's D > 1 | P15: =COUNTIF(F2:F1387,">1") -> 0
A16: =ROW()-1 -> 15 | B16: =SUMPRODUCT(MMULT('Analysis Data'!N16:U16,'Final Model'!$B$59:$I$66),'Analysis Data'!N16:U16) -> 0.0017506418 | C16: ='Residual Diagnostics'!F16 -> -34.44372 | D16: =C16/('Final Model'!$B$21*SQRT(1-B16)) -> -0.7030897 | E16: =D16*SQRT(('Final Model'!$B$24-1)/('Final Model'!$B$24-D16^2)) -> -0.70296065 | F16: =D16^2/($P$3+1)*B16/(1-B16) -> 0.00010836518 | G16: =($P$2-1)*(B16-1/$P$2) -> 1.4253604 | H16: =E16*SQRT(B16/(1-B16)) -> -0.029438125 | I16: =ABS(D16) -> 0.7030897 | J16: =IF(B16>$P$4,1,0) -> 0 | K16: =IF(F16>$P$6,1,0) -> 0 | L16: =IF(G16>$P$9,1,0) -> 0 | M16: =IF(ABS(H16)>$P$8,1,0) -> 0 | O16: Mahalanobis > 10 | P16: =SUM(L2:L1387) -> 246
A17: =ROW()-1 -> 16 | B17: =SUMPRODUCT(MMULT('Analysis Data'!N17:U17,'Final Model'!$B$59:$I$66),'Analysis Data'!N17:U17) -> 0.0017328935 | C17: ='Residual Diagnostics'!F17 -> 68.037096 | D17: =C17/('Final Model'!$B$21*SQRT(1-B17)) -> 1.3888092 | E17: =D17*SQRT(('Final Model'!$B$24-1)/('Final Model'!$B$24-D17^2)) -> 1.3892779 | F17: =D17^2/($P$3+1)*B17/(1-B17) -> 0.00041852396 | G17: =($P$2-1)*(B17-1/$P$2) -> 1.4007791 | H17: =E17*SQRT(B17/(1-B17)) -> 0.057883086 | I17: =ABS(D17) -> 1.3888092 | J17: =IF(B17>$P$4,1,0) -> 0 | K17: =IF(F17>$P$6,1,0) -> 0 | L17: =IF(G17>$P$9,1,0) -> 0 | M17: =IF(ABS(H17)>$P$8,1,0) -> 0 | O17: |DFFITS| > threshold | P17: =SUM(M2:M1387) -> 76
A18: =ROW()-1 -> 17 | B18: =SUMPRODUCT(MMULT('Analysis Data'!N18:U18,'Final Model'!$B$59:$I$66),'Analysis Data'!N18:U18) -> 0.0024346989 | C18: ='Residual Diagnostics'!F18 -> -50.055694 | D18: =C18/('Final Model'!$B$21*SQRT(1-B18)) -> -1.0221227 | E18: =D18*SQRT(('Final Model'!$B$24-1)/('Final Model'!$B$24-D18^2)) -> -1.0221393 | F18: =D18^2/($P$3+1)*B18/(1-B18) -> 0.00031872783 | G18: =($P$2-1)*(B18-1/$P$2) -> 2.3727794 | H18: =E18*SQRT(B18/(1-B18)) -> -0.050496589 | I18: =ABS(D18) -> 1.0221227 | J18: =IF(B18>$P$4,1,0) -> 0 | K18: =IF(F18>$P$6,1,0) -> 0 | L18: =IF(G18>$P$9,1,0) -> 0 | M18: =IF(ABS(H18)>$P$8,1,0) -> 0 | O18: Max Cook D | P18: =MAX(F2:F1387) -> 0.023102122
A19: =ROW()-1 -> 18 | B19: =SUMPRODUCT(MMULT('Analysis Data'!N19:U19,'Final Model'!$B$59:$I$66),'Analysis Data'!N19:U19) -> 0.0023533201 | C19: ='Residual Diagnostics'!F19 -> -42.6275 | D19: =C19/('Final Model'!$B$21*SQRT(1-B19)) -> -0.87040562 | E19: =D19*SQRT(('Final Model'!$B$24-1)/('Final Model'!$B$24-D19^2)) -> -0.87032902 | F19: =D19^2/($P$3+1)*B19/(1-B19) -> 0.00022338686 | G19: =($P$2-1)*(B19-1/$P$2) -> 2.2600698 | H19: =E19*SQRT(B19/(1-B19)) -> -0.042270325 | I19: =ABS(D19) -> 0.87040562 | J19: =IF(B19>$P$4,1,0) -> 0 | K19: =IF(F19>$P$6,1,0) -> 0 | L19: =IF(G19>$P$9,1,0) -> 0 | M19: =IF(ABS(H19)>$P$8,1,0) -> 0 | O19: Max leverage | P19: =MAX(B2:B1387) -> 0.071905895
A20: =ROW()-1 -> 19 | B20: =SUMPRODUCT(MMULT('Analysis Data'!N20:U20,'Final Model'!$B$59:$I$66),'Analysis Data'!N20:U20) -> 0.0023533201 | C20: ='Residual Diagnostics'!F20 -> 126.40203 | D20: =C20/('Final Model'!$B$21*SQRT(1-B20)) -> 2.5809874 | E20: =D20*SQRT(('Final Model'!$B$24-1)/('Final Model'!$B$24-D20^2)) -> 2.5863097 | F20: =D20^2/($P$3+1)*B20/(1-B20) -> 0.0019642015 | G20: =($P$2-1)*(B20-1/$P$2) -> 2.2600698 | H20: =E20*SQRT(B20/(1-B20)) -> 0.12561244 | I20: =ABS(D20) -> 2.5809874 | J20: =IF(B20>$P$4,1,0) -> 0 | K20: =IF(F20>$P$6,1,0) -> 0 | L20: =IF(G20>$P$9,1,0) -> 0 | M20: =IF(ABS(H20)>$P$8,1,0) -> 0
A21: =ROW()-1 -> 20 | B21: =SUMPRODUCT(MMULT('Analysis Data'!N21:U21,'Final Model'!$B$59:$I$66),'Analysis Data'!N21:U21) -> 0.0023533201 | C21: ='Residual Diagnostics'!F21 -> -77.072762 | D21: =C21/('Final Model'!$B$21*SQRT(1-B21)) -> -1.5737392 | E21: =D21*SQRT(('Final Model'!$B$24-1)/('Final Model'!$B$24-D21^2)) -> -1.5745837 | F21: =D21^2/($P$3+1)*B21/(1-B21) -> 0.00073026376 | G21: =($P$2-1)*(B21-1/$P$2) -> 2.2600698 | H21: =E21*SQRT(B21/(1-B21)) -> -0.076474713 | I21: =ABS(D21) -> 1.5737392 | J21: =IF(B21>$P$4,1,0) -> 0 | K21: =IF(F21>$P$6,1,0) -> 0 | L21: =IF(G21>$P$9,1,0) -> 0 | M21: =IF(ABS(H21)>$P$8,1,0) -> 0 | O21: Reading: no observation has Cook D near 1 (max 0.023). The flagged leverage / Mahalanobis points are structural: all 36 Endcap-with-Rep rows (a rare cell) exceed 3(k+1)/n. They are legitimate observations that define the interaction. See Outliers sheet and report Section 5 for the sensitivity analysis.
A22: =ROW()-1 -> 21 | B22: =SUMPRODUCT(MMULT('Analysis Data'!N22:U22,'Final Model'!$B$59:$I$66),'Analysis Data'!N22:U22) -> 0.0017022006 | C22: ='Residual Diagnostics'!F22 -> 52.192918 | D22: =C22/('Final Model'!$B$21*SQRT(1-B22)) -> 1.0653731 | E22: =D22*SQRT(('Final Model'!$B$24-1)/('Final Model'!$B$24-D22^2)) -> 1.0654253 | F22: =D22^2/($P$3+1)*B22/(1-B22) -> 0.00024191573 | G22: =($P$2-1)*(B22-1/$P$2) -> 1.3582694 | H22: =E22*SQRT(B22/(1-B22)) -> 0.043994495 | I22: =ABS(D22) -> 1.0653731 | J22: =IF(B22>$P$4,1,0) -> 0 | K22: =IF(F22>$P$6,1,0) -> 0 | L22: =IF(G22>$P$9,1,0) -> 0 | M22: =IF(ABS(H22)>$P$8,1,0) -> 0
A23: =ROW()-1 -> 22 | B23: =SUMPRODUCT(MMULT('Analysis Data'!N23:U23,'Final Model'!$B$59:$I$66),'Analysis Data'!N23:U23) -> 0.0017022006 | C23: ='Residual Diagnostics'!F23 -> 1.9925421 | D23: =C23/('Final Model'!$B$21*SQRT(1-B23)) -> 0.0406722 | E23: =D23*SQRT(('Final Model'!$B$24-1)/('Final Model'!$B$24-D23^2)) -> 0.040657464 | F23: =D23^2/($P$3+1)*B23/(1-B23) -> 3.5257861e-07 | G23: =($P$2-1)*(B23-1/$P$2) -> 1.3582694 | H23: =E23*SQRT(B23/(1-B23)) -> 0.0016788643 | I23: =ABS(D23) -> 0.0406722 | J23: =IF(B23>$P$4,1,0) -> 0 | K23: =IF(F23>$P$6,1,0) -> 0 | L23: =IF(G23>$P$9,1,0) -> 0 | M23: =IF(ABS(H23)>$P$8,1,0) -> 0
A24: =ROW()-1 -> 23 | B24: =SUMPRODUCT(MMULT('Analysis Data'!N24:U24,'Final Model'!$B$59:$I$66),'Analysis Data'!N24:U24) -> 0.0029657184 | C24: ='Residual Diagnostics'!F24 -> -27.097237 | D24: =C24/('Final Model'!$B$21*SQRT(1-B24)) -> -0.55346502 | E24: =D24*SQRT(('Final Model'!$B$24-1)/('Final Model'!$B$24-D24^2)) -> -0.55332567 | F24: =D24^2/($P$3+1)*B24/(1-B24) -> 0.00011389645 | G24: =($P$2-1)*(B24-1/$P$2) -> 3.1082415 | H24: =E24*SQRT(B24/(1-B24)) -> -0.030178019 | I24: =ABS(D24) -> 0.55346502 | J24: =IF(B24>$P$4,1,0) -> 0 | K24: =IF(F24>$P$6,1,0) -> 0 | L24: =IF(G24>$P$9,1,0) -> 0 | M24: =IF(ABS(H24)>$P$8,1,0) -> 0
A25: =ROW()-1 -> 24 | B25: =SUMPRODUCT(MMULT('Analysis Data'!N25:U25,'Final Model'!$B$59:$I$66),'Analysis Data'!N25:U25) -> 0.0018725411 | C25: ='Residual Diagnostics'!F25 -> 29.126093 | D25: =C25/('Final Model'!$B$21*SQRT(1-B25)) -> 0.59457882 | E25: =D25*SQRT(('Final Model'!$B$24-1)/('Final Model'!$B$24-D25^2)) -> 0.5944393 | F25: =D25^2/($P$3+1)*B25/(1-B25) -> 8.2903763e-05 | G25: =($P$2-1)*(B25-1/$P$2) -> 1.594191 | H25: =E25*SQRT(B25/(1-B25)) -> 0.025747211 | I25: =ABS(D25) -> 0.59457882 | J25: =IF(B25>$P$4,1,0) -> 0 | K25: =IF(F25>$P$6,1,0) -> 0 | L25: =IF(G25>$P$9,1,0) -> 0 | M25: =IF(ABS(H25)>$P$8,1,0) -> 0
A26: =ROW()-1 -> 25 | B26: =SUMPRODUCT(MMULT('Analysis Data'!N26:U26,'Final Model'!$B$59:$I$66),'Analysis Data'!N26:U26) -> 0.001767518 | C26: ='Residual Diagnostics'!F26 -> 23.507915 | D26: =C26/('Final Model'!$B$21*SQRT(1-B26)) -> 0.47986433 | E26: =D26*SQRT(('Final Model'!$B$24-1)/('Final Model'!$B$24-D26^2)) -> 0.47973026 | F26: =D26^2/($P$3+1)*B26/(1-B26) -> 5.0965828e-05 | G26: =($P$2-1)*(B26-1/$P$2) -> 1.4487339 | H26: =E26*SQRT(B26/(1-B26)) -> 0.0201866 | I26: =ABS(D26) -> 0.47986433 | J26: =IF(B26>$P$4,1,0) -> 0 | K26: =IF(F26>$P$6,1,0) -> 0 | L26: =IF(G26>$P$9,1,0) -> 0 | M26: =IF(ABS(H26)>$P$8,1,0) -> 0
A27: =ROW()-1 -> 26 | B27: =SUMPRODUCT(MMULT('Analysis Data'!N27:U27,'Final Model'!$B$59:$I$66),'Analysis Data'!N27:U27) -> 0.0016884109 | C27: ='Residual Diagnostics'!F27 -> 15.108482 | D27: =C27/('Final Model'!$B$21*SQRT(1-B27)) -> 0.30839547 | E27: =D27*SQRT(('Final Model'!$B$24-1)/('Final Model'!$B$24-D27^2)) -> 0.30829419 | F27: =D27^2/($P$3+1)*B27/(1-B27) -> 2.0106572e-05 | G27: =($P$2-1)*(B27-1/$P$2) -> 1.3391706 | H27: =E27*SQRT(B27/(1-B27)) -> 0.012678602 | I27: =ABS(D27) -> 0.30839547 | J27: =IF(B27>$P$4,1,0) -> 0 | K27: =IF(F27>$P$6,1,0) -> 0 | L27: =IF(G27>$P$9,1,0) -> 0 | M27: =IF(ABS(H27)>$P$8,1,0) -> 0
A28: =ROW()-1 -> 27 | B28: =SUMPRODUCT(MMULT('Analysis Data'!N28:U28,'Final Model'!$B$59:$I$66),'Analysis Data'!N28:U28) -> 0.001722684 | C28: ='Residual Diagnostics'!F28 -> -55.72535 | D28: =C28/('Final Model'!$B$21*SQRT(1-B28)) -> -1.1374895 | E28: =D28*SQRT(('Final Model'!$B$24-1)/('Final Model'!$B$24-D28^2)) -> -1.1376109 | F28: =D28^2/($P$3+1)*B28/(1-B28) -> 0.00027909963 | G28: =($P$2-1)*(B28-1/$P$2) -> 1.3866389 | H28: =E28*SQRT(B28/(1-B28)) -> -0.047257525 | I28: =ABS(D28) -> 1.1374895 | J28: =IF(B28>$P$4,1,0) -> 0 | K28: =IF(F28>$P$6,1,0) -> 0 | L28: =IF(G28>$P$9,1,0) -> 0 | M28: =IF(ABS(H28)>$P$8,1,0) -> 0
A29: =ROW()-1 -> 28 | B29: =SUMPRODUCT(MMULT('Analysis Data'!N29:U29,'Final Model'!$B$59:$I$66),'Analysis Data'!N29:U29) -> 0.059909419 | C29: ='Residual Diagnostics'!F29 -> 19.979089 | D29: =C29/('Final Model'!$B$21*SQRT(1-B29)) -> 0.42025322 | E29: =D29*SQRT(('Final Model'!$B$24-1)/('Final Model'!$B$24-D29^2)) -> 0.42012763 | F29: =D29^2/($P$3+1)*B29/(1-B29) -> 0.0014068815 | G29: =($P$2-1)*(B29-1/$P$2) -> 81.975267 | H29: =E29*SQRT(B29/(1-B29)) -> 0.10605812 | I29: =ABS(D29) -> 0.42025322 | J29: =IF(B29>$P$4,1,0) -> 1 | K29: =IF(F29>$P$6,1,0) -> 0 | L29: =IF(G29>$P$9,1,0) -> 1 | M29: =IF(ABS(H29)>$P$8,1,0) -> 0
A30: =ROW()-1 -> 29 | B30: =SUMPRODUCT(MMULT('Analysis Data'!N30:U30,'Final Model'!$B$59:$I$66),'Analysis Data'!N30:U30) -> 0.059761149 | C30: ='Residual Diagnostics'!F30 -> 36.939722 | D30: =C30/('Final Model'!$B$21*SQRT(1-B30)) -> 0.77695299 | E30: =D30*SQRT(('Final Model'!$B$24-1)/('Final Model'!$B$24-D30^2)) -> 0.77684119 | F30: =D30^2/($P$3+1)*B30/(1-B30) -> 0.0047960118 | G30: =($P$2-1)*(B30-1/$P$2) -> 81.769913 | H30: =E30*SQRT(B30/(1-B30)) -> 0.19584957 | I30: =ABS(D30) -> 0.77695299 | J30: =IF(B30>$P$4,1,0) -> 1 | K30: =IF(F30>$P$6,1,0) -> 1 | L30: =IF(G30>$P$9,1,0) -> 1 | M30: =IF(ABS(H30)>$P$8,1,0) -> 1
A31: =ROW()-1 -> 30 | B31: =SUMPRODUCT(MMULT('Analysis Data'!N31:U31,'Final Model'!$B$59:$I$66),'Analysis Data'!N31:U31) -> 0.059855839 | C31: ='Residual Diagnostics'!F31 -> -40.709062 | D31: =C31/('Final Model'!$B$21*SQRT(1-B31)) -> -0.85627661 | E31: =D31*SQRT(('Final Model'!$B$24-1)/('Final Model'!$B$24-D31^2)) -> -0.85619367 | F31: =D31^2/($P$3+1)*B31/(1-B31) -> 0.0058351261 | G31: =($P$2-1)*(B31-1/$P$2) -> 81.901058 | H31: =E31*SQRT(B31/(1-B31)) -> -0.21603696 | I31: =ABS(D31) -> 0.85627661 | J31: =IF(B31>$P$4,1,0) -> 1 | K31: =IF(F31>$P$6,1,0) -> 1 | L31: =IF(G31>$P$9,1,0) -> 1 | M31: =IF(ABS(H31)>$P$8,1,0) -> 1
A32: =ROW()-1 -> 31 | B32: =SUMPRODUCT(MMULT('Analysis Data'!N32:U32,'Final Model'!$B$59:$I$66),'Analysis Data'!N32:U32) -> 0.06033377 | C32: ='Residual Diagnostics'!F32 -> -71.020428 | D32: =C32/('Final Model'!$B$21*SQRT(1-B32)) -> -1.4942274 | E32: =D32*SQRT(('Final Model'!$B$24-1)/('Final Model'!$B$24-D32^2)) -> -1.4948966 | F32: =D32^2/($P$3+1)*B32/(1-B32) -> 0.017919679 | G32: =($P$2-1)*(B32-1/$P$2) -> 82.562993 | H32: =E32*SQRT(B32/(1-B32)) -> -0.37879531 | I32: =ABS(D32) -> 1.4942274 | J32: =IF(B32>$P$4,1,0) -> 1 | K32: =IF(F32>$P$6,1,0) -> 1 | L32: =IF(G32>$P$9,1,0) -> 1 | M32: =IF(ABS(H32)>$P$8,1,0) -> 1
A33: =ROW()-1 -> 32 | B33: =SUMPRODUCT(MMULT('Analysis Data'!N33:U33,'Final Model'!$B$59:$I$66),'Analysis Data'!N33:U33) -> 0.05923687 | C33: ='Residual Diagnostics'!F33 -> 12.642046 | D33: =C33/('Final Model'!$B$21*SQRT(1-B33)) -> 0.26582598 | E33: =D33*SQRT(('Final Model'!$B$24-1)/('Final Model'!$B$24-D33^2)) -> 0.26573632 | F33: =D33^2/($P$3+1)*B33/(1-B33) -> 0.00055618167 | G33: =($P$2-1)*(B33-1/$P$2) -> 81.043787 | H33: =E33*SQRT(B33/(1-B33)) -> 0.066681725 | I33: =ABS(D33) -> 0.26582598 | J33: =IF(B33>$P$4,1,0) -> 1 | K33: =IF(F33>$P$6,1,0) -> 0 | L33: =IF(G33>$P$9,1,0) -> 1 | M33: =IF(ABS(H33)>$P$8,1,0) -> 0
... A1387: =ROW()-1 -> 1386 | B1387: =SUMPRODUCT(MMULT('Analysis Data'!N1387:U1387,'Final Model'!$B$59:$I$66),'Analysis Data'!N1387:U1387) -> 0.0019204962 | C1387: ='Residual Diagnostics'!F1387 -> -17.222456 | D1387: =C1387/('Final Model'!$B$21*SQRT(1-B1387)) -> -0.35158693 | E1387: =D1387*SQRT(('Final Model'!$B$24-1)/('Final Model'!$B$24-D1387^2)) -> -0.3514751 | F1387: =D1387^2/($P$3+1)*B1387/(1-B1387) -> 2.9731975e-05 | G1387: =($P$2-1)*(B1387-1/$P$2) -> 1.6606087 | H1387: =E1387*SQRT(B1387/(1-B1387)) -> -0.015417669 | I1387: =ABS(D1387) -> 0.35158693 | J1387: =IF(B1387>$P$4,1,0) -> 0 | K1387: =IF(F1387>$P$6,1,0) -> 0 | L1387: =IF(G1387>$P$9,1,0) -> 0 | M1387: =IF(ABS(H1387)>$P$8,1,0) -> 0

Sheet Model Comparison
A1: MODEL COMPARISON (all values formula-linked to the model sheets)
A3: Model | B3: Variables | C3: R² | D3: Adj R² | E3: Std error | F3: F | G3: Model p-value | H3: DW (Python) | I3: Key finding
A4: 0A | B4: Sales ~ Price | C4: ='Baseline Models'!$B$21 -> 0.00035451571 | D4: ='Baseline Models'!$B$22 -> -0.00036777149 | E4: ='Baseline Models'!$B$23 -> 111.01914 | F4: ='Baseline Models'!$B$27 -> 0.49082375 | G4: ='Baseline Models'!$B$28 -> 0.48367784 | H4: 0.79045152 | I4: Price alone explains nothing (R² ≈ 0)
A5: 0B | B5: Sales ~ Demo | C5: ='Baseline Models'!$B$58 -> 0.10847672 | D5: ='Baseline Models'!$B$59 -> 0.10783256 | E5: ='Baseline Models'!$B$60 -> 104.84342 | F5: ='Baseline Models'!$B$64 -> 168.39918 | G5: ='Baseline Models'!$B$65 -> 2.0086572e-36 | H5: 0.87145022 | I5: Current demo alone: R² 0.11
A6: 0C | B6: Sales ~ Endcap | C6: ='Baseline Models'!$B$95 -> 0.35190494 | D6: ='Baseline Models'!$B$96 -> 0.35143666 | E6: ='Baseline Models'!$B$97 -> 89.391086 | F6: ='Baseline Models'!$B$101 -> 751.48918 | G6: ='Baseline Models'!$B$102 -> 1.6274053e-132 | H6: 0.87965966 | I6: Endcap alone: R² 0.35 (unadjusted)
A7: Model 1 (Full MLR) | B7: Price, Rep, Endcap, Demo, D13, D45, Natural, Fitness | C7: ='Full MLR'!$B$19 -> 0.67263527 | D7: ='Full MLR'!$B$20 -> 0.67073336 | E7: ='Full MLR'!$B$21 -> 63.693025 | F7: ='Full MLR'!$B$25 -> 353.66468 | G7: ='Full MLR'!$B$26 -> 0 | H7: 1.3786891 | I7: Full MLR: Natural & Fitness insignificant; DW 1.38 and strong heteroscedasticity (missing interaction)
A8: Model 2 (selected, no interaction) | B8: Price, Rep, Endcap, Demo, D13, D45 | C8: ='Variable Selection'!$B$19 -> 0.67226502 | D8: ='Variable Selection'!$B$20 -> 0.67083905 | E8: ='Variable Selection'!$B$21 -> 63.682803 | F8: ='Variable Selection'!$B$25 -> 471.44467 | G8: ='Variable Selection'!$B$26 -> 0 | H8: 1.3775506 | I8: Natural & Fitness dropped (partial F p=0.46); same fit as Model 1
A9: Model 3 (Full + interaction) | B9: Model 1 + Endcap x Rep | C9: ='Interaction Analysis'!$B$19 -> 0.8058684 | D9: ='Interaction Analysis'!$B$20 -> 0.80459864 | E9: ='Interaction Analysis'!$B$21 -> 49.06613 | F9: ='Interaction Analysis'!$B$25 -> 634.66392 | G9: ='Interaction Analysis'!$B$26 -> 0 | H9: 2.0919497 | I9: Interaction adds ~13.3 pts of R²; DW 2.09
A10: FINAL MODEL | B10: Price, Rep, Endcap, Demo, D13, D45, Endcap x Rep | C10: ='Final Model'!$B$19 -> 0.80585644 | D10: ='Final Model'!$B$20 -> 0.80487022 | E10: ='Final Model'!$B$21 -> 49.032021 | F10: ='Final Model'!$B$25 -> 817.12003 | G10: ='Final Model'!$B$26 -> 0 | H10: 2.0916164 | I10: PREFERRED FINAL MODEL: best adj R² among models that keep hierarchy; all retained terms significant except Endcap main (kept for interpretation)
A11: Final w/o Endcap main | B11: Price, Rep, Demo, D13, D45, Endcap x Rep | C11: ='Interaction Analysis'!$B$64 -> 0.80585606 | D11: ='Interaction Analysis'!$B$65 -> 0.80501135 | E11: ='Interaction Analysis'!$B$66 -> 49.014286 | F11: ='Interaction Analysis'!$B$70 -> 953.99624 | G11: ='Interaction Analysis'!$B$71 -> 0 | H11: 2.0917447 | I11: Endcap main effect dropped: identical fit; alternative parsimonious form
A13: Models are compared on adjusted R², partial F-tests, diagnostics (autocorrelation and heteroscedasticity disappear once the interaction is included), parsimony and business logic - not on R² alone.
A15: Sensitivity of key coefficients (Python / statsmodels, static values)
A16: Specification | B16: Price | C16: Sales Rep | D16: Endcap | E16: Demo | F16: Demo1-3 | G16: Demo4-5 | H16: Endcap x Rep
A17: Final (baseline) | B17: -22.066351 | C17: 59.461761 | D17: 0.62038277 | E17: 106.7527 | F17: 73.369792 | G17: 74.551964 | H17: 453.8033
A18: Excl. Cook>4/(n-k-1) or |t|>3 | B18: -23.132797 | C18: 60.104772 | D18: 4.5769218 | E18: 107.45903 | F18: 73.364865 | G18: 79.294096 | H18: 452.83969
A19: Excl. |stud. resid|>3 | B19: -21.556044 | C19: 59.23112 | D19: 0.45285888 | E19: 108.63696 | F19: 74.12815 | G19: 74.353713 | H19: 453.61925
A20: Restricted: no Endcap main effect | B20: -22.064787 | C20: 59.44196 | D20: - | E20: 106.75871 | F20: 73.377352 | G20: 74.561374 | H20: 454.42284
A21: + Region dummies | B21: -21.731137 | C21: 39.466342 | D21: -1.1611319 | E21: 106.41765 | F21: 72.632312 | G21: 72.587618 | H21: 457.49816
A22: + Week dummies | B22: -21.666527 | C22: 59.534017 | D22: 0.23073983 | E22: 104.05329 | F22: 73.174524 | G22: 74.285487 | H22: 453.12471
A23: + Store dummies (126) | B23: -26.290574 | C23: 38.42499 | D23: 10.119287 | E23: 107.07446 | F23: 72.120444 | G23: 72.764915 | H23: 449.48258
A25: Cluster-robust (by store) standard errors for the final model (Python, static): coefficients unchanged; SEs of Price, Demo4-5, Endcap, Endcap x Rep fall or stay similar; no conclusion changes.
A26: Variable | B26: Coef | C26: Cluster SE | D26: p-value
A27: const | B27: 276.57349 | C27: 10.349096 | D27: 2.4498919e-157
A28: Price | B28: -22.066351 | C28: 2.6073917 | D28: 2.6058957e-17
A29: Rep | B29: 59.461761 | C29: 2.9751238 | D29: 7.2453115e-89
A30: Endcap | B30: 0.62038277 | C30: 6.9397545 | D30: 0.92876761
A31: Demo | B31: 106.7527 | C31: 6.1381292 | D31: 9.5310694e-68
A32: D13 | B32: 73.369792 | C32: 3.1550643 | D32: 1.2776611e-119
A33: D45 | B33: 74.551964 | C33: 4.7156897 | D33: 2.6824197e-56
A34: EndRep | B34: 453.8033 | C34: 8.7283366 | D34: 0

Sheet Excel vs JASP
A1: EXCEL vs JASP vs INDEPENDENT CHECK (final model)
A2: JASP WAS NOT EXECUTED: no JASP installation or integration was available in the environment used to build this workbook, so no JASP output exists and none is claimed. A JASP-ready CSV and click-by-click specification are provided in the Supplementary folder. Fill column C after running the model in JASP. The independent check (column D) is a separate statsmodels (Python) OLS fit of the same model on the same data.
A4: Statistic | B4: Excel (this workbook) | C4: JASP (to be filled after running JASP) | D4: Independent check: Python statsmodels | E4: Difference Excel - Python | F4: Match (|diff| < 1e-6)? | G4: Excel - JASP (auto once C filled)
A5: R² | B5: ='Final Model'!$B$19 -> 0.80585644 | D5: 0.80585644 | E5: =B5-D5 -> 0 | F5: =IF(ABS(E5)<0.000001,"Yes","CHECK") -> Yes | G5: =IF(C5="","not run",B5-C5) -> not run
A6: Adjusted R² | B6: ='Final Model'!$B$20 -> 0.80487022 | D6: 0.80487022 | E6: =B6-D6 -> 0 | F6: =IF(ABS(E6)<0.000001,"Yes","CHECK") -> Yes | G6: =IF(C6="","not run",B6-C6) -> not run
A7: F-statistic | B7: ='Final Model'!$B$25 -> 817.12003 | D7: 817.12003 | E7: =B7-D7 -> 0 | F7: =IF(ABS(E7)<0.000001,"Yes","CHECK") -> Yes | G7: =IF(C7="","not run",B7-C7) -> not run
A8: Model p-value | B8: ='Final Model'!$B$26 -> 0 | D8: 0 | E8: =B8-D8 -> 0 | F8: =IF(ABS(E8)<0.000001,"Yes","CHECK") -> Yes | G8: =IF(C8="","not run",B8-C8) -> not run
A9: Standard error | B9: ='Final Model'!$B$21 -> 49.032021 | D9: 49.032021 | E9: =B9-D9 -> 0 | F9: =IF(ABS(E9)<0.000001,"Yes","CHECK") -> Yes | G9: =IF(C9="","not run",B9-C9) -> not run
A10: Intercept | B10: ='Final Model'!$B$33 -> 276.57349 | D10: 276.57349 | E10: =B10-D10 -> 0 | F10: =IF(ABS(E10)<0.000001,"Yes","CHECK") -> Yes | G10: =IF(C10="","not run",B10-C10) -> not run
A11: Price coefficient | B11: ='Final Model'!$B$34 -> -22.066351 | D11: -22.066351 | E11: =B11-D11 -> 0 | F11: =IF(ABS(E11)<0.000001,"Yes","CHECK") -> Yes | G11: =IF(C11="","not run",B11-C11) -> not run
A12: Sales Rep coefficient | B12: ='Final Model'!$B$35 -> 59.461761 | D12: 59.461761 | E12: =B12-D12 -> 0 | F12: =IF(ABS(E12)<0.000001,"Yes","CHECK") -> Yes | G12: =IF(C12="","not run",B12-C12) -> not run
A13: Endcap coefficient | B13: ='Final Model'!$B$36 -> 0.62038277 | D13: 0.62038277 | E13: =B13-D13 -> 4.2088555e-13 | F13: =IF(ABS(E13)<0.000001,"Yes","CHECK") -> Yes | G13: =IF(C13="","not run",B13-C13) -> not run
A14: Demo coefficient | B14: ='Final Model'!$B$37 -> 106.7527 | D14: 106.7527 | E14: =B14-D14 -> 0 | F14: =IF(ABS(E14)<0.000001,"Yes","CHECK") -> Yes | G14: =IF(C14="","not run",B14-C14) -> not run
A15: Demo1-3 coefficient | B15: ='Final Model'!$B$38 -> 73.369792 | D15: 73.369792 | E15: =B15-D15 -> 0 | F15: =IF(ABS(E15)<0.000001,"Yes","CHECK") -> Yes | G15: =IF(C15="","not run",B15-C15) -> not run
A16: Demo4-5 coefficient | B16: ='Final Model'!$B$39 -> 74.551964 | D16: 74.551964 | E16: =B16-D16 -> 0 | F16: =IF(ABS(E16)<0.000001,"Yes","CHECK") -> Yes | G16: =IF(C16="","not run",B16-C16) -> not run
A17: Endcap x Sales Rep coefficient | B17: ='Final Model'!$B$40 -> 453.8033 | D17: 453.8033 | E17: =B17-D17 -> 0 | F17: =IF(ABS(E17)<0.000001,"Yes","CHECK") -> Yes | G17: =IF(C17="","not run",B17-C17) -> not run
A18: Price SE | B18: ='Final Model'!$C$34 -> 3.0446216 | D18: 3.0446216 | E18: =B18-D18 -> 0 | F18: =IF(ABS(E18)<0.000001,"Yes","CHECK") -> Yes | G18: =IF(C18="","not run",B18-C18) -> not run
A19: Endcap x Rep SE | B19: ='Final Model'!$C$40 -> 14.73721 | D19: 14.73721 | E19: =B19-D19 -> 0 | F19: =IF(ABS(E19)<0.000001,"Yes","CHECK") -> Yes | G19: =IF(C19="","not run",B19-C19) -> not run
A20: Endcap x Rep p-value | B20: ='Final Model'!$E$40 -> 7.0499844e-159 | D20: 7.0499844e-159 | E20: =B20-D20 -> -9.8855619e-172 | F20: =IF(ABS(E20)<0.000001,"Yes","CHECK") -> Yes | G20: =IF(C20="","not run",B20-C20) -> not run
A21: Durbin-Watson | B21: ='Residual Diagnostics'!$P$6 -> 2.0916164 | D21: 2.0916164 | E21: =B21-D21 -> 0 | F21: =IF(ABS(E21)<0.000001,"Yes","CHECK") -> Yes | G21: =IF(C21="","not run",B21-C21) -> not run
A22: Max Cook D | B22: =Influence!$P$18 -> 0.023102122 | D22: 0.023102122 | E22: =B22-D22 -> -3.0184188e-16 | F22: =IF(ABS(E22)<0.000001,"Yes","CHECK") -> Yes | G22: =IF(C22="","not run",B22-C22) -> not run
A23: Max leverage | B23: =Influence!$P$19 -> 0.071905895 | D23: 0.071905895 | E23: =B23-D23 -> 0 | F23: =IF(ABS(E23)<0.000001,"Yes","CHECK") -> Yes | G23: =IF(C23="","not run",B23-C23) -> not run
A24: VIF Endcap | B24: =VIF!$B$25 -> 3.0923861 | D24: 3.0923861 | E24: =B24-D24 -> 0 | F24: =IF(ABS(E24)<0.000001,"Yes","CHECK") -> Yes | G24: =IF(C24="","not run",B24-C24) -> not run
A26: Checklist when running in JASP: same CSV (GoodBelly_JASP_Data.csv), 1,386 rows, Sales Rep/Endcap/Demo variables as scale (0/1), interaction column EndRep supplied, Method = Enter, include intercept, report R², adj R², ANOVA, coefficients with 95% CI, collinearity statistics, Durbin-Watson, residual plots, P-P plot, Cook's distance.

Sheet Final Results
A1: FINAL RESULTS - PREFERRED MODEL (all linked to Final Model sheet)
A3: Equation: Sales = b0 + b1·Price + b2·SalesRep + b3·Endcap + b4·Demo + b5·Demo1-3 + b6·Demo4-5 + b7·(Endcap×SalesRep) + e
A5: Variable | B5: Coefficient | C5: Std error | D5: t | E5: p-value | F5: Lower 95% | G5: Upper 95%
A6: Intercept | B6: ='Final Model'!$B$33 -> 276.57349 | C6: ='Final Model'!$C$33 -> 12.168591 | D6: ='Final Model'!$D$33 -> 22.728472 | E6: ='Final Model'!$E$33 -> 2.235281e-97 | F6: ='Final Model'!$F$33 -> 252.70253 | G6: ='Final Model'!$G$33 -> 300.44446
A7: Price | B7: ='Final Model'!$B$34 -> -22.066351 | C7: ='Final Model'!$C$34 -> 3.0446216 | D7: ='Final Model'!$D$34 -> -7.2476499 | E7: ='Final Model'!$E$34 -> 7.03912e-13 | F7: ='Final Model'!$F$34 -> -28.038946 | G7: ='Final Model'!$G$34 -> -16.093757
A8: Sales Rep | B8: ='Final Model'!$B$35 -> 59.461761 | C8: ='Final Model'!$C$35 -> 3.0112427 | D8: ='Final Model'!$D$35 -> 19.746585 | E8: ='Final Model'!$E$35 -> 1.2561872e-76 | F8: ='Final Model'!$F$35 -> 53.554645 | G8: ='Final Model'!$G$35 -> 65.368876
A9: Endcap | B9: ='Final Model'!$B$36 -> 0.62038277 | C9: ='Final Model'!$C$36 -> 12.076894 | D9: ='Final Model'!$D$36 -> 0.051369398 | E9: ='Final Model'!$E$36 -> 0.95903861 | F9: ='Final Model'!$F$36 -> -23.070703 | G9: ='Final Model'!$G$36 -> 24.311469
A10: Demo | B10: ='Final Model'!$B$37 -> 106.7527 | C10: ='Final Model'!$C$37 -> 5.7001901 | D10: ='Final Model'!$D$37 -> 18.727919 | E10: ='Final Model'!$E$37 -> 6.6868354e-70 | F10: ='Final Model'!$F$37 -> 95.570708 | G10: ='Final Model'!$G$37 -> 117.93469
A11: Demo1-3 | B11: ='Final Model'!$B$38 -> 73.369792 | C11: ='Final Model'!$C$38 -> 3.7659884 | D11: ='Final Model'!$D$38 -> 19.482214 | E11: ='Final Model'!$E$38 -> 7.3129943e-75 | F11: ='Final Model'!$F$38 -> 65.982102 | G11: ='Final Model'!$G$38 -> 80.757483
A12: Demo4-5 | B12: ='Final Model'!$B$39 -> 74.551964 | C12: ='Final Model'!$C$39 -> 5.0397248 | D12: ='Final Model'!$D$39 -> 14.792864 | E12: ='Final Model'!$E$39 -> 4.5661721e-46 | F12: ='Final Model'!$F$39 -> 64.665601 | G12: ='Final Model'!$G$39 -> 84.438326
A13: Endcap x Sales Rep | B13: ='Final Model'!$B$40 -> 453.8033 | C13: ='Final Model'!$C$40 -> 14.73721 | D13: ='Final Model'!$D$40 -> 30.793028 | E13: ='Final Model'!$E$40 -> 7.0499844e-159 | F13: ='Final Model'!$F$40 -> 424.89351 | G13: ='Final Model'!$G$40 -> 482.71309
A15: R² | B15: ='Final Model'!$B$19 -> 0.80585644
A16: Adjusted R² | B16: ='Final Model'!$B$20 -> 0.80487022
A17: Standard error | B17: ='Final Model'!$B$21 -> 49.032021
A18: F-statistic | B18: ='Final Model'!$B$25 -> 817.12003
A19: Model p-value | B19: ='Final Model'!$B$26 -> 0
A20: Observations | B20: ='Final Model'!$B$22 -> 1386
A22: Key answers
A23: Q1 | B23: Final model explains ≈80.6% of variation in weekly sales (adj R² 0.805). Endcap works only together with a regional Sales Rep; demos, Sales Rep and lower price all lift sales.
A24: Q2 | B24: Assumptions broadly satisfied after adding the interaction (DW 2.09, no heteroscedasticity at 5%, near-normal residuals, VIF<3.2, no influential points). The initial model without the interaction violated independence and constant variance.
A25: Q3 | B25: Yes. +107 units in demo week, +73 in weeks 1-3, +75 in weeks 4-5 (all p<0.001); lift persists at least 4-5 weeks with no measurable decay.
A26: Q4 | B26: Yes, conditionally: ≈ +454 units/store-week with a regional rep; no detectable effect without one.
A27: Q5 | B27: Added Endcap x Rep, removed Natural/Fitness; further: store/time effects, clustered SEs, experimental testing, cost data.
A28: Q6 | B28: Keep the demo program and run it with an eye on cost per lift; place endcaps where regional reps support them; collect cost/margin data; test targeting experimentally. ROI cannot be computed from supplied data.
